{"updated": "2026-07-21 21:45:22", "updated_ts": 1784637922, "scan_sec": 180, "us_open": false, "ws": true, "liq_events": 42942, "count": 35, "cols": ["흡수/이탈", "VWAP", "MTF", "오더북", "청산", "볼밴", "스퀴즈", "ATR", "레인지", "FLOW", "SURGE", "KIMCHI"], "rows": [{"sym": "ONDOUSDT", "base": "ONDO", "mark": "💎", "why": "순위권 + 강한연료 — 아직 갈 자리", "alpha": 60, "g": [["흡수/이탈", "— 0", 0], ["VWAP", "VWAP 위 지지 +4", 4], ["MTF", "BTC 대비 강세 +6", 6], ["오더북", "균형 ×1.06 +0", 0], ["청산", "↑ 숏청산 우위 $123K +5", 5], ["볼밴", "상단 접근 +6", 6], ["스퀴즈", "정상 +0", 0], ["ATR", "정상 변동성 +0", 0], ["레인지", "레인지 상단 +6", 6], ["FLOW", "Flow -1", -1], ["SURGE", "×1.84 +4", 4], ["KIMCHI", "-0.07%", 0]], "conflict": ["이미 +15%"], "onchain": null, "price": 0.4011, "p24": 15.26, "oi4": 10.5, "oi1": 0.3, "cvd": 0.812, "fr": 0.005, "atr": 2.5, "flow": -0.6, "surge": 1.84, "ret4": 2.85, "bb_pos": 0.912, "bb_squeeze": false, "bb_just_broke": false, "rng": 0.883, "kimp": -0.07, "liq": [122612.9888508, 23918.75240759, 64], "vwap_broke": false, "spot_fuel": false, "turnover": 149906101, "tradfi": false, "pinned": false, "rank": 1, "since": 1784628201, "since_min": 162}, {"sym": "TAOUSDT", "base": "TAO", "mark": "⭐", "why": "현물주도 상승 — 실제 돈", "alpha": 59, "g": [["흡수/이탈", "— 0", 0], ["VWAP", "VWAP 위 지지 +4", 4], ["MTF", "BTC 동조화 +0", 0], ["오더북", "균형 ×0.97 +0", 0], ["청산", "미미 $10K 0", 0], ["볼밴", "밴드 밖 진행중 — 이미 감 0", 0], ["스퀴즈", "정상 +0", 0], ["ATR", "낮은 변동성 +3", 3], ["레인지", "레인지 상단 +6", 6], ["FLOW", "Flow +12", 12], ["SURGE", "×1.63 +4", 4], ["KIMCHI", "+0.15%", 0]], "conflict": ["볼밴 이미 감"], "onchain": null, "price": 201.96, "p24": 3.81, "oi4": 1.9, "oi1": -0.0, "cvd": 0.672, "fr": 0.005, "atr": 1.26, "flow": 7.7, "surge": 1.63, "ret4": 1.57, "bb_pos": 1.02, "bb_squeeze": false, "bb_just_broke": false, "rng": 0.943, "kimp": 0.15, "liq": [10371.10914, 3252.14398, 12], "vwap_broke": false, "spot_fuel": true, "turnover": 72150329, "tradfi": false, "pinned": false, "rank": 2, "since": 1784635941, "since_min": 33}, {"sym": "SAMSUNGUSDT", "base": "SAMSUNG", "mark": "🟢", "why": "초입(+5%) + 연료 — 진입검토", "alpha": 74, "g": [["흡수/이탈", "ACC +14", 14], ["VWAP", "VWAP 아래 저항 -4", -4], ["MTF", "BTC 동조화 +0", 0], ["오더북", "매수벽 우위 ×1.94 +8", 8], ["청산", "청산 데이터 없음 0", 0], ["볼밴", "밴드 중단 0", 0], ["스퀴즈", "정상 +0", 0], ["ATR", "극저 변동성 +6", 6], ["레인지", "레인지 상단 +6", 6], ["FLOW", "Flow +14", 14], ["SURGE", "×0.40 +0", 0], ["KIMCHI", "—", 0]], "conflict": ["VWAP 아래"], "onchain": null, "price": 178.75, "p24": 5.05, "oi4": 5.8, "oi1": 7.3, "cvd": 0.708, "fr": 0.0, "atr": 0.78, "flow": 8.7, "surge": 0.4, "ret4": 0.33, "bb_pos": 0.787, "bb_squeeze": false, "bb_just_broke": false, "rng": 0.893, "kimp": null, "liq": null, "vwap_broke": true, "spot_fuel": false, "turnover": 101250596, "tradfi": true, "pinned": false, "rank": 3, "since": 1784603001, "since_min": 582}, {"sym": "VIRTUALUSDT", "base": "VIRTUAL", "mark": "🟢", "why": "초입(+8%) + 연료 — 진입검토", "alpha": 69, "g": [["흡수/이탈", "ACC +14", 14], ["VWAP", "VWAP 아래 저항 -4", -4], ["MTF", "BTC 동조화 +0", 0], ["오더북", "매수벽 우위 ×1.73 +8", 8], ["청산", "미미 $7K 0", 0], ["볼밴", "상단 접근 +6", 6], ["스퀴즈", "정상 +0", 0], ["ATR", "낮은 변동성 +3", 3], ["레인지", "레인지 상단 +6", 6], ["FLOW", "Flow +2", 2], ["SURGE", "×1.49 +4", 4], ["KIMCHI", "-0.02%", 0]], "conflict": ["VWAP 아래"], "onchain": null, "price": 0.667, "p24": 7.93, "oi4": 6.1, "oi1": 0.3, "cvd": 0.882, "fr": 0.005, "atr": 1.35, "flow": 1.5, "surge": 1.49, "ret4": 1.57, "bb_pos": 0.862, "bb_squeeze": false, "bb_just_broke": false, "rng": 0.857, "kimp": -0.02, "liq": [6531.71957226, 9.94128, 12], "vwap_broke": true, "spot_fuel": false, "turnover": 32875208, "tradfi": false, "pinned": false, "rank": 4, "since": 1784631801, "since_min": 102}, {"sym": "LITEUSDT", "base": "LITE", "mark": "🟢", "why": "초입(+6%) + 연료 — 진입검토", "alpha": 56, "g": [["흡수/이탈", "ACC +14", 14], ["VWAP", "VWAP 아래 저항 -4", -4], ["MTF", "BTC 동조화 +0", 0], ["오더북", "매도벽 압박 ×0.38 -8", -8], ["청산", "청산 데이터 없음 0", 0], ["볼밴", "상단 접근 +6", 6], ["스퀴즈", "정상 +0", 0], ["ATR", "극저 변동성 +6", 6], ["레인지", "레인지 상단 +6", 6], ["FLOW", "Flow +2", 2], ["SURGE", "×1.76 +4", 4], ["KIMCHI", "—", 0]], "conflict": ["VWAP 아래", "매도벽"], "onchain": null, "price": 804.0, "p24": 6.09, "oi4": 6.1, "oi1": 0.5, "cvd": 0.835, "fr": 0.0, "atr": 0.87, "flow": 1.3, "surge": 1.76, "ret4": 0.38, "bb_pos": 0.812, "bb_squeeze": false, "bb_just_broke": false, "rng": 0.843, "kimp": null, "liq": null, "vwap_broke": true, "spot_fuel": false, "turnover": 30664441, "tradfi": false, "pinned": false, "rank": 5, "since": 1784628201, "since_min": 162}, {"sym": "LAUSDT", "base": "LA", "mark": "🟢", "why": "연료생존 — 진입검토", "alpha": 41, "g": [["흡수/이탈", "— 0", 0], ["VWAP", "VWAP 위 지지 +4", 4], ["MTF", "BTC 동조화 +0", 0], ["오더북", "매도 우위 ×0.80 -4", -4], ["청산", "↑ 숏청산 우위 $36K +5", 5], ["볼밴", "밴드 중단 0", 0], ["스퀴즈", "대형 FR스퀴즈 ★ +8", 8], ["ATR", "정상 변동성 +0", 0], ["레인지", "레인지 내 0", 0], ["FLOW", "Flow -2", -2], ["SURGE", "×0.57 +0", 0], ["KIMCHI", "+3.25%", 0]], "conflict": ["매도벽", "이미 +18%"], "onchain": null, "price": 0.05863, "p24": 17.75, "oi4": 6.4, "oi1": 7.1, "cvd": 0.584, "fr": -1.1672, "atr": 4.93, "flow": -1.3, "surge": 0.57, "ret4": 0.63, "bb_pos": 0.707, "bb_squeeze": false, "bb_just_broke": false, "rng": 0.512, "kimp": 3.25, "liq": [35916.2123274, 23459.468521, 93], "vwap_broke": false, "spot_fuel": false, "turnover": 87978151, "tradfi": false, "pinned": false, "rank": 6, "since": 1784635402, "since_min": 42}, {"sym": "ETHUSDT", "base": "ETH", "mark": "🟡", "why": "연료 약함 — 관찰", "alpha": 75, "g": [["흡수/이탈", "— 0", 0], ["VWAP", "VWAP 위 지지 +4", 4], ["MTF", "BTC 동조화 +0", 0], ["오더북", "매수 우위 ×1.33 +4", 4], ["청산", "대형 숏청산 ★ $1268K +8", 8], ["볼밴", "압축+상단 — 돌파임박 ★ +12", 12], ["스퀴즈", "정상 +0", 0], ["ATR", "극저 변동성 +6", 6], ["레인지", "레인지 상단 +6", 6], ["FLOW", "Flow +5", 5], ["SURGE", "×0.92 +0", 0], ["KIMCHI", "-0.03%", 0]], "conflict": [], "onchain": null, "price": 1941.12, "p24": 3.57, "oi4": 0.2, "oi1": -0.1, "cvd": 0.767, "fr": 0.0011, "atr": 0.6, "flow": 3.0, "surge": 0.92, "ret4": 0.13, "bb_pos": 0.855, "bb_squeeze": true, "bb_just_broke": false, "rng": 0.879, "kimp": -0.03, "liq": [1268489.2212500002, 530905.63879, 126], "vwap_broke": false, "spot_fuel": false, "turnover": 8407340352, "tradfi": false, "pinned": true, "rank": 7, "since": 1784635222, "since_min": 44}, {"sym": "EPICUSDT", "base": "EPIC", "mark": "🟡", "why": "연료 약함 — 관찰", "alpha": 65, "g": [["흡수/이탈", "— 0", 0], ["VWAP", "VWAP 강한 돌파 +10", 10], ["MTF", "BTC 대비 강세 +6", 6], ["오더북", "균형 ×0.91 +0", 0], ["청산", "미미 $17K 0", 0], ["볼밴", "상단 접근 +6", 6], ["스퀴즈", "정상 +0", 0], ["ATR", "고변동성 -4", -4], ["레인지", "고점 돌파 +4", 4], ["FLOW", "Flow -5", -5], ["SURGE", "×3.07 +18", 18], ["KIMCHI", "—", 0]], "conflict": [], "onchain": null, "price": 0.5467, "p24": 28.82, "oi4": 13.8, "oi1": 3.2, "cvd": 0.368, "fr": 0.005, "atr": 6.36, "flow": -3.1, "surge": 3.07, "ret4": 4.31, "bb_pos": 0.968, "bb_squeeze": false, "bb_just_broke": false, "rng": 0.957, "kimp": null, "liq": [15699.8663859, 16956.933536, 65], "vwap_broke": false, "spot_fuel": false, "turnover": 23556976, "tradfi": false, "pinned": false, "rank": 8, "since": 1784634862, "since_min": 51}, {"sym": "BTCUSDT", "base": "BTC", "mark": "🟡", "why": "연료 약함 — 관찰", "alpha": 62, "g": [["흡수/이탈", "— 0", 0], ["VWAP", "VWAP 위 지지 +4", 4], ["MTF", "BTC 동조화 +0", 0], ["오더북", "매도 우위 ×0.80 -4", -4], ["청산", "대형 숏청산 ★ $2868K +8", 8], ["볼밴", "상단 접근 +6", 6], ["스퀴즈", "정상 +0", 0], ["ATR", "극저 변동성 +6", 6], ["레인지", "고점 돌파 +4", 4], ["FLOW", "Flow +8", 8], ["SURGE", "×0.88 +0", 0], ["KIMCHI", "+0.01%", 0]], "conflict": [], "onchain": null, "price": 66491.7, "p24": 2.89, "oi4": 0.7, "oi1": 0.3, "cvd": 0.693, "fr": 0.0075, "atr": 0.4, "flow": 5.2, "surge": 0.88, "ret4": 0.48, "bb_pos": 0.979, "bb_squeeze": false, "bb_just_broke": false, "rng": 0.96, "kimp": 0.01, "liq": [2868482.46275, 182722.98080000002, 123], "vwap_broke": false, "spot_fuel": false, "turnover": 10773963994, "tradfi": false, "pinned": true, "rank": 9, "since": 1784511858, "since_min": 2101}, {"sym": "XAGUSDT", "base": "XAG", "mark": "🟡", "why": "연료 약함 — 관찰", "alpha": 58, "g": [["흡수/이탈", "— 0", 0], ["VWAP", "VWAP 위 지지 +4", 4], ["MTF", "BTC 동조화 +0", 0], ["오더북", "매수벽 우위 ×1.74 +8", 8], ["청산", "미미 $11K 0", 0], ["볼밴", "상단 접근 +6", 6], ["스퀴즈", "정상 +0", 0], ["ATR", "극저 변동성 +6", 6], ["레인지", "레인지 상단 +6", 6], ["FLOW", "Flow -2", -2], ["SURGE", "×0.92 +0", 0], ["KIMCHI", "—", 0]], "conflict": [], "onchain": null, "price": 59.03, "p24": 3.82, "oi4": 3.5, "oi1": 0.7, "cvd": 0.446, "fr": 0.016, "atr": 0.49, "flow": -1.1, "surge": 0.92, "ret4": 0.03, "bb_pos": 0.804, "bb_squeeze": false, "bb_just_broke": false, "rng": 0.911, "kimp": null, "liq": [9828.368520000002, 10833.60247, 13], "vwap_broke": false, "spot_fuel": false, "turnover": 793264418, "tradfi": true, "pinned": false, "rank": 10, "since": 1784631621, "since_min": 105}, {"sym": "JTOUSDT", "base": "JTO", "mark": "🟡", "why": "연료 약함 — 관찰", "alpha": 56, "g": [["흡수/이탈", "— 0", 0], ["VWAP", "VWAP 강한 돌파 +10", 10], ["MTF", "BTC 대비 강세 +6", 6], ["오더북", "매도 우위 ×0.69 -4", -4], ["청산", "미미 $9K 0", 0], ["볼밴", "밴드압축 5.0% — 대기 +4", 4], ["스퀴즈", "정상 +0", 0], ["ATR", "정상 변동성 +0", 0], ["레인지", "레인지 상단 +6", 6], ["FLOW", "Flow -4", -4], ["SURGE", "×2.97 +8", 8], ["KIMCHI", "+0.15%", 0]], "conflict": [], "onchain": null, "price": 0.6181, "p24": 3.31, "oi4": 2.0, "oi1": 1.2, "cvd": 1.0, "fr": 0.003, "atr": 2.04, "flow": -2.3, "surge": 2.97, "ret4": 2.57, "bb_pos": 0.735, "bb_squeeze": true, "bb_just_broke": false, "rng": 0.671, "kimp": 0.15, "liq": [8709.799343, 609.6927, 16], "vwap_broke": false, "spot_fuel": false, "turnover": 28263113, "tradfi": false, "pinned": false, "rank": 11, "since": 1784520318, "since_min": 1960}, {"sym": "CLUSDT", "base": "CL", "mark": "🟡", "why": "연료 약함 — 관찰", "alpha": 54, "g": [["흡수/이탈", "— 0", 0], ["VWAP", "VWAP 위 지지 +4", 4], ["MTF", "BTC 동조화 +0", 0], ["오더북", "균형 ×1.13 +0", 0], ["청산", "↑ 숏청산 우위 $181K +5", 5], ["볼밴", "밴드 밖 진행중 — 이미 감 0", 0], ["스퀴즈", "FR스퀴즈 중 +5", 5], ["ATR", "낮은 변동성 +3", 3], ["레인지", "레인지 상단 +6", 6], ["FLOW", "Flow -7", -7], ["SURGE", "×2.33 +8", 8], ["KIMCHI", "—", 0]], "conflict": [], "onchain": null, "price": 84.11, "p24": 2.5, "oi4": 4.5, "oi1": 1.9, "cvd": 0.711, "fr": -0.0159, "atr": 1.28, "flow": -4.2, "surge": 2.33, "ret4": 2.25, "bb_pos": 1.159, "bb_squeeze": false, "bb_just_broke": false, "rng": 0.902, "kimp": null, "liq": [181054.0218868, 11900.2352, 34], "vwap_broke": false, "spot_fuel": false, "turnover": 714062422, "tradfi": false, "pinned": false, "rank": 12, "since": 1784563223, "since_min": 1244}, {"sym": "ENAUSDT", "base": "ENA", "mark": "🟡", "why": "연료 약함 — 관찰", "alpha": 53, "g": [["흡수/이탈", "— 0", 0], ["VWAP", "VWAP 위 지지 +4", 4], ["MTF", "BTC 동조화 +0", 0], ["오더북", "균형 ×0.94 +0", 0], ["청산", "↑ 숏청산 우위 $47K +5", 5], ["볼밴", "상단 접근 +6", 6], ["스퀴즈", "정상 +0", 0], ["ATR", "낮은 변동성 +3", 3], ["레인지", "레인지 상단 +6", 6], ["FLOW", "Flow -5", -5], ["SURGE", "×1.85 +4", 4], ["KIMCHI", "-0.21%", 0]], "conflict": [], "onchain": null, "price": 0.08705, "p24": 6.82, "oi4": 4.9, "oi1": -0.0, "cvd": 0.827, "fr": 0.005, "atr": 1.48, "flow": -3.0, "surge": 1.85, "ret4": 2.21, "bb_pos": 0.915, "bb_squeeze": false, "bb_just_broke": false, "rng": 0.929, "kimp": -0.21, "liq": [47232.9896579, 755.5241599999999, 23], "vwap_broke": false, "spot_fuel": false, "turnover": 81114626, "tradfi": false, "pinned": false, "rank": 13, "since": 1784636662, "since_min": 21}, {"sym": "COINUSDT", "base": "COIN", "mark": "🟡", "why": "연료 약함 — 관찰", "alpha": 45, "g": [["흡수/이탈", "— 0", 0], ["VWAP", "VWAP 위 지지 +4", 4], ["MTF", "BTC 동조화 +0", 0], ["오더북", "매도벽 압박 ×0.52 -8", -8], ["청산", "청산 데이터 없음 0", 0], ["볼밴", "방금 상단 돌파 — 초입 +8", 8], ["스퀴즈", "정상 +0", 0], ["ATR", "낮은 변동성 +3", 3], ["레인지", "레인지 상단 +6", 6], ["FLOW", "Flow -2", -2], ["SURGE", "×1.54 +4", 4], ["KIMCHI", "—", 0]], "conflict": [], "onchain": null, "price": 167.52, "p24": 5.11, "oi4": 2.7, "oi1": -0.5, "cvd": 0.554, "fr": 0.0196, "atr": 1.05, "flow": -1.4, "surge": 1.54, "ret4": 0.58, "bb_pos": 1.004, "bb_squeeze": false, "bb_just_broke": true, "rng": 0.878, "kimp": null, "liq": null, "vwap_broke": false, "spot_fuel": false, "turnover": 26491732, "tradfi": true, "pinned": false, "rank": 14, "since": 1784555841, "since_min": 1368}, {"sym": "SPCXUSDT", "base": "SPCX", "mark": "🟡", "why": "연료 약함 — 관찰", "alpha": 45, "g": [["흡수/이탈", "— 0", 0], ["VWAP", "VWAP 위 지지 +4", 4], ["MTF", "BTC 동조화 +0", 0], ["오더북", "균형 ×0.98 +0", 0], ["청산", "혼조 0", 0], ["볼밴", "압축+상단 — 돌파임박 ★ +12", 12], ["스퀴즈", "정상 +0", 0], ["ATR", "극저 변동성 +6", 6], ["레인지", "레인지 내 0", 0], ["FLOW", "Flow -11", -11], ["SURGE", "×1.91 +4", 4], ["KIMCHI", "—", 0]], "conflict": [], "onchain": null, "price": 122.41, "p24": -2.27, "oi4": 1.7, "oi1": 0.9, "cvd": 0.449, "fr": 0.0345, "atr": 0.77, "flow": -6.6, "surge": 1.91, "ret4": 0.27, "bb_pos": 0.901, "bb_squeeze": true, "bb_just_broke": false, "rng": 0.451, "kimp": null, "liq": [35506.7606928, 26031.795100000003, 19], "vwap_broke": false, "spot_fuel": false, "turnover": 698373832, "tradfi": true, "pinned": false, "rank": 15, "since": 1784581401, "since_min": 942}, {"sym": "MUUUSDT", "base": "MUU", "mark": "🟡", "why": "연료 약함 — 관찰", "alpha": 44, "g": [["흡수/이탈", "ACC +28", 28], ["VWAP", "VWAP 아래 저항 -4", -4], ["MTF", "BTC 동조화 +0", 0], ["오더북", "매도벽 압박 ×0.24 -8", -8], ["청산", "청산 데이터 없음 0", 0], ["볼밴", "상단 접근 +6", 6], ["스퀴즈", "정상 +0", 0], ["ATR", "낮은 변동성 +3", 3], ["레인지", "레인지 상단 +6", 6], ["FLOW", "Flow -17", -17], ["SURGE", "×1.08 +0", 0], ["KIMCHI", "—", 0]], "conflict": [], "onchain": null, "price": 31.62, "p24": 6.72, "oi4": 38.5, "oi1": 0.0, "cvd": 0.5, "fr": 0.0, "atr": 1.54, "flow": -10.4, "surge": 1.08, "ret4": -0.09, "bb_pos": 0.802, "bb_squeeze": false, "bb_just_broke": false, "rng": 0.856, "kimp": null, "liq": null, "vwap_broke": true, "spot_fuel": false, "turnover": 18323784, "tradfi": false, "pinned": false, "rank": 16, "since": 1784636662, "since_min": 21}, {"sym": "SOXSUSDT", "base": "SOXS", "mark": "🟡", "why": "연료 약함 — 관찰", "alpha": 43, "g": [["흡수/이탈", "ACC +28", 28], ["VWAP", "VWAP 아래 저항 -4", -4], ["MTF", "BTC 동조화 +0", 0], ["오더북", "균형 ×1.06 +0", 0], ["청산", "미미 $1K 0", 0], ["볼밴", "밴드 하단 -3", -3], ["스퀴즈", "정상 +0", 0], ["ATR", "낮은 변동성 +3", 3], ["레인지", "저점 근접 -6", -6], ["FLOW", "Flow -5", -5], ["SURGE", "×0.99 +0", 0], ["KIMCHI", "—", 0]], "conflict": [], "onchain": null, "price": 47.09, "p24": -7.47, "oi4": 14.1, "oi1": 3.7, "cvd": 0.266, "fr": 0.0, "atr": 1.71, "flow": -3.3, "surge": 0.99, "ret4": -0.32, "bb_pos": 0.159, "bb_squeeze": false, "bb_just_broke": false, "rng": 0.06, "kimp": null, "liq": [0, 1495.068382, 2], "vwap_broke": true, "spot_fuel": false, "turnover": 37843941, "tradfi": true, "pinned": false, "rank": 17, "since": 1784637922, "since_min": 0}, {"sym": "GLWUSDT", "base": "GLW", "mark": "🟡", "why": "연료 약함 — 관찰", "alpha": 43, "g": [["흡수/이탈", "— 0", 0], ["VWAP", "VWAP 위 지지 +4", 4], ["MTF", "BTC 동조화 +0", 0], ["오더북", "매도 우위 ×0.71 -4", -4], ["청산", "청산 데이터 없음 0", 0], ["볼밴", "상단 접근 +6", 6], ["스퀴즈", "롱 과열 -4", -4], ["ATR", "극저 변동성 +6", 6], ["레인지", "레인지 상단 +6", 6], ["FLOW", "Flow -1", -1], ["SURGE", "×1.07 +0", 0], ["KIMCHI", "—", 0]], "conflict": [], "onchain": null, "price": 161.39, "p24": 1.22, "oi4": 2.1, "oi1": 0.1, "cvd": 0.271, "fr": 0.0641, "atr": 0.97, "flow": -0.8, "surge": 1.07, "ret4": 0.6, "bb_pos": 0.876, "bb_squeeze": false, "bb_just_broke": false, "rng": 0.922, "kimp": null, "liq": null, "vwap_broke": false, "spot_fuel": false, "turnover": 20703081, "tradfi": false, "pinned": false, "rank": 18, "since": 1784631441, "since_min": 108}, {"sym": "SOLUSDT", "base": "SOL", "mark": "🟡", "why": "연료 약함 — 관찰", "alpha": 42, "g": [["흡수/이탈", "— 0", 0], ["VWAP", "VWAP 위 지지 +4", 4], ["MTF", "BTC 동조화 +0", 0], ["오더북", "균형 ×1.03 +0", 0], ["청산", "↓ 롱청산 우위 $70K -6", -6], ["볼밴", "밴드압축 1.7% — 대기 +4", 4], ["스퀴즈", "정상 +0", 0], ["ATR", "극저 변동성 +6", 6], ["레인지", "레인지 상단 +6", 6], ["FLOW", "Flow -2", -2], ["SURGE", "×0.93 +0", 0], ["KIMCHI", "-0.01%", 0]], "conflict": [], "onchain": null, "price": 78.39, "p24": 2.2, "oi4": -0.0, "oi1": 0.4, "cvd": 0.712, "fr": 0.0019, "atr": 0.45, "flow": -1.5, "surge": 0.93, "ret4": 0.1, "bb_pos": 0.765, "bb_squeeze": true, "bb_just_broke": false, "rng": 0.85, "kimp": -0.01, "liq": [2786.9445, 70073.1809, 27], "vwap_broke": false, "spot_fuel": false, "turnover": 1173359490, "tradfi": false, "pinned": true, "rank": 19, "since": 1784516538, "since_min": 2023}, {"sym": "ONUSDT", "base": "ON", "mark": "🟡", "why": "연료 약함 — 관찰", "alpha": 40, "g": [["흡수/이탈", "— 0", 0], ["VWAP", "VWAP 아래 저항 -4", -4], ["MTF", "BTC 대비 약세 -6", -6], ["오더북", "매수 우위 ×1.48 +4", 4], ["청산", "혼조 0", 0], ["볼밴", "밴드압축 23.4% — 대기 +4", 4], ["스퀴즈", "정상 +0", 0], ["ATR", "고변동성 -4", -4], ["레인지", "레인지 내 0", 0], ["FLOW", "Flow -2", -2], ["SURGE", "×3.28 +18", 18], ["KIMCHI", "—", 0]], "conflict": [], "onchain": null, "price": 0.14487, "p24": 20.35, "oi4": 2.1, "oi1": -10.5, "cvd": 0.342, "fr": 0.0352, "atr": 21.64, "flow": -1.0, "surge": 3.28, "ret4": -10.65, "bb_pos": 0.287, "bb_squeeze": true, "bb_just_broke": false, "rng": 0.385, "kimp": null, "liq": [166992.05362679999, 206841.5009115, 419], "vwap_broke": true, "spot_fuel": false, "turnover": 73227740, "tradfi": false, "pinned": false, "rank": 20, "since": 1784631441, "since_min": 108}, {"sym": "BILLUSDT", "base": "BILL", "mark": "🟡", "why": "연료 약함 — 관찰", "alpha": 39, "g": [["흡수/이탈", "— 0", 0], ["VWAP", "VWAP 위 지지 +4", 4], ["MTF", "BTC 동조화 +0", 0], ["오더북", "균형 ×1.08 +0", 0], ["청산", "미미 $3K 0", 0], ["볼밴", "밴드압축 6.2% — 대기 +4", 4], ["스퀴즈", "FR스퀴즈 중 +5", 5], ["ATR", "정상 변동성 +0", 0], ["레인지", "레인지 내 0", 0], ["FLOW", "Flow -4", -4], ["SURGE", "×0.82 +0", 0], ["KIMCHI", "—", 0]], "conflict": [], "onchain": {"src": "cold", "score": 73, "mark": "🟢", "grade": "강한 펌프 가능성", "cold_score": 73, "cold_usd": 33392242, "cold_n": 8, "cold_wallets": 3, "cold_days": 22.7, "peak": 0.2, "accum_score": null, "accum_usd": null, "accum_wallets": null, "accum_wd": null, "accum_days": null, "conc": false}, "price": 0.024, "p24": -2.52, "oi4": -0.0, "oi1": -0.2, "cvd": 0.839, "fr": -0.0146, "atr": 2.25, "flow": -2.2, "surge": 0.82, "ret4": 1.01, "bb_pos": 0.417, "bb_squeeze": true, "bb_just_broke": false, "rng": 0.262, "kimp": null, "liq": [2528.7027029, 2589.2943854, 8], "vwap_broke": false, "spot_fuel": false, "turnover": 7909949, "tradfi": false, "pinned": true, "rank": 21, "since": 1784512938, "since_min": 2083}, {"sym": "IBMUSDT", "base": "IBM", "mark": "🟡", "why": "연료 약함 — 관찰", "alpha": 35, "g": [["흡수/이탈", "ACC +14", 14], ["VWAP", "VWAP 위 지지 +4", 4], ["MTF", "BTC 동조화 +0", 0], ["오더북", "매도벽 압박 ×0.37 -8", -8], ["청산", "청산 데이터 없음 0", 0], ["볼밴", "밴드압축 1.9% — 대기 +4", 4], ["스퀴즈", "정상 +0", 0], ["ATR", "극저 변동성 +6", 6], ["레인지", "레인지 내 0", 0], ["FLOW", "Flow -15", -15], ["SURGE", "×1.03 +0", 0], ["KIMCHI", "—", 0]], "conflict": [], "onchain": null, "price": 211.64, "p24": 0.56, "oi4": 6.6, "oi1": 0.7, "cvd": 0.446, "fr": 0.0, "atr": 0.37, "flow": -9.3, "surge": 1.03, "ret4": -0.08, "bb_pos": 0.137, "bb_squeeze": true, "bb_just_broke": false, "rng": 0.332, "kimp": null, "liq": null, "vwap_broke": false, "spot_fuel": false, "turnover": 21197407, "tradfi": false, "pinned": false, "rank": 22, "since": 1784574023, "since_min": 1064}, {"sym": "MSTRUSDT", "base": "MSTR", "mark": "🟡", "why": "연료 약함 — 관찰", "alpha": 34, "g": [["흡수/이탈", "— 0", 0], ["VWAP", "VWAP 위 지지 +4", 4], ["MTF", "BTC 동조화 +0", 0], ["오더북", "매도 우위 ×0.71 -4", -4], ["청산", "청산 데이터 없음 0", 0], ["볼밴", "압축+상단 — 돌파임박 ★ +12", 12], ["스퀴즈", "정상 +0", 0], ["ATR", "극저 변동성 +6", 6], ["레인지", "레인지 상단 +6", 6], ["FLOW", "Flow -20", -20], ["SURGE", "×1.38 +0", 0], ["KIMCHI", "—", 0]], "conflict": [], "onchain": null, "price": 101.35, "p24": 5.68, "oi4": 1.7, "oi1": 0.9, "cvd": 0.405, "fr": 0.0313, "atr": 0.85, "flow": -12.2, "surge": 1.38, "ret4": 0.06, "bb_pos": 0.881, "bb_squeeze": true, "bb_just_broke": false, "rng": 0.901, "kimp": null, "liq": null, "vwap_broke": false, "spot_fuel": false, "turnover": 114345855, "tradfi": true, "pinned": false, "rank": 23, "since": 1784294417, "since_min": 5725}, {"sym": "LINKUSDT", "base": "LINK", "mark": "🟡", "why": "연료 약함 — 관찰", "alpha": 34, "g": [["흡수/이탈", "— 0", 0], ["VWAP", "VWAP 아래 저항 -4", -4], ["MTF", "BTC 동조화 +0", 0], ["오더북", "균형 ×0.90 +0", 0], ["청산", "미미 $4K 0", 0], ["볼밴", "밴드압축 3.3% — 대기 +4", 4], ["스퀴즈", "정상 +0", 0], ["ATR", "극저 변동성 +6", 6], ["레인지", "레인지 상단 +6", 6], ["FLOW", "Flow -8", -8], ["SURGE", "×0.57 +0", 0], ["KIMCHI", "+0.03%", 0]], "conflict": [], "onchain": {"src": "cold", "score": 73, "mark": "🟢", "grade": "강한 펌프 가능성", "cold_score": 73, "cold_usd": 18610326, "cold_n": 9, "cold_wallets": 10, "cold_days": 33.0, "peak": 10.9, "accum_score": null, "accum_usd": null, "accum_wallets": null, "accum_wd": null, "accum_days": null, "conc": false}, "price": 8.698, "p24": 2.97, "oi4": 1.0, "oi1": 0.0, "cvd": 0.48, "fr": 0.01, "atr": 0.46, "flow": -5.1, "surge": 0.57, "ret4": 0.03, "bb_pos": 0.729, "bb_squeeze": true, "bb_just_broke": false, "rng": 0.881, "kimp": 0.03, "liq": [3921.13665, 0, 1], "vwap_broke": true, "spot_fuel": false, "turnover": 93627613, "tradfi": false, "pinned": true, "rank": 24, "since": 1784620823, "since_min": 284}, {"sym": "NBISUSDT", "base": "NBIS", "mark": "🟡", "why": "연료 약함 — 관찰", "alpha": 32, "g": [["흡수/이탈", "— 0", 0], ["VWAP", "VWAP 아래 저항 -4", -4], ["MTF", "BTC 동조화 +0", 0], ["오더북", "균형 ×1.04 +0", 0], ["청산", "청산 데이터 없음 0", 0], ["볼밴", "밴드 중단 0", 0], ["스퀴즈", "정상 +0", 0], ["ATR", "낮은 변동성 +3", 3], ["레인지", "레인지 상단 +6", 6], ["FLOW", "Flow -3", -3], ["SURGE", "×1.03 +0", 0], ["KIMCHI", "—", 0]], "conflict": [], "onchain": null, "price": 194.77, "p24": 4.76, "oi4": 3.1, "oi1": -0.3, "cvd": 0.234, "fr": 0.0262, "atr": 1.03, "flow": -1.6, "surge": 1.03, "ret4": -0.82, "bb_pos": 0.74, "bb_squeeze": false, "bb_just_broke": false, "rng": 0.871, "kimp": null, "liq": null, "vwap_broke": true, "spot_fuel": false, "turnover": 57411401, "tradfi": false, "pinned": false, "rank": 25, "since": 1784555661, "since_min": 1371}, {"sym": "SKHYUSDT", "base": "SKHY", "mark": "🟡", "why": "연료 약함 — 관찰", "alpha": 31, "g": [["흡수/이탈", "ACC +14", 14], ["VWAP", "VWAP 아래 저항 -4", -4], ["MTF", "BTC 동조화 +0", 0], ["오더북", "매도 우위 ×0.86 -4", -4], ["청산", "↓ 롱청산 우위 $33K -6", -6], ["볼밴", "밴드압축 8.6% — 대기 +4", 4], ["스퀴즈", "정상 +0", 0], ["ATR", "낮은 변동성 +3", 3], ["레인지", "레인지 상단 +6", 6], ["FLOW", "Flow -12", -12], ["SURGE", "×0.73 +0", 0], ["KIMCHI", "—", 0]], "conflict": [], "onchain": null, "price": 159.64, "p24": -1.42, "oi4": 5.9, "oi1": 2.1, "cvd": 0.168, "fr": 0.0242, "atr": 1.08, "flow": -7.5, "surge": 0.73, "ret4": -1.4, "bb_pos": 0.691, "bb_squeeze": true, "bb_just_broke": false, "rng": 0.682, "kimp": null, "liq": [0, 33388.1747362, 6], "vwap_broke": true, "spot_fuel": false, "turnover": 829145414, "tradfi": false, "pinned": false, "rank": 26, "since": 1784628201, "since_min": 162}, {"sym": "CBRSUSDT", "base": "CBRS", "mark": "🟡", "why": "연료 약함 — 관찰", "alpha": 28, "g": [["흡수/이탈", "— 0", 0], ["VWAP", "VWAP 아래 저항 -4", -4], ["MTF", "BTC 동조화 +0", 0], ["오더북", "매수벽 우위 ×1.88 +8", 8], ["청산", "청산 데이터 없음 0", 0], ["볼밴", "밴드압축 4.7% — 대기 +4", 4], ["스퀴즈", "정상 +0", 0], ["ATR", "극저 변동성 +6", 6], ["레인지", "레인지 상단 +6", 6], ["FLOW", "Flow -22", -22], ["SURGE", "×1.39 +0", 0], ["KIMCHI", "—", 0]], "conflict": [], "onchain": null, "price": 180.8, "p24": 2.72, "oi4": 2.6, "oi1": -0.2, "cvd": 0.0, "fr": 0.0, "atr": 0.93, "flow": -13.8, "surge": 1.39, "ret4": -1.4, "bb_pos": 0.689, "bb_squeeze": true, "bb_just_broke": false, "rng": 0.857, "kimp": null, "liq": null, "vwap_broke": true, "spot_fuel": false, "turnover": 25671604, "tradfi": false, "pinned": false, "rank": 27, "since": 1784581401, "since_min": 942}, {"sym": "AMDUSDT", "base": "AMD", "mark": "🟡", "why": "연료 약함 — 관찰", "alpha": 24, "g": [["흡수/이탈", "— 0", 0], ["VWAP", "VWAP 아래 저항 -4", -4], ["MTF", "BTC 동조화 +0", 0], ["오더북", "매수벽 우위 ×2.02 +8", 8], ["청산", "청산 데이터 없음 0", 0], ["볼밴", "밴드 중단 0", 0], ["스퀴즈", "정상 +0", 0], ["ATR", "극저 변동성 +6", 6], ["레인지", "레인지 상단 +6", 6], ["FLOW", "Flow -22", -22], ["SURGE", "×0.82 +0", 0], ["KIMCHI", "—", 0]], "conflict": [], "onchain": null, "price": 523.07, "p24": 1.8, "oi4": 2.1, "oi1": 0.3, "cvd": 0.413, "fr": 0.0182, "atr": 0.63, "flow": -13.4, "surge": 0.82, "ret4": -0.66, "bb_pos": 0.76, "bb_squeeze": false, "bb_just_broke": false, "rng": 0.654, "kimp": null, "liq": null, "vwap_broke": true, "spot_fuel": false, "turnover": 46424209, "tradfi": true, "pinned": false, "rank": 28, "since": 1784570602, "since_min": 1122}, {"sym": "TSLAUSDT", "base": "TSLA", "mark": "🟡", "why": "연료 약함 — 관찰", "alpha": 23, "g": [["흡수/이탈", "— 0", 0], ["VWAP", "VWAP 아래 저항 -4", -4], ["MTF", "BTC 동조화 +0", 0], ["오더북", "균형 ×0.96 +0", 0], ["청산", "청산 데이터 없음 0", 0], ["볼밴", "밴드압축 1.6% — 대기 +4", 4], ["스퀴즈", "정상 +0", 0], ["ATR", "극저 변동성 +6", 6], ["레인지", "레인지 내 0", 0], ["FLOW", "Flow -17", -17], ["SURGE", "×1.80 +4", 4], ["KIMCHI", "—", 0]], "conflict": [], "onchain": null, "price": 371.71, "p24": -3.34, "oi4": 2.6, "oi1": 0.2, "cvd": 0.0, "fr": 0.0239, "atr": 0.44, "flow": -10.7, "surge": 1.8, "ret4": -0.75, "bb_pos": 0.377, "bb_squeeze": true, "bb_just_broke": false, "rng": 0.116, "kimp": null, "liq": null, "vwap_broke": true, "spot_fuel": false, "turnover": 47745516, "tradfi": true, "pinned": false, "rank": 29, "since": 1784556201, "since_min": 1362}, {"sym": "SNDKUSDT", "base": "SNDK", "mark": "🟡", "why": "연료 약함 — 관찰", "alpha": 21, "g": [["흡수/이탈", "— 0", 0], ["VWAP", "VWAP 아래 저항 -4", -4], ["MTF", "BTC 동조화 +0", 0], ["오더북", "매수 우위 ×1.16 +4", 4], ["청산", "↓ 롱청산 우위 $36K -6", -6], ["볼밴", "밴드 중단 0", 0], ["스퀴즈", "정상 +0", 0], ["ATR", "낮은 변동성 +3", 3], ["레인지", "레인지 상단 +6", 6], ["FLOW", "Flow -12", -12], ["SURGE", "×0.75 +0", 0], ["KIMCHI", "—", 0]], "conflict": [], "onchain": null, "price": 1490.17, "p24": 6.48, "oi4": 3.9, "oi1": 0.9, "cvd": 0.213, "fr": 0.0, "atr": 1.24, "flow": -7.5, "surge": 0.75, "ret4": -1.07, "bb_pos": 0.758, "bb_squeeze": false, "bb_just_broke": false, "rng": 0.818, "kimp": null, "liq": [4944.8416992, 36413.9665105, 15], "vwap_broke": true, "spot_fuel": false, "turnover": 2623198587, "tradfi": true, "pinned": false, "rank": 30, "since": 1784635222, "since_min": 44}, {"sym": "SNXXUSDT", "base": "SNXX", "mark": "🟡", "why": "연료 약함 — 관찰", "alpha": 19, "g": [["흡수/이탈", "— 0", 0], ["VWAP", "VWAP 아래 저항 -4", -4], ["MTF", "BTC 동조화 +0", 0], ["오더북", "매도벽 압박 ×0.57 -8", -8], ["청산", "미미 $1K 0", 0], ["볼밴", "밴드 중단 0", 0], ["스퀴즈", "정상 +0", 0], ["ATR", "정상 변동성 +0", 0], ["레인지", "레인지 상단 +6", 6], ["FLOW", "Flow -5", -5], ["SURGE", "×0.76 +0", 0], ["KIMCHI", "—", 0]], "conflict": [], "onchain": null, "price": 15.87, "p24": 12.08, "oi4": 1.9, "oi1": 2.1, "cvd": 0.229, "fr": 0.0, "atr": 2.54, "flow": -3.1, "surge": 0.76, "ret4": -2.34, "bb_pos": 0.747, "bb_squeeze": false, "bb_just_broke": false, "rng": 0.8, "kimp": null, "liq": [0, 1319.3093546, 6], "vwap_broke": true, "spot_fuel": false, "turnover": 71659267, "tradfi": false, "pinned": false, "rank": 31, "since": 1784635222, "since_min": 44}, {"sym": "GOOGLUSDT", "base": "GOOGL", "mark": "🟡", "why": "연료 약함 — 관찰", "alpha": 9, "g": [["흡수/이탈", "— 0", 0], ["VWAP", "VWAP 아래 저항 -4", -4], ["MTF", "BTC 동조화 +0", 0], ["오더북", "매도 우위 ×0.70 -4", -4], ["청산", "청산 데이터 없음 0", 0], ["볼밴", "밴드압축 1.7% — 대기 +4", 4], ["스퀴즈", "정상 +0", 0], ["ATR", "극저 변동성 +6", 6], ["레인지", "레인지 내 0", 0], ["FLOW", "Flow -23", -23], ["SURGE", "×0.85 +0", 0], ["KIMCHI", "—", 0]], "conflict": [], "onchain": null, "price": 351.15, "p24": 0.7, "oi4": 2.9, "oi1": 0.8, "cvd": 0.0, "fr": 0.0285, "atr": 0.82, "flow": -14.1, "surge": 0.85, "ret4": -1.3, "bb_pos": 0.018, "bb_squeeze": true, "bb_just_broke": false, "rng": 0.188, "kimp": null, "liq": null, "vwap_broke": true, "spot_fuel": false, "turnover": 56676655, "tradfi": true, "pinned": false, "rank": 32, "since": 1784628023, "since_min": 164}, {"sym": "ERAUSDT", "base": "ERA", "mark": "🔴", "why": "수직급등 +65% — 과열 추격금지", "alpha": 59, "g": [["흡수/이탈", "— 0", 0], ["VWAP", "VWAP 강한 돌파 +10", 10], ["MTF", "BTC 대비 초강세 +12", 12], ["오더북", "매도벽 압박 ×0.14 -8", -8], ["청산", "↑ 숏청산 우위 $199K +5", 5], ["볼밴", "밴드 중단 0", 0], ["스퀴즈", "대형 FR스퀴즈 ★ +8", 8], ["ATR", "고변동성 -4", -4], ["레인지", "레인지 상단 +6", 6], ["FLOW", "Flow +0", 0], ["SURGE", "×0.84 +0", 0], ["KIMCHI", "+3.77%", 0]], "conflict": [], "onchain": null, "price": 0.10283, "p24": 64.95, "oi4": 29.2, "oi1": 13.2, "cvd": 0.765, "fr": -1.444, "atr": 8.72, "flow": 0.2, "surge": 0.84, "ret4": 9.98, "bb_pos": 0.797, "bb_squeeze": false, "bb_just_broke": false, "rng": 0.858, "kimp": 3.77, "liq": [199192.6092125, 77118.355982, 307], "vwap_broke": false, "spot_fuel": false, "turnover": 328893892, "tradfi": false, "pinned": false, "rank": 33, "since": 1784637742, "since_min": 3}, {"sym": "HOMEUSDT", "base": "HOME", "mark": "🔴", "why": "하락 중 -15% — 롱 근거 없음", "alpha": 34, "g": [["흡수/이탈", "— 0", 0], ["VWAP", "VWAP 아래 저항 -4", -4], ["MTF", "BTC 동조화 +0", 0], ["오더북", "매수 우위 ×1.20 +4", 4], ["청산", "미미 $11K 0", 0], ["볼밴", "밴드압축 11.3% — 대기 +4", 4], ["스퀴즈", "대형 FR스퀴즈 ★ +8", 8], ["ATR", "정상 변동성 +0", 0], ["레인지", "저점 근접 -6", -6], ["FLOW", "Flow -2", -2], ["SURGE", "×0.95 +0", 0], ["KIMCHI", "—", 0]], "conflict": [], "onchain": null, "price": 0.00669, "p24": -15.21, "oi4": 3.0, "oi1": 0.6, "cvd": 0.466, "fr": -0.2145, "atr": 2.45, "flow": -1.5, "surge": 0.95, "ret4": -0.89, "bb_pos": 0.149, "bb_squeeze": true, "bb_just_broke": false, "rng": 0.075, "kimp": null, "liq": [2530.6373, 10967.78343, 33], "vwap_broke": true, "spot_fuel": false, "turnover": 24255815, "tradfi": false, "pinned": false, "rank": 34, "since": 1784630721, "since_min": 120}, {"sym": "TLMUSDT", "base": "TLM", "mark": "🔴", "why": "하락 중 -17% — 롱 근거 없음", "alpha": 1, "g": [["흡수/이탈", "— 0", 0], ["VWAP", "VWAP 아래 저항 -4", -4], ["MTF", "BTC 대비 약세 -6", -6], ["오더북", "매수 우위 ×1.20 +4", 4], ["청산", "미미 $19K 0", 0], ["볼밴", "밴드 하단 -3", -3], ["스퀴즈", "정상 +0", 0], ["ATR", "정상 변동성 +0", 0], ["레인지", "저점 근접 -6", -6], ["FLOW", "Flow -14", -14], ["SURGE", "×0.68 +0", 0], ["KIMCHI", "—", 0]], "conflict": [], "onchain": null, "price": 0.001629, "p24": -17.06, "oi4": 1.8, "oi1": -0.9, "cvd": 0.0, "fr": -0.0056, "atr": 2.23, "flow": -8.6, "surge": 0.68, "ret4": -3.67, "bb_pos": 0.072, "bb_squeeze": false, "bb_just_broke": false, "rng": 0.023, "kimp": null, "liq": [351.4798032, 19225.0956319, 47], "vwap_broke": true, "spot_fuel": false, "turnover": 28661001, "tradfi": false, "pinned": false, "rank": 35, "since": 1784581401, "since_min": 942}]}