{"updated": "2026-07-22 00:51:21", "updated_ts": 1784649081, "scan_sec": 180, "us_open": true, "ws": true, "liq_events": 47851, "count": 35, "cols": ["흡수/이탈", "VWAP", "MTF", "오더북", "청산", "볼밴", "스퀴즈", "ATR", "레인지", "FLOW", "SURGE", "KIMCHI"], "rows": [{"sym": "GRAMUSDT", "base": "GRAM", "mark": "💎", "why": "초입(+7%) + 강한연료 — 노다지", "alpha": 100, "g": [["흡수/이탈", "ACC +28", 28], ["VWAP", "VWAP 강한 돌파 +10", 10], ["MTF", "BTC 대비 강세 +6", 6], ["오더북", "매수 우위 ×1.30 +4", 4], ["청산", "미미 $14K 0", 0], ["볼밴", "밴드 밖 진행중 — 이미 감 0", 0], ["스퀴즈", "정상 +0", 0], ["ATR", "정상 변동성 +0", 0], ["레인지", "레인지 상단 +6", 6], ["FLOW", "Flow +5", 5], ["SURGE", "×14.76 +18", 18], ["KIMCHI", "—", 0]], "conflict": ["볼밴 이미 감"], "onchain": null, "price": 1.527, "p24": 6.93, "oi4": 15.4, "oi1": 14.7, "cvd": 0.987, "fr": 0.0012, "atr": 3.38, "flow": 3.4, "surge": 14.76, "ret4": 5.24, "bb_pos": 1.311, "bb_squeeze": false, "bb_just_broke": false, "rng": 0.752, "kimp": null, "liq": [13844.194465199998, 8718.1622, 31], "vwap_broke": false, "spot_fuel": false, "turnover": 32174771, "tradfi": false, "pinned": false, "rank": 1, "since": 1784646201, "since_min": 48}, {"sym": "ONEUSDT", "base": "ONE", "mark": "💎", "why": "순위권 + 강한연료 — 아직 갈 자리", "alpha": 74, "g": [["흡수/이탈", "— 0", 0], ["VWAP", "VWAP 위 지지 +4", 4], ["MTF", "BTC 대비 초강세 +12", 12], ["오더북", "균형 ×1.10 +0", 0], ["청산", "혼조 0", 0], ["볼밴", "밴드 밖 진행중 — 이미 감 0", 0], ["스퀴즈", "대형 FR스퀴즈 ★ +8", 8], ["ATR", "고변동성 -4", -4], ["레인지", "레인지 상단 +6", 6], ["FLOW", "Flow +0", 0], ["SURGE", "×247.53 +18", 18], ["KIMCHI", "—", 0]], "conflict": ["볼밴 이미 감", "이미 +36%"], "onchain": null, "price": 0.001534, "p24": 35.87, "oi4": 103.1, "oi1": 21.2, "cvd": 0.748, "fr": -0.9447, "atr": 11.96, "flow": -0.1, "surge": 247.53, "ret4": 33.98, "bb_pos": 1.088, "bb_squeeze": false, "bb_just_broke": false, "rng": 0.751, "kimp": null, "liq": [202508.9402481, 155093.5800738, 385], "vwap_broke": false, "spot_fuel": false, "turnover": 46512421, "tradfi": false, "pinned": false, "rank": 2, "since": 1784646201, "since_min": 48}, {"sym": "MUUUSDT", "base": "MUU", "mark": "💎", "why": "순위권 + 강한연료 — 아직 갈 자리", "alpha": 62, "g": [["흡수/이탈", "— 0", 0], ["VWAP", "VWAP 강한 돌파 +10", 10], ["MTF", "BTC 대비 초강세 +12", 12], ["오더북", "매도벽 압박 ×0.18 -8", -8], ["청산", "↑ 숏청산 우위 $57K +5", 5], ["볼밴", "밴드 밖 진행중 — 이미 감 0", 0], ["스퀴즈", "정상 +0", 0], ["ATR", "정상 변동성 +0", 0], ["레인지", "고점 돌파 +4", 4], ["FLOW", "Flow -9", -9], ["SURGE", "×3.67 +18", 18], ["KIMCHI", "—", 0]], "conflict": ["볼밴 이미 감", "레인지 고점", "매도벽", "이미 +16%"], "onchain": null, "price": 34.15, "p24": 15.76, "oi4": 8.2, "oi1": 0.5, "cvd": 1.0, "fr": 0.0, "atr": 3.94, "flow": -5.9, "surge": 3.67, "ret4": 7.82, "bb_pos": 1.034, "bb_squeeze": false, "bb_just_broke": false, "rng": 0.98, "kimp": null, "liq": [56862.704312400005, 1283.4279999999999, 21], "vwap_broke": false, "spot_fuel": false, "turnover": 19922477, "tradfi": false, "pinned": false, "rank": 3, "since": 1784645121, "since_min": 66}, {"sym": "COINUSDT", "base": "COIN", "mark": "🟢", "why": "연료생존 — 진입검토", "alpha": 96, "g": [["흡수/이탈", "ACC +14", 14], ["VWAP", "VWAP 강한 돌파 +10", 10], ["MTF", "BTC 대비 초강세 +12", 12], ["오더북", "매수벽 우위 ×4.57 +8", 8], ["청산", "미미 $0K 0", 0], ["볼밴", "밴드 밖 진행중 — 이미 감 0", 0], ["스퀴즈", "정상 +0", 0], ["ATR", "정상 변동성 +0", 0], ["레인지", "고점 돌파 +4", 4], ["FLOW", "Flow +0", 0], ["SURGE", "×9.15 +18", 18], ["KIMCHI", "—", 0]], "conflict": ["볼밴 이미 감", "레인지 고점"], "onchain": null, "price": 180.45, "p24": 11.33, "oi4": 5.7, "oi1": -0.9, "cvd": 1.0, "fr": 0.0, "atr": 3.36, "flow": 0.1, "surge": 9.15, "ret4": 9.12, "bb_pos": 1.145, "bb_squeeze": false, "bb_just_broke": false, "rng": 0.993, "kimp": null, "liq": [132.2802, 0, 4], "vwap_broke": false, "spot_fuel": false, "turnover": 37142784, "tradfi": true, "pinned": false, "rank": 4, "since": 1784642601, "since_min": 108}, {"sym": "SNDKUSDT", "base": "SNDK", "mark": "🟢", "why": "연료생존 — 진입검토", "alpha": 87, "g": [["흡수/이탈", "— 0", 0], ["VWAP", "VWAP 강한 돌파 +10", 10], ["MTF", "BTC 대비 강세 +6", 6], ["오더북", "매수벽 우위 ×5.65 +8", 8], ["청산", "↑ 숏청산 우위 $340K +5", 5], ["볼밴", "상단 접근 +6", 6], ["스퀴즈", "정상 +0", 0], ["ATR", "정상 변동성 +0", 0], ["레인지", "고점 돌파 +4", 4], ["FLOW", "Flow +0", 0], ["SURGE", "×3.61 +18", 18], ["KIMCHI", "—", 0]], "conflict": ["레인지 고점"], "onchain": null, "price": 1551.12, "p24": 9.29, "oi4": 5.0, "oi1": 2.5, "cvd": 0.924, "fr": 0.0, "atr": 2.52, "flow": 0.2, "surge": 3.61, "ret4": 3.7, "bb_pos": 0.949, "bb_squeeze": false, "bb_just_broke": false, "rng": 0.953, "kimp": null, "liq": [339563.9261221, 216650.3499836, 105], "vwap_broke": false, "spot_fuel": false, "turnover": 2570466774, "tradfi": true, "pinned": false, "rank": 5, "since": 1784646201, "since_min": 48}, {"sym": "CBRSUSDT", "base": "CBRS", "mark": "🟢", "why": "연료생존 — 진입검토", "alpha": 83, "g": [["흡수/이탈", "ACC +14", 14], ["VWAP", "VWAP 강한 돌파 +10", 10], ["MTF", "BTC 대비 초강세 +12", 12], ["오더북", "매도벽 압박 ×0.33 -8", -8], ["청산", "미미 $0K 0", 0], ["볼밴", "밴드 밖 진행중 — 이미 감 0", 0], ["스퀴즈", "정상 +0", 0], ["ATR", "정상 변동성 +0", 0], ["레인지", "레인지 상단 +6", 6], ["FLOW", "Flow +1", 1], ["SURGE", "×8.46 +18", 18], ["KIMCHI", "—", 0]], "conflict": ["볼밴 이미 감", "매도벽"], "onchain": null, "price": 198.08, "p24": 14.99, "oi4": 6.7, "oi1": 3.5, "cvd": 1.0, "fr": 0.0, "atr": 3.61, "flow": 0.4, "surge": 8.46, "ret4": 9.01, "bb_pos": 1.206, "bb_squeeze": false, "bb_just_broke": false, "rng": 0.948, "kimp": null, "liq": [0, 100.5426968, 1], "vwap_broke": false, "spot_fuel": false, "turnover": 28777352, "tradfi": false, "pinned": false, "rank": 6, "since": 1784642601, "since_min": 108}, {"sym": "SAMSUNGUSDT", "base": "SAMSUNG", "mark": "🟢", "why": "초입(+8%) + 연료 — 진입검토", "alpha": 57, "g": [["흡수/이탈", "ACC +14", 14], ["VWAP", "VWAP 강한 돌파 +10", 10], ["MTF", "BTC 동조화 +0", 0], ["오더북", "매도 우위 ×0.70 -4", -4], ["청산", "미미 $14K 0", 0], ["볼밴", "상단 접근 +6", 6], ["스퀴즈", "롱 과열 -4", -4], ["ATR", "낮은 변동성 +3", 3], ["레인지", "고점 돌파 +4", 4], ["FLOW", "Flow -2", -2], ["SURGE", "×1.11 +0", 0], ["KIMCHI", "—", 0]], "conflict": ["레인지 고점", "매도벽"], "onchain": null, "price": 183.15, "p24": 7.7, "oi4": 7.9, "oi1": 0.5, "cvd": 1.0, "fr": 0.0739, "atr": 1.35, "flow": -1.5, "surge": 1.11, "ret4": 2.22, "bb_pos": 0.906, "bb_squeeze": false, "bb_just_broke": false, "rng": 0.989, "kimp": null, "liq": [13800.6026801, 0, 5], "vwap_broke": false, "spot_fuel": false, "turnover": 103251449, "tradfi": true, "pinned": false, "rank": 7, "since": 1784646201, "since_min": 48}, {"sym": "EPICUSDT", "base": "EPIC", "mark": "🟢", "why": "연료생존 — 진입검토", "alpha": 49, "g": [["흡수/이탈", "— 0", 0], ["VWAP", "VWAP 강한 돌파 +10", 10], ["MTF", "BTC 대비 강세 +6", 6], ["오더북", "균형 ×0.94 +0", 0], ["청산", "미미 $10K 0", 0], ["볼밴", "상단 접근 +6", 6], ["스퀴즈", "정상 +0", 0], ["ATR", "정상 변동성 +0", 0], ["레인지", "레인지 상단 +6", 6], ["FLOW", "Flow -9", -9], ["SURGE", "×0.88 +0", 0], ["KIMCHI", "—", 0]], "conflict": ["이미 +25%"], "onchain": null, "price": 0.5453, "p24": 25.27, "oi4": 5.0, "oi1": -0.4, "cvd": 0.733, "fr": 0.005, "atr": 4.06, "flow": -5.8, "surge": 0.88, "ret4": 4.37, "bb_pos": 0.839, "bb_squeeze": false, "bb_just_broke": false, "rng": 0.926, "kimp": null, "liq": [3038.5869011, 10416.3688297, 32], "vwap_broke": false, "spot_fuel": false, "turnover": 28413315, "tradfi": false, "pinned": false, "rank": 8, "since": 1784646201, "since_min": 48}, {"sym": "ONDOUSDT", "base": "ONDO", "mark": "🟢", "why": "연료생존 — 진입검토", "alpha": 49, "g": [["흡수/이탈", "— 0", 0], ["VWAP", "VWAP 위 지지 +4", 4], ["MTF", "BTC 동조화 +0", 0], ["오더북", "균형 ×0.95 +0", 0], ["청산", "미미 $9K 0", 0], ["볼밴", "상단 접근 +6", 6], ["스퀴즈", "정상 +0", 0], ["ATR", "낮은 변동성 +3", 3], ["레인지", "레인지 상단 +6", 6], ["FLOW", "Flow +0", 0], ["SURGE", "×0.77 +0", 0], ["KIMCHI", "+0.06%", 0]], "conflict": ["이미 +16%"], "onchain": null, "price": 0.4081, "p24": 16.14, "oi4": 4.7, "oi1": 1.7, "cvd": 0.822, "fr": 0.005, "atr": 1.7, "flow": 0.1, "surge": 0.77, "ret4": 1.7, "bb_pos": 0.844, "bb_squeeze": false, "bb_just_broke": false, "rng": 0.936, "kimp": 0.06, "liq": [9323.991402239999, 2982.12604984, 38], "vwap_broke": false, "spot_fuel": false, "turnover": 165962313, "tradfi": false, "pinned": false, "rank": 9, "since": 1784646021, "since_min": 50}, {"sym": "AMDUSDT", "base": "AMD", "mark": "🟡", "why": "연료 약함 — 관찰", "alpha": 86, "g": [["흡수/이탈", "— 0", 0], ["VWAP", "VWAP 강한 돌파 +10", 10], ["MTF", "BTC 동조화 +0", 0], ["오더북", "매수벽 우위 ×1.55 +8", 8], ["청산", "미미 $7K 0", 0], ["볼밴", "상단 접근 +6", 6], ["스퀴즈", "정상 +0", 0], ["ATR", "낮은 변동성 +3", 3], ["레인지", "레인지 상단 +6", 6], ["FLOW", "Flow +5", 5], ["SURGE", "×4.89 +18", 18], ["KIMCHI", "—", 0]], "conflict": [], "onchain": null, "price": 534.1, "p24": 3.98, "oi4": 1.7, "oi1": -0.4, "cvd": 0.952, "fr": 0.0, "atr": 1.8, "flow": 3.2, "surge": 4.89, "ret4": 1.92, "bb_pos": 0.944, "bb_squeeze": false, "bb_just_broke": false, "rng": 0.945, "kimp": null, "liq": [6600.9979490000005, 0, 3], "vwap_broke": false, "spot_fuel": false, "turnover": 36763704, "tradfi": true, "pinned": false, "rank": 10, "since": 1784570602, "since_min": 1307}, {"sym": "BTCUSDT", "base": "BTC", "mark": "🟡", "why": "연료 약함 — 관찰", "alpha": 78, "g": [["흡수/이탈", "— 0", 0], ["VWAP", "VWAP 아래 저항 -4", -4], ["MTF", "BTC 동조화 +0", 0], ["오더북", "매수벽 우위 ×3.08 +8", 8], ["청산", "대형 숏청산 ★ $9838K +8", 8], ["볼밴", "상단 접근 +6", 6], ["스퀴즈", "정상 +0", 0], ["ATR", "극저 변동성 +6", 6], ["레인지", "레인지 상단 +6", 6], ["FLOW", "Flow +14", 14], ["SURGE", "×1.57 +4", 4], ["KIMCHI", "+0.06%", 0]], "conflict": [], "onchain": null, "price": 66640.0, "p24": 2.07, "oi4": 1.3, "oi1": 0.6, "cvd": 0.853, "fr": 0.002, "atr": 0.56, "flow": 8.5, "surge": 1.57, "ret4": 0.47, "bb_pos": 0.843, "bb_squeeze": false, "bb_just_broke": false, "rng": 0.845, "kimp": 0.06, "liq": [9838473.069400001, 1590380.58567, 258], "vwap_broke": true, "spot_fuel": false, "turnover": 10615045826, "tradfi": false, "pinned": true, "rank": 11, "since": 1784511858, "since_min": 2287}, {"sym": "MUUSDT", "base": "MU", "mark": "🟡", "why": "연료 약함 — 관찰", "alpha": 76, "g": [["흡수/이탈", "— 0", 0], ["VWAP", "VWAP 강한 돌파 +10", 10], ["MTF", "BTC 대비 강세 +6", 6], ["오더북", "매도벽 압박 ×0.52 -8", -8], ["청산", "대형 숏청산 ★ $459K +8", 8], ["볼밴", "밴드 밖 진행중 — 이미 감 0", 0], ["스퀴즈", "정상 +0", 0], ["ATR", "정상 변동성 +0", 0], ["레인지", "고점 돌파 +4", 4], ["FLOW", "Flow +8", 8], ["SURGE", "×3.47 +18", 18], ["KIMCHI", "—", 0]], "conflict": [], "onchain": null, "price": 954.77, "p24": 7.97, "oi4": 4.6, "oi1": 2.0, "cvd": 1.0, "fr": 0.0, "atr": 2.08, "flow": 5.3, "surge": 3.47, "ret4": 4.06, "bb_pos": 1.028, "bb_squeeze": false, "bb_just_broke": false, "rng": 0.975, "kimp": null, "liq": [458861.8763856, 47763.8230898, 58], "vwap_broke": false, "spot_fuel": false, "turnover": 1048047996, "tradfi": true, "pinned": false, "rank": 12, "since": 1784648721, "since_min": 6}, {"sym": "MVLLUSDT", "base": "MVLL", "mark": "🟡", "why": "연료 약함 — 관찰", "alpha": 74, "g": [["흡수/이탈", "— 0", 0], ["VWAP", "VWAP 강한 돌파 +10", 10], ["MTF", "BTC 동조화 +0", 0], ["오더북", "매수벽 우위 ×3.51 +8", 8], ["청산", "미미 $6K 0", 0], ["볼밴", "밴드 중단 0", 0], ["스퀴즈", "정상 +0", 0], ["ATR", "정상 변동성 +0", 0], ["레인지", "레인지 상단 +6", 6], ["FLOW", "Flow +2", 2], ["SURGE", "×3.62 +18", 18], ["KIMCHI", "—", 0]], "conflict": [], "onchain": null, "price": 26.11, "p24": 9.29, "oi4": 1.8, "oi1": 1.7, "cvd": 0.938, "fr": 0.0, "atr": 3.44, "flow": 1.2, "surge": 3.62, "ret4": 1.83, "bb_pos": 0.788, "bb_squeeze": false, "bb_just_broke": false, "rng": 0.904, "kimp": null, "liq": [32.170100000000005, 5540.1600938, 11], "vwap_broke": false, "spot_fuel": false, "turnover": 19250382, "tradfi": false, "pinned": false, "rank": 13, "since": 1784642601, "since_min": 108}, {"sym": "OPUSDT", "base": "OP", "mark": "🟡", "why": "연료 약함 — 관찰", "alpha": 68, "g": [["흡수/이탈", "— 0", 0], ["VWAP", "VWAP 위 지지 +4", 4], ["MTF", "BTC 동조화 +0", 0], ["오더북", "매수 우위 ×1.36 +4", 4], ["청산", "미미 $2K 0", 0], ["볼밴", "밴드 중단 0", 0], ["스퀴즈", "정상 +0", 0], ["ATR", "극저 변동성 +6", 6], ["레인지", "레인지 상단 +6", 6], ["FLOW", "Flow +18", 18], ["SURGE", "×0.83 +0", 0], ["KIMCHI", "+0.03%", 0]], "conflict": [], "onchain": null, "price": 0.0971, "p24": 3.74, "oi4": 3.2, "oi1": 1.1, "cvd": 0.814, "fr": 0.01, "atr": 0.9, "flow": 11.0, "surge": 0.83, "ret4": 0.21, "bb_pos": 0.746, "bb_squeeze": false, "bb_just_broke": false, "rng": 0.875, "kimp": 0.03, "liq": [1210.56423, 1590.6279699999998, 4], "vwap_broke": false, "spot_fuel": false, "turnover": 26998046, "tradfi": false, "pinned": false, "rank": 14, "since": 1784646201, "since_min": 48}, {"sym": "LTCUSDT", "base": "LTC", "mark": "🟡", "why": "연료 약함 — 관찰", "alpha": 67, "g": [["흡수/이탈", "— 0", 0], ["VWAP", "VWAP 위 지지 +4", 4], ["MTF", "BTC 동조화 +0", 0], ["오더북", "매수 우위 ×1.28 +4", 4], ["청산", "미미 $10K 0", 0], ["볼밴", "상단 접근 +6", 6], ["스퀴즈", "정상 +0", 0], ["ATR", "극저 변동성 +6", 6], ["레인지", "레인지 상단 +6", 6], ["FLOW", "Flow +7", 7], ["SURGE", "×1.67 +4", 4], ["KIMCHI", "—", 0]], "conflict": [], "onchain": null, "price": 47.79, "p24": 0.93, "oi4": 2.4, "oi1": 0.2, "cvd": 0.491, "fr": 0.0097, "atr": 0.74, "flow": 4.1, "surge": 1.67, "ret4": 0.82, "bb_pos": 0.908, "bb_squeeze": false, "bb_just_broke": false, "rng": 0.702, "kimp": null, "liq": [10358.60117, 100.149, 14], "vwap_broke": false, "spot_fuel": false, "turnover": 57745604, "tradfi": false, "pinned": false, "rank": 15, "since": 1784408538, "since_min": 4009}, {"sym": "QQQUSDT", "base": "QQQ", "mark": "🟡", "why": "연료 약함 — 관찰", "alpha": 66, "g": [["흡수/이탈", "— 0", 0], ["VWAP", "VWAP 위 지지 +4", 4], ["MTF", "BTC 동조화 +0", 0], ["오더북", "매수벽 우위 ×2.77 +8", 8], ["청산", "미미 $0K 0", 0], ["볼밴", "상단 접근 +6", 6], ["스퀴즈", "정상 +0", 0], ["ATR", "극저 변동성 +6", 6], ["레인지", "고점 돌파 +4", 4], ["FLOW", "Flow +0", 0], ["SURGE", "×2.37 +8", 8], ["KIMCHI", "—", 0]], "conflict": [], "onchain": null, "price": 708.66, "p24": 1.04, "oi4": 2.0, "oi1": 0.7, "cvd": 0.668, "fr": 0.0, "atr": 0.48, "flow": -0.2, "surge": 2.37, "ret4": 0.45, "bb_pos": 0.874, "bb_squeeze": false, "bb_just_broke": false, "rng": 0.952, "kimp": null, "liq": [0, 7.069800000000001, 1], "vwap_broke": false, "spot_fuel": false, "turnover": 157067246, "tradfi": true, "pinned": false, "rank": 16, "since": 1784502138, "since_min": 2449}, {"sym": "METAUSDT", "base": "META", "mark": "🟡", "why": "연료 약함 — 관찰", "alpha": 63, "g": [["흡수/이탈", "— 0", 0], ["VWAP", "VWAP 아래 저항 -4", -4], ["MTF", "BTC 동조화 +0", 0], ["오더북", "매수벽 우위 ×2.03 +8", 8], ["청산", "청산 데이터 없음 0", 0], ["볼밴", "밴드압축 1.3% — 대기 +4", 4], ["스퀴즈", "정상 +0", 0], ["ATR", "낮은 변동성 +3", 3], ["레인지", "레인지 내 0", 0], ["FLOW", "Flow +4", 4], ["SURGE", "×6.24 +18", 18], ["KIMCHI", "-100.00%", 0]], "conflict": [], "onchain": null, "price": 647.94, "p24": 0.03, "oi4": 4.3, "oi1": -1.6, "cvd": 0.239, "fr": 0.0, "atr": 1.06, "flow": 2.3, "surge": 6.24, "ret4": 0.3, "bb_pos": 0.597, "bb_squeeze": true, "bb_just_broke": false, "rng": 0.388, "kimp": -100.0, "liq": null, "vwap_broke": true, "spot_fuel": false, "turnover": 27169506, "tradfi": true, "pinned": false, "rank": 17, "since": 1784574023, "since_min": 1250}, {"sym": "JTOUSDT", "base": "JTO", "mark": "🟡", "why": "연료 약함 — 관찰", "alpha": 60, "g": [["흡수/이탈", "— 0", 0], ["VWAP", "VWAP 위 지지 +4", 4], ["MTF", "BTC 대비 강세 +6", 6], ["오더북", "매도벽 압박 ×0.55 -8", -8], ["청산", "미미 $9K 0", 0], ["볼밴", "압축+상단 — 돌파임박 ★ +12", 12], ["스퀴즈", "정상 +0", 0], ["ATR", "정상 변동성 +0", 0], ["레인지", "레인지 상단 +6", 6], ["FLOW", "Flow -8", -8], ["SURGE", "×3.07 +18", 18], ["KIMCHI", "+0.11%", 0]], "conflict": [], "onchain": null, "price": 0.6231, "p24": 2.03, "oi4": 4.3, "oi1": 2.0, "cvd": 0.89, "fr": 0.005, "atr": 2.82, "flow": -5.0, "surge": 3.07, "ret4": 2.67, "bb_pos": 0.821, "bb_squeeze": true, "bb_just_broke": false, "rng": 0.736, "kimp": 0.11, "liq": [9036.755239, 42.5062, 14], "vwap_broke": false, "spot_fuel": false, "turnover": 27697261, "tradfi": false, "pinned": false, "rank": 18, "since": 1784646201, "since_min": 48}, {"sym": "ETHUSDT", "base": "ETH", "mark": "🟡", "why": "연료 약함 — 관찰", "alpha": 59, "g": [["흡수/이탈", "— 0", 0], ["VWAP", "VWAP 아래 저항 -4", -4], ["MTF", "BTC 동조화 +0", 0], ["오더북", "매수벽 우위 ×8.03 +8", 8], ["청산", "대형 숏청산 ★ $2104K +8", 8], ["볼밴", "밴드압축 3.0% — 대기 +4", 4], ["스퀴즈", "정상 +0", 0], ["ATR", "극저 변동성 +6", 6], ["레인지", "레인지 상단 +6", 6], ["FLOW", "Flow +1", 1], ["SURGE", "×1.00 +0", 0], ["KIMCHI", "+0.04%", 0]], "conflict": [], "onchain": null, "price": 1928.76, "p24": 1.72, "oi4": 0.1, "oi1": -0.3, "cvd": 0.241, "fr": 0.0032, "atr": 0.71, "flow": 0.6, "surge": 1.0, "ret4": -0.3, "bb_pos": 0.591, "bb_squeeze": true, "bb_just_broke": false, "rng": 0.623, "kimp": 0.04, "liq": [2104109.6807600004, 633894.08075, 168], "vwap_broke": true, "spot_fuel": false, "turnover": 7718879988, "tradfi": false, "pinned": true, "rank": 19, "since": 1784635222, "since_min": 230}, {"sym": "HOMEUSDT", "base": "HOME", "mark": "🟡", "why": "연료 약함 — 관찰", "alpha": 58, "g": [["흡수/이탈", "— 0", 0], ["VWAP", "VWAP 위 지지 +4", 4], ["MTF", "BTC 동조화 +0", 0], ["오더북", "매수 우위 ×1.26 +4", 4], ["청산", "미미 $3K 0", 0], ["볼밴", "밴드압축 8.0% — 대기 +4", 4], ["스퀴즈", "대형 FR스퀴즈 ★ +8", 8], ["ATR", "낮은 변동성 +3", 3], ["레인지", "레인지 내 0", 0], ["FLOW", "Flow +5", 5], ["SURGE", "×0.85 +0", 0], ["KIMCHI", "—", 0]], "conflict": [], "onchain": null, "price": 0.00674, "p24": -11.89, "oi4": 3.8, "oi1": 1.1, "cvd": 0.511, "fr": -0.2988, "atr": 1.97, "flow": 2.9, "surge": 0.85, "ret4": 0.75, "bb_pos": 0.256, "bb_squeeze": true, "bb_just_broke": false, "rng": 0.144, "kimp": null, "liq": [301.65902, 3418.94526, 18], "vwap_broke": false, "spot_fuel": false, "turnover": 23852459, "tradfi": false, "pinned": false, "rank": 20, "since": 1784649081, "since_min": 0}, {"sym": "CLUSDT", "base": "CL", "mark": "🟡", "why": "연료 약함 — 관찰", "alpha": 58, "g": [["흡수/이탈", "— 0", 0], ["VWAP", "VWAP 위 지지 +4", 4], ["MTF", "BTC 동조화 +0", 0], ["오더북", "균형 ×1.14 +0", 0], ["청산", "↑ 숏청산 우위 $106K +5", 5], ["볼밴", "상단 접근 +6", 6], ["스퀴즈", "FR스퀴즈 중 +5", 5], ["ATR", "낮은 변동성 +3", 3], ["레인지", "레인지 상단 +6", 6], ["FLOW", "Flow -5", -5], ["SURGE", "×1.75 +4", 4], ["KIMCHI", "—", 0]], "conflict": [], "onchain": null, "price": 84.54, "p24": 3.65, "oi4": 1.9, "oi1": 0.7, "cvd": 0.773, "fr": -0.0172, "atr": 1.16, "flow": -3.4, "surge": 1.75, "ret4": 0.81, "bb_pos": 0.954, "bb_squeeze": false, "bb_just_broke": false, "rng": 0.866, "kimp": null, "liq": [105566.4236, 19263.8228, 40], "vwap_broke": false, "spot_fuel": false, "turnover": 731377061, "tradfi": false, "pinned": false, "rank": 21, "since": 1784563223, "since_min": 1430}, {"sym": "BILLUSDT", "base": "BILL", "mark": "🟡", "why": "연료 약함 — 관찰", "alpha": 54, "g": [["흡수/이탈", "— 0", 0], ["VWAP", "VWAP 강한 돌파 +10", 10], ["MTF", "BTC 대비 강세 +6", 6], ["오더북", "균형 ×1.00 +0", 0], ["청산", "미미 $0K 0", 0], ["볼밴", "밴드 밖 진행중 — 이미 감 0", 0], ["스퀴즈", "FR스퀴즈 중 +5", 5], ["ATR", "정상 변동성 +0", 0], ["레인지", "레인지 상단 +6", 6], ["FLOW", "Flow -3", -3], ["SURGE", "×1.29 +0", 0], ["KIMCHI", "—", 0]], "conflict": [], "onchain": {"src": "cold", "score": 73, "mark": "🟢", "grade": "강한 펌프 가능성", "cold_score": 73, "cold_usd": 33392242, "cold_n": 8, "cold_wallets": 3, "cold_days": 22.8, "peak": 0.2, "accum_score": null, "accum_usd": null, "accum_wallets": null, "accum_wd": null, "accum_days": null, "conc": false}, "price": 0.02508, "p24": -0.75, "oi4": -0.1, "oi1": -0.3, "cvd": 0.877, "fr": -0.0293, "atr": 2.8, "flow": -1.6, "surge": 1.29, "ret4": 4.01, "bb_pos": 1.12, "bb_squeeze": false, "bb_just_broke": false, "rng": 0.842, "kimp": null, "liq": [54.12245, 96.04499999999999, 3], "vwap_broke": false, "spot_fuel": false, "turnover": 7931743, "tradfi": false, "pinned": true, "rank": 22, "since": 1784512938, "since_min": 2269}, {"sym": "LAUSDT", "base": "LA", "mark": "🟡", "why": "연료 약함 — 관찰", "alpha": 48, "g": [["흡수/이탈", "ACC +14", 14], ["VWAP", "VWAP 아래 저항 -4", -4], ["MTF", "BTC 동조화 +0", 0], ["오더북", "매수벽 우위 ×1.65 +8", 8], ["청산", "↓ 롱청산 우위 $33K -6", -6], ["볼밴", "밴드압축 30.2% — 대기 +4", 4], ["스퀴즈", "대형 FR스퀴즈 ★ +8", 8], ["ATR", "정상 변동성 +0", 0], ["레인지", "레인지 내 0", 0], ["FLOW", "Flow -6", -6], ["SURGE", "×0.52 +0", 0], ["KIMCHI", "+1.60%", 0]], "conflict": [], "onchain": null, "price": 0.05756, "p24": 14.5, "oi4": 9.4, "oi1": 3.0, "cvd": 0.236, "fr": -1.1482, "atr": 4.35, "flow": -3.9, "surge": 0.52, "ret4": -2.14, "bb_pos": 0.579, "bb_squeeze": true, "bb_just_broke": false, "rng": 0.434, "kimp": 1.6, "liq": [15445.5257617, 33219.238595, 74], "vwap_broke": true, "spot_fuel": false, "turnover": 104172356, "tradfi": false, "pinned": false, "rank": 23, "since": 1784645661, "since_min": 57}, {"sym": "BABAUSDT", "base": "BABA", "mark": "🟡", "why": "연료 약함 — 관찰", "alpha": 44, "g": [["흡수/이탈", "ACC +14", 14], ["VWAP", "VWAP 아래 저항 -4", -4], ["MTF", "BTC 동조화 +0", 0], ["오더북", "매수 우위 ×1.37 +4", 4], ["청산", "청산 데이터 없음 0", 0], ["볼밴", "밴드 하단 -3", -3], ["스퀴즈", "정상 +0", 0], ["ATR", "극저 변동성 +6", 6], ["레인지", "레인지 내 0", 0], ["FLOW", "Flow -21", -21], ["SURGE", "×3.65 +18", 18], ["KIMCHI", "—", 0]], "conflict": [], "onchain": null, "price": 118.33, "p24": -2.39, "oi4": 7.2, "oi1": 1.7, "cvd": 0.364, "fr": 0.0064, "atr": 0.91, "flow": -13.3, "surge": 3.65, "ret4": -0.67, "bb_pos": 0.126, "bb_squeeze": false, "bb_just_broke": false, "rng": 0.114, "kimp": null, "liq": null, "vwap_broke": true, "spot_fuel": false, "turnover": 20211688, "tradfi": true, "pinned": false, "rank": 24, "since": 1784642601, "since_min": 108}, {"sym": "VIRTUALUSDT", "base": "VIRTUAL", "mark": "🟡", "why": "연료 약함 — 관찰", "alpha": 43, "g": [["흡수/이탈", "— 0", 0], ["VWAP", "VWAP 위 지지 +4", 4], ["MTF", "BTC 동조화 +0", 0], ["오더북", "균형 ×0.95 +0", 0], ["청산", "미미 $3K 0", 0], ["볼밴", "상단 접근 +6", 6], ["스퀴즈", "정상 +0", 0], ["ATR", "낮은 변동성 +3", 3], ["레인지", "레인지 상단 +6", 6], ["FLOW", "Flow -6", -6], ["SURGE", "×1.19 +0", 0], ["KIMCHI", "-0.23%", 0]], "conflict": [], "onchain": null, "price": 0.6705, "p24": 3.63, "oi4": 2.2, "oi1": 1.1, "cvd": 0.717, "fr": 0.005, "atr": 1.54, "flow": -3.8, "surge": 1.19, "ret4": -0.06, "bb_pos": 0.818, "bb_squeeze": false, "bb_just_broke": false, "rng": 0.746, "kimp": -0.23, "liq": [2710.50577704, 1809.1012385099998, 6], "vwap_broke": false, "spot_fuel": false, "turnover": 26200117, "tradfi": false, "pinned": false, "rank": 25, "since": 1784646201, "since_min": 48}, {"sym": "GOOGLUSDT", "base": "GOOGL", "mark": "🟡", "why": "연료 약함 — 관찰", "alpha": 41, "g": [["흡수/이탈", "ACC +14", 14], ["VWAP", "VWAP 아래 저항 -4", -4], ["MTF", "BTC 동조화 +0", 0], ["오더북", "매수벽 우위 ×5.99 +8", 8], ["청산", "미미 $2K 0", 0], ["볼밴", "밴드 하단 -3", -3], ["스퀴즈", "정상 +0", 0], ["ATR", "극저 변동성 +6", 6], ["레인지", "레인지 내 0", 0], ["FLOW", "Flow -14", -14], ["SURGE", "×1.63 +4", 4], ["KIMCHI", "—", 0]], "conflict": [], "onchain": null, "price": 349.61, "p24": -2.05, "oi4": 9.0, "oi1": 1.7, "cvd": 0.334, "fr": 0.0006, "atr": 0.82, "flow": -8.8, "surge": 1.63, "ret4": -0.92, "bb_pos": 0.025, "bb_squeeze": false, "bb_just_broke": false, "rng": 0.174, "kimp": null, "liq": [2118.989692, 0, 2], "vwap_broke": true, "spot_fuel": false, "turnover": 48844669, "tradfi": true, "pinned": false, "rank": 26, "since": 1784628023, "since_min": 350}, {"sym": "IBMUSDT", "base": "IBM", "mark": "🟡", "why": "연료 약함 — 관찰", "alpha": 40, "g": [["흡수/이탈", "— 0", 0], ["VWAP", "VWAP 아래 저항 -4", -4], ["MTF", "BTC 동조화 +0", 0], ["오더북", "매수벽 우위 ×1.59 +8", 8], ["청산", "미미 $5K 0", 0], ["볼밴", "밴드 하단 -3", -3], ["스퀴즈", "정상 +0", 0], ["ATR", "낮은 변동성 +3", 3], ["레인지", "레인지 내 0", 0], ["FLOW", "Flow -12", -12], ["SURGE", "×3.42 +18", 18], ["KIMCHI", "—", 0]], "conflict": [], "onchain": null, "price": 210.75, "p24": -0.32, "oi4": 4.7, "oi1": 1.9, "cvd": 0.067, "fr": 0.0, "atr": 1.17, "flow": -7.2, "surge": 3.42, "ret4": -0.39, "bb_pos": 0.026, "bb_squeeze": false, "bb_just_broke": false, "rng": 0.175, "kimp": null, "liq": [0, 5270.2265, 1], "vwap_broke": true, "spot_fuel": false, "turnover": 21099878, "tradfi": false, "pinned": false, "rank": 27, "since": 1784639001, "since_min": 167}, {"sym": "HEMIUSDT", "base": "HEMI", "mark": "🟡", "why": "연료 약함 — 관찰", "alpha": 40, "g": [["흡수/이탈", "— 0", 0], ["VWAP", "VWAP 강한 돌파 +10", 10], ["MTF", "BTC 동조화 +0", 0], ["오더북", "매수 우위 ×1.23 +4", 4], ["청산", "미미 $4K 0", 0], ["볼밴", "밴드 중단 0", 0], ["스퀴즈", "정상 +0", 0], ["ATR", "정상 변동성 +0", 0], ["레인지", "저점 근접 -6", -6], ["FLOW", "Flow +2", 2], ["SURGE", "×0.31 +0", 0], ["KIMCHI", "—", 0]], "conflict": [], "onchain": null, "price": 0.005288, "p24": -8.61, "oi4": 4.0, "oi1": 0.1, "cvd": 0.514, "fr": 0.005, "atr": 3.31, "flow": 1.2, "surge": 0.31, "ret4": 1.93, "bb_pos": 0.269, "bb_squeeze": false, "bb_just_broke": false, "rng": 0.078, "kimp": null, "liq": [440.16553440000007, 4022.050811, 20], "vwap_broke": false, "spot_fuel": false, "turnover": 159686172, "tradfi": false, "pinned": false, "rank": 28, "since": 1784648181, "since_min": 14}, {"sym": "NATGASUSDT", "base": "NATGAS", "mark": "🟡", "why": "연료 약함 — 관찰", "alpha": 39, "g": [["흡수/이탈", "— 0", 0], ["VWAP", "VWAP 위 지지 +4", 4], ["MTF", "BTC 동조화 +0", 0], ["오더북", "매도 우위 ×0.83 -4", -4], ["청산", "미미 $0K 0", 0], ["볼밴", "밴드 중단 0", 0], ["스퀴즈", "정상 +0", 0], ["ATR", "극저 변동성 +6", 6], ["레인지", "레인지 내 0", 0], ["FLOW", "Flow -5", -5], ["SURGE", "×2.58 +8", 8], ["KIMCHI", "—", 0]], "conflict": [], "onchain": null, "price": 2.85, "p24": 0.92, "oi4": 4.1, "oi1": 0.2, "cvd": 0.484, "fr": 0.0, "atr": 0.84, "flow": -3.0, "surge": 2.58, "ret4": -0.14, "bb_pos": 0.62, "bb_squeeze": false, "bb_just_broke": false, "rng": 0.576, "kimp": null, "liq": [0, 230.4051, 1], "vwap_broke": false, "spot_fuel": false, "turnover": 18435652, "tradfi": false, "pinned": false, "rank": 29, "since": 1784566821, "since_min": 1371}, {"sym": "LINKUSDT", "base": "LINK", "mark": "🟡", "why": "연료 약함 — 관찰", "alpha": 35, "g": [["흡수/이탈", "— 0", 0], ["VWAP", "VWAP 아래 저항 -4", -4], ["MTF", "BTC 동조화 +0", 0], ["오더북", "균형 ×0.94 +0", 0], ["청산", "미미 $8K 0", 0], ["볼밴", "밴드압축 3.0% — 대기 +4", 4], ["스퀴즈", "정상 +0", 0], ["ATR", "극저 변동성 +6", 6], ["레인지", "레인지 상단 +6", 6], ["FLOW", "Flow -7", -7], ["SURGE", "×0.80 +0", 0], ["KIMCHI", "-0.04%", 0]], "conflict": [], "onchain": {"src": "cold", "score": 73, "mark": "🟢", "grade": "강한 펌프 가능성", "cold_score": 73, "cold_usd": 18610326, "cold_n": 9, "cold_wallets": 10, "cold_days": 33.2, "peak": 10.9, "accum_score": null, "accum_usd": null, "accum_wallets": null, "accum_wd": null, "accum_days": null, "conc": false}, "price": 8.69, "p24": 1.95, "oi4": 0.3, "oi1": 0.2, "cvd": 0.746, "fr": 0.01, "atr": 0.6, "flow": -4.3, "surge": 0.8, "ret4": -0.17, "bb_pos": 0.611, "bb_squeeze": true, "bb_just_broke": false, "rng": 0.726, "kimp": -0.04, "liq": [8278.22868, 28.544999999999998, 4], "vwap_broke": true, "spot_fuel": false, "turnover": 84961324, "tradfi": false, "pinned": true, "rank": 30, "since": 1784620823, "since_min": 470}, {"sym": "SOLUSDT", "base": "SOL", "mark": "🟡", "why": "연료 약함 — 관찰", "alpha": 33, "g": [["흡수/이탈", "— 0", 0], ["VWAP", "VWAP 아래 저항 -4", -4], ["MTF", "BTC 동조화 +0", 0], ["오더북", "균형 ×1.07 +0", 0], ["청산", "혼조 0", 0], ["볼밴", "밴드압축 1.6% — 대기 +4", 4], ["스퀴즈", "정상 +0", 0], ["ATR", "극저 변동성 +6", 6], ["레인지", "레인지 내 0", 0], ["FLOW", "Flow -7", -7], ["SURGE", "×1.49 +4", 4], ["KIMCHI", "+0.08%", 0]], "conflict": [], "onchain": null, "price": 78.05, "p24": 0.79, "oi4": -0.1, "oi1": -0.2, "cvd": 0.643, "fr": 0.0027, "atr": 0.6, "flow": -4.6, "surge": 1.49, "ret4": -0.37, "bb_pos": 0.418, "bb_squeeze": true, "bb_just_broke": false, "rng": 0.478, "kimp": 0.08, "liq": [127555.257256, 100263.4462, 41], "vwap_broke": true, "spot_fuel": false, "turnover": 1078596923, "tradfi": false, "pinned": true, "rank": 31, "since": 1784516538, "since_min": 2209}, {"sym": "RIFUSDT", "base": "RIF", "mark": "🔴", "why": "하락 중 -31% — 롱 근거 없음", "alpha": 61, "g": [["흡수/이탈", "ACC +28", 28], ["VWAP", "VWAP 강한 돌파 +10", 10], ["MTF", "BTC 대비 약세 -6", -6], ["오더북", "균형 ×0.92 +0", 0], ["청산", "↓ 롱청산 우위 $101K -6", -6], ["볼밴", "밴드 하단 -3", -3], ["스퀴즈", "정상 +0", 0], ["ATR", "고변동성 -4", -4], ["레인지", "레인지 내 0", 0], ["FLOW", "Flow -6", -6], ["SURGE", "×4.19 +18", 18], ["KIMCHI", "—", 0]], "conflict": [], "onchain": null, "price": 0.0857, "p24": -30.8, "oi4": 21.0, "oi1": 4.1, "cvd": 0.191, "fr": 0.0012, "atr": 14.35, "flow": -4.0, "surge": 4.19, "ret4": -14.7, "bb_pos": 0.095, "bb_squeeze": false, "bb_just_broke": false, "rng": 0.219, "kimp": null, "liq": [42342.2817137, 101181.845814, 190], "vwap_broke": false, "spot_fuel": false, "turnover": 27410144, "tradfi": false, "pinned": false, "rank": 32, "since": 1784640081, "since_min": 149}, {"sym": "ERAUSDT", "base": "ERA", "mark": "🔴", "why": "수직급등 +64% — 과열 추격금지", "alpha": 59, "g": [["흡수/이탈", "— 0", 0], ["VWAP", "VWAP 아래 저항 -4", -4], ["MTF", "BTC 대비 강세 +6", 6], ["오더북", "매수벽 우위 ×1.82 +8", 8], ["청산", "↑ 숏청산 우위 $140K +5", 5], ["볼밴", "밴드압축 66.2% — 대기 +4", 4], ["스퀴즈", "대형 FR스퀴즈 ★ +8", 8], ["ATR", "고변동성 -4", -4], ["레인지", "레인지 상단 +6", 6], ["FLOW", "Flow +0", 0], ["SURGE", "×0.89 +0", 0], ["KIMCHI", "+2.67%", 0]], "conflict": [], "onchain": null, "price": 0.1006, "p24": 63.58, "oi4": 19.6, "oi1": 2.0, "cvd": 0.496, "fr": -1.3983, "atr": 7.45, "flow": -0.1, "surge": 0.89, "ret4": 3.05, "bb_pos": 0.688, "bb_squeeze": true, "bb_just_broke": false, "rng": 0.793, "kimp": 2.67, "liq": [139574.92212920001, 68802.0125292, 227], "vwap_broke": true, "spot_fuel": false, "turnover": 400151349, "tradfi": false, "pinned": false, "rank": 33, "since": 1784637742, "since_min": 188}, {"sym": "PROMUSDT", "base": "PROM", "mark": "🔴", "why": "하락 중 -31% — 롱 근거 없음", "alpha": 57, "g": [["흡수/이탈", "ACC +14", 14], ["VWAP", "VWAP 위 지지 +4", 4], ["MTF", "BTC 동조화 +0", 0], ["오더북", "매수 우위 ×1.25 +4", 4], ["청산", "미미 $6K 0", 0], ["볼밴", "밴드압축 28.6% — 대기 +4", 4], ["스퀴즈", "정상 +0", 0], ["ATR", "정상 변동성 +0", 0], ["레인지", "레인지 내 0", 0], ["FLOW", "Flow +1", 1], ["SURGE", "×0.53 +0", 0], ["KIMCHI", "—", 0]], "conflict": [], "onchain": null, "price": 1.679, "p24": -31.05, "oi4": 6.4, "oi1": 0.6, "cvd": 0.232, "fr": -0.0086, "atr": 4.04, "flow": 0.5, "surge": 0.53, "ret4": 1.08, "bb_pos": 0.26, "bb_squeeze": true, "bb_just_broke": false, "rng": 0.102, "kimp": null, "liq": [2543.51709426, 5501.21254609, 30], "vwap_broke": false, "spot_fuel": false, "turnover": 108944733, "tradfi": false, "pinned": false, "rank": 34, "since": 1784639361, "since_min": 161}, {"sym": "DEXEUSDT", "base": "DEXE", "mark": "🔴", "why": "하락 중 -73% — 롱 근거 없음", "alpha": 42, "g": [["흡수/이탈", "ACC +28", 28], ["VWAP", "VWAP 아래 저항 -4", -4], ["MTF", "BTC 대비 약세 -6", -6], ["오더북", "매수 우위 ×1.32 +4", 4], ["청산", "혼조 0", 0], ["볼밴", "밴드 하단 -3", -3], ["스퀴즈", "대형 FR스퀴즈 ★ +8", 8], ["ATR", "고변동성 -4", -4], ["레인지", "저점 근접 -6", -6], ["FLOW", "Flow -5", -5], ["SURGE", "×1.09 +0", 0], ["KIMCHI", "—", 0]], "conflict": [], "onchain": null, "price": 9.48, "p24": -72.92, "oi4": 20.5, "oi1": 10.5, "cvd": 0.588, "fr": -0.8034, "atr": 25.14, "flow": -3.2, "surge": 1.09, "ret4": -25.36, "bb_pos": 0.081, "bb_squeeze": false, "bb_just_broke": false, "rng": 0.033, "kimp": null, "liq": [324220.10330927, 335255.11712483, 644], "vwap_broke": true, "spot_fuel": false, "turnover": 452726694, "tradfi": false, "pinned": false, "rank": 35, "since": 1784642601, "since_min": 108}]}