{"updated": "2026-07-21 20:09:21", "updated_ts": 1784632161, "scan_sec": 180, "us_open": false, "ws": true, "liq_events": 40914, "count": 34, "cols": ["흡수/이탈", "VWAP", "MTF", "오더북", "청산", "볼밴", "스퀴즈", "ATR", "레인지", "FLOW", "SURGE", "KIMCHI"], "rows": [{"sym": "ONDOUSDT", "base": "ONDO", "mark": "💎", "why": "순위권 + 강한연료 — 아직 갈 자리", "alpha": 71, "g": [["흡수/이탈", "— 0", 0], ["VWAP", "VWAP 강한 돌파 +10", 10], ["MTF", "BTC 대비 강세 +6", 6], ["오더북", "매수 우위 ×1.22 +4", 4], ["청산", "↑ 숏청산 우위 $142K +5", 5], ["볼밴", "밴드 밖 진행중 — 이미 감 0", 0], ["스퀴즈", "정상 +0", 0], ["ATR", "정상 변동성 +0", 0], ["레인지", "레인지 상단 +6", 6], ["FLOW", "Flow +2", 2], ["SURGE", "×2.20 +8", 8], ["KIMCHI", "-0.21%", 0]], "conflict": ["볼밴 이미 감", "이미 +16%"], "onchain": null, "price": 0.4051, "p24": 15.88, "oi4": 13.3, "oi1": 2.5, "cvd": 0.72, "fr": 0.005, "atr": 2.59, "flow": 1.2, "surge": 2.2, "ret4": 3.74, "bb_pos": 1.013, "bb_squeeze": false, "bb_just_broke": false, "rng": 0.942, "kimp": -0.21, "liq": [142367.3817944, 20113.23018062, 91], "vwap_broke": false, "spot_fuel": false, "turnover": 140756380, "tradfi": false, "pinned": false, "rank": 1, "since": 1784628201, "since_min": 65}, {"sym": "MUUUSDT", "base": "MUU", "mark": "💎", "why": "초입(+6%) + 강한연료 — 노다지", "alpha": 47, "g": [["흡수/이탈", "ACC +28", 28], ["VWAP", "VWAP 아래 저항 -4", -4], ["MTF", "BTC 동조화 +0", 0], ["오더북", "매도벽 압박 ×0.47 -8", -8], ["청산", "미미 $3K 0", 0], ["볼밴", "상단 접근 +6", 6], ["스퀴즈", "정상 +0", 0], ["ATR", "낮은 변동성 +3", 3], ["레인지", "레인지 상단 +6", 6], ["FLOW", "Flow -18", -18], ["SURGE", "×1.43 +4", 4], ["KIMCHI", "—", 0]], "conflict": ["VWAP 아래", "매도벽"], "onchain": null, "price": 31.74, "p24": 6.3, "oi4": 33.0, "oi1": 9.3, "cvd": 0.774, "fr": 0.0, "atr": 1.69, "flow": -11.2, "surge": 1.43, "ret4": 1.44, "bb_pos": 0.85, "bb_squeeze": false, "bb_just_broke": false, "rng": 0.875, "kimp": null, "liq": [3495.0938613000003, 0, 5], "vwap_broke": true, "spot_fuel": false, "turnover": 18717541, "tradfi": false, "pinned": false, "rank": 2, "since": 1784588421, "since_min": 728}, {"sym": "ETHUSDT", "base": "ETH", "mark": "⭐", "why": "현물주도 상승 — 실제 돈", "alpha": 57, "g": [["흡수/이탈", "— 0", 0], ["VWAP", "VWAP 아래 저항 -4", -4], ["MTF", "BTC 동조화 +0", 0], ["오더북", "매도벽 압박 ×0.14 -8", -8], ["청산", "대형 숏청산 ★ $3323K +8", 8], ["볼밴", "밴드압축 3.2% — 대기 +4", 4], ["스퀴즈", "정상 +0", 0], ["ATR", "극저 변동성 +6", 6], ["레인지", "레인지 상단 +6", 6], ["FLOW", "Flow +11", 11], ["SURGE", "×1.43 +4", 4], ["KIMCHI", "-0.04%", 0]], "conflict": ["VWAP 아래", "매도벽"], "onchain": null, "price": 1930.28, "p24": 2.93, "oi4": 1.0, "oi1": -0.1, "cvd": 0.765, "fr": -0.0009, "atr": 0.63, "flow": 7.0, "surge": 1.43, "ret4": -0.16, "bb_pos": 0.723, "bb_squeeze": true, "bb_just_broke": false, "rng": 0.768, "kimp": -0.04, "liq": [3322574.4491, 335747.36846, 230], "vwap_broke": true, "spot_fuel": true, "turnover": 9001657352, "tradfi": false, "pinned": true, "rank": 3, "since": 1784628201, "since_min": 65}, {"sym": "VIRTUALUSDT", "base": "VIRTUAL", "mark": "🟢", "why": "연료생존 — 진입검토", "alpha": 74, "g": [["흡수/이탈", "ACC +14", 14], ["VWAP", "VWAP 위 지지 +4", 4], ["MTF", "BTC 동조화 +0", 0], ["오더북", "매수 우위 ×1.34 +4", 4], ["청산", "미미 $8K 0", 0], ["볼밴", "상단 접근 +6", 6], ["스퀴즈", "정상 +0", 0], ["ATR", "낮은 변동성 +3", 3], ["레인지", "레인지 상단 +6", 6], ["FLOW", "Flow +3", 3], ["SURGE", "×1.43 +4", 4], ["KIMCHI", "+0.01%", 0]], "conflict": [], "onchain": null, "price": 0.6709, "p24": 8.95, "oi4": 5.5, "oi1": 5.9, "cvd": 0.807, "fr": 0.005, "atr": 1.38, "flow": 2.1, "surge": 1.43, "ret4": 1.51, "bb_pos": 0.985, "bb_squeeze": false, "bb_just_broke": false, "rng": 0.912, "kimp": 0.01, "liq": [7920.76541165, 688.5580806, 16], "vwap_broke": false, "spot_fuel": false, "turnover": 33222803, "tradfi": false, "pinned": false, "rank": 4, "since": 1784631801, "since_min": 5}, {"sym": "LITEUSDT", "base": "LITE", "mark": "🟢", "why": "초입(+6%) + 연료 — 진입검토", "alpha": 72, "g": [["흡수/이탈", "ACC +14", 14], ["VWAP", "VWAP 위 지지 +4", 4], ["MTF", "BTC 동조화 +0", 0], ["오더북", "매수벽 우위 ×4.52 +8", 8], ["청산", "청산 데이터 없음 0", 0], ["볼밴", "상단 접근 +6", 6], ["스퀴즈", "정상 +0", 0], ["ATR", "극저 변동성 +6", 6], ["레인지", "레인지 상단 +6", 6], ["FLOW", "Flow -6", -6], ["SURGE", "×1.59 +4", 4], ["KIMCHI", "—", 0]], "conflict": [], "onchain": null, "price": 802.74, "p24": 5.61, "oi4": 6.6, "oi1": 1.4, "cvd": 0.979, "fr": 0.0, "atr": 0.63, "flow": -3.5, "surge": 1.59, "ret4": 0.74, "bb_pos": 0.843, "bb_squeeze": false, "bb_just_broke": false, "rng": 0.919, "kimp": null, "liq": null, "vwap_broke": false, "spot_fuel": false, "turnover": 30605163, "tradfi": false, "pinned": false, "rank": 5, "since": 1784628201, "since_min": 65}, {"sym": "ENAUSDT", "base": "ENA", "mark": "🟢", "why": "연료생존 — 진입검토", "alpha": 60, "g": [["흡수/이탈", "— 0", 0], ["VWAP", "VWAP 위 지지 +4", 4], ["MTF", "BTC 동조화 +0", 0], ["오더북", "균형 ×0.94 +0", 0], ["청산", "↑ 숏청산 우위 $47K +5", 5], ["볼밴", "압축+상단 — 돌파임박 ★ +12", 12], ["스퀴즈", "정상 +0", 0], ["ATR", "낮은 변동성 +3", 3], ["레인지", "레인지 상단 +6", 6], ["FLOW", "Flow -4", -4], ["SURGE", "×1.53 +4", 4], ["KIMCHI", "+0.03%", 0]], "conflict": [], "onchain": null, "price": 0.08684, "p24": 8.86, "oi4": 4.8, "oi1": 4.4, "cvd": 0.808, "fr": 0.005, "atr": 1.31, "flow": -2.8, "surge": 1.53, "ret4": 1.24, "bb_pos": 0.947, "bb_squeeze": true, "bb_just_broke": false, "rng": 0.898, "kimp": 0.03, "liq": [46879.1992914, 19915.765985000002, 19], "vwap_broke": false, "spot_fuel": false, "turnover": 82908243, "tradfi": false, "pinned": false, "rank": 6, "since": 1784631801, "since_min": 5}, {"sym": "SNDKUSDT", "base": "SNDK", "mark": "🟢", "why": "초입(+5%) + 연료 — 진입검토", "alpha": 49, "g": [["흡수/이탈", "ACC +14", 14], ["VWAP", "VWAP 아래 저항 -4", -4], ["MTF", "BTC 동조화 +0", 0], ["오더북", "매도벽 압박 ×0.64 -8", -8], ["청산", "↑ 숏청산 우위 $196K +5", 5], ["볼밴", "상단 접근 +6", 6], ["스퀴즈", "정상 +0", 0], ["ATR", "낮은 변동성 +3", 3], ["레인지", "레인지 상단 +6", 6], ["FLOW", "Flow -3", -3], ["SURGE", "×0.94 +0", 0], ["KIMCHI", "—", 0]], "conflict": ["VWAP 아래", "매도벽"], "onchain": null, "price": 1493.53, "p24": 5.26, "oi4": 5.2, "oi1": 0.1, "cvd": 0.725, "fr": 0.0, "atr": 1.35, "flow": -1.8, "surge": 0.94, "ret4": 0.34, "bb_pos": 0.802, "bb_squeeze": false, "bb_just_broke": false, "rng": 0.834, "kimp": null, "liq": [196110.0968275, 19403.6888535, 75], "vwap_broke": true, "spot_fuel": false, "turnover": 2650762585, "tradfi": true, "pinned": false, "rank": 7, "since": 1784628201, "since_min": 65}, {"sym": "SNXXUSDT", "base": "SNXX", "mark": "🟢", "why": "연료생존 — 진입검토", "alpha": 34, "g": [["흡수/이탈", "— 0", 0], ["VWAP", "VWAP 아래 저항 -4", -4], ["MTF", "BTC 동조화 +0", 0], ["오더북", "균형 ×1.09 +0", 0], ["청산", "미미 $3K 0", 0], ["볼밴", "상단 접근 +6", 6], ["스퀴즈", "정상 +0", 0], ["ATR", "정상 변동성 +0", 0], ["레인지", "레인지 상단 +6", 6], ["FLOW", "Flow -4", -4], ["SURGE", "×0.76 +0", 0], ["KIMCHI", "—", 0]], "conflict": ["VWAP 아래"], "onchain": null, "price": 15.94, "p24": 10.31, "oi4": 4.7, "oi1": 0.3, "cvd": 0.677, "fr": 0.0, "atr": 2.79, "flow": -2.5, "surge": 0.76, "ret4": 0.57, "bb_pos": 0.8, "bb_squeeze": false, "bb_just_broke": false, "rng": 0.829, "kimp": null, "liq": [2492.4722999999994, 3302.4812546000003, 13], "vwap_broke": true, "spot_fuel": false, "turnover": 72993800, "tradfi": false, "pinned": false, "rank": 8, "since": 1784599401, "since_min": 545}, {"sym": "TAOUSDT", "base": "TAO", "mark": "🟡", "why": "연료 약함 — 관찰", "alpha": 66, "g": [["흡수/이탈", "— 0", 0], ["VWAP", "VWAP 아래 저항 -4", -4], ["MTF", "BTC 동조화 +0", 0], ["오더북", "매수벽 우위 ×1.55 +8", 8], ["청산", "미미 $10K 0", 0], ["볼밴", "상단 접근 +6", 6], ["스퀴즈", "정상 +0", 0], ["ATR", "낮은 변동성 +3", 3], ["레인지", "레인지 상단 +6", 6], ["FLOW", "Flow +13", 13], ["SURGE", "×1.72 +4", 4], ["KIMCHI", "+0.01%", 0]], "conflict": [], "onchain": null, "price": 199.71, "p24": 2.41, "oi4": 2.2, "oi1": 1.0, "cvd": 0.346, "fr": 0.0041, "atr": 1.08, "flow": 8.1, "surge": 1.72, "ret4": 0.41, "bb_pos": 0.916, "bb_squeeze": false, "bb_just_broke": false, "rng": 0.707, "kimp": 0.01, "liq": [10336.180900000001, 4278.33478, 16], "vwap_broke": true, "spot_fuel": false, "turnover": 70068546, "tradfi": false, "pinned": false, "rank": 9, "since": 1784631801, "since_min": 5}, {"sym": "1000PEPEUSDT", "base": "PEPE", "mark": "🟡", "why": "연료 약함 — 관찰", "alpha": 64, "g": [["흡수/이탈", "— 0", 0], ["VWAP", "VWAP 위 지지 +4", 4], ["MTF", "BTC 동조화 +0", 0], ["오더북", "매도 우위 ×0.69 -4", -4], ["청산", "↑ 숏청산 우위 $122K +5", 5], ["볼밴", "압축+상단 — 돌파임박 ★ +12", 12], ["스퀴즈", "정상 +0", 0], ["ATR", "낮은 변동성 +3", 3], ["레인지", "레인지 상단 +6", 6], ["FLOW", "Flow +8", 8], ["SURGE", "×1.10 +0", 0], ["KIMCHI", "-99.90%", 0]], "conflict": [], "onchain": null, "price": 0.0029554, "p24": 2.45, "oi4": 2.3, "oi1": 0.5, "cvd": 0.651, "fr": 0.0071, "atr": 1.18, "flow": 5.2, "surge": 1.1, "ret4": 1.18, "bb_pos": 0.905, "bb_squeeze": true, "bb_just_broke": false, "rng": 0.843, "kimp": -99.9, "liq": [122022.7899676, 4309.4385692, 39], "vwap_broke": false, "spot_fuel": false, "turnover": 171087292, "tradfi": false, "pinned": false, "rank": 10, "since": 1784517618, "since_min": 1909}, {"sym": "XAGUSDT", "base": "XAG", "mark": "🟡", "why": "연료 약함 — 관찰", "alpha": 61, "g": [["흡수/이탈", "ACC +14", 14], ["VWAP", "VWAP 아래 저항 -4", -4], ["MTF", "BTC 동조화 +0", 0], ["오더북", "균형 ×0.88 +0", 0], ["청산", "↑ 숏청산 우위 $278K +5", 5], ["볼밴", "밴드 중단 0", 0], ["스퀴즈", "정상 +0", 0], ["ATR", "극저 변동성 +6", 6], ["레인지", "레인지 상단 +6", 6], ["FLOW", "Flow +4", 4], ["SURGE", "×0.64 +0", 0], ["KIMCHI", "—", 0]], "conflict": [], "onchain": null, "price": 58.85, "p24": 3.17, "oi4": 5.2, "oi1": 2.3, "cvd": 0.298, "fr": 0.0094, "atr": 0.47, "flow": 2.6, "surge": 0.64, "ret4": -0.71, "bb_pos": 0.782, "bb_squeeze": false, "bb_just_broke": false, "rng": 0.831, "kimp": null, "liq": [278431.75824, 43359.770730000004, 30], "vwap_broke": true, "spot_fuel": false, "turnover": 804039899, "tradfi": true, "pinned": false, "rank": 11, "since": 1784631621, "since_min": 8}, {"sym": "ERAUSDT", "base": "ERA", "mark": "🟡", "why": "연료 약함 — 관찰", "alpha": 60, "g": [["흡수/이탈", "— 0", 0], ["VWAP", "VWAP 강한 돌파 +10", 10], ["MTF", "BTC 대비 강세 +6", 6], ["오더북", "균형 ×1.00 +0", 0], ["청산", "↑ 숏청산 우위 $225K +5", 5], ["볼밴", "밴드 중단 0", 0], ["스퀴즈", "대형 FR스퀴즈 ★ +8", 8], ["ATR", "고변동성 -4", -4], ["레인지", "레인지 상단 +6", 6], ["FLOW", "Flow -1", -1], ["SURGE", "×0.68 +0", 0], ["KIMCHI", "+2.79%", 0]], "conflict": [], "onchain": null, "price": 0.09782, "p24": 58.21, "oi4": 8.3, "oi1": 9.0, "cvd": 0.335, "fr": -1.2831, "atr": 7.98, "flow": -0.3, "surge": 0.68, "ret4": 3.17, "bb_pos": 0.75, "bb_squeeze": false, "bb_just_broke": false, "rng": 0.755, "kimp": 2.79, "liq": [224575.7470326, 121842.3690675, 397], "vwap_broke": false, "spot_fuel": false, "turnover": 279123880, "tradfi": false, "pinned": false, "rank": 12, "since": 1784631981, "since_min": 2}, {"sym": "CLUSDT", "base": "CL", "mark": "🟡", "why": "연료 약함 — 관찰", "alpha": 57, "g": [["흡수/이탈", "— 0", 0], ["VWAP", "VWAP 위 지지 +4", 4], ["MTF", "BTC 동조화 +0", 0], ["오더북", "균형 ×1.03 +0", 0], ["청산", "↑ 숏청산 우위 $121K +5", 5], ["볼밴", "밴드 밖 진행중 — 이미 감 0", 0], ["스퀴즈", "FR스퀴즈 중 +5", 5], ["ATR", "낮은 변동성 +3", 3], ["레인지", "고점 돌파 +4", 4], ["FLOW", "Flow -2", -2], ["SURGE", "×2.11 +8", 8], ["KIMCHI", "—", 0]], "conflict": [], "onchain": null, "price": 83.37, "p24": 2.31, "oi4": 2.4, "oi1": 2.2, "cvd": 0.61, "fr": -0.0136, "atr": 1.13, "flow": -1.0, "surge": 2.11, "ret4": 1.77, "bb_pos": 1.064, "bb_squeeze": false, "bb_just_broke": false, "rng": 0.966, "kimp": null, "liq": [121107.4470932, 34502.8897, 43], "vwap_broke": false, "spot_fuel": false, "turnover": 847979154, "tradfi": false, "pinned": false, "rank": 13, "since": 1784563223, "since_min": 1148}, {"sym": "ONUSDT", "base": "ON", "mark": "🟡", "why": "연료 약함 — 관찰", "alpha": 53, "g": [["흡수/이탈", "— 0", 0], ["VWAP", "VWAP 아래 저항 -4", -4], ["MTF", "BTC 대비 초강세 +12", 12], ["오더북", "매수 우위 ×1.50 +4", 4], ["청산", "혼조 0", 0], ["볼밴", "압축+상단 — 돌파임박 ★ +12", 12], ["스퀴즈", "롱 과열 -4", -4], ["ATR", "고변동성 -4", -4], ["레인지", "레인지 상단 +6", 6], ["FLOW", "Flow -3", -3], ["SURGE", "×1.97 +4", 4], ["KIMCHI", "—", 0]], "conflict": [], "onchain": null, "price": 0.16369, "p24": 28.2, "oi4": 17.5, "oi1": 3.9, "cvd": 0.445, "fr": 0.0567, "atr": 11.57, "flow": -1.7, "surge": 1.97, "ret4": 6.61, "bb_pos": 0.826, "bb_squeeze": true, "bb_just_broke": false, "rng": 0.701, "kimp": null, "liq": [140941.5805084, 105839.9913366, 282], "vwap_broke": true, "spot_fuel": false, "turnover": 59679192, "tradfi": false, "pinned": false, "rank": 14, "since": 1784631441, "since_min": 12}, {"sym": "SKHYUSDT", "base": "SKHY", "mark": "🟡", "why": "연료 약함 — 관찰", "alpha": 52, "g": [["흡수/이탈", "— 0", 0], ["VWAP", "VWAP 아래 저항 -4", -4], ["MTF", "BTC 동조화 +0", 0], ["오더북", "매수벽 우위 ×3.81 +8", 8], ["청산", "↑ 숏청산 우위 $128K +5", 5], ["볼밴", "밴드압축 8.6% — 대기 +4", 4], ["스퀴즈", "정상 +0", 0], ["ATR", "낮은 변동성 +3", 3], ["레인지", "레인지 상단 +6", 6], ["FLOW", "Flow +0", 0], ["SURGE", "×0.78 +0", 0], ["KIMCHI", "—", 0]], "conflict": [], "onchain": null, "price": 160.77, "p24": -1.05, "oi4": 3.2, "oi1": 1.6, "cvd": 0.712, "fr": 0.015, "atr": 1.15, "flow": 0.1, "surge": 0.78, "ret4": 0.4, "bb_pos": 0.786, "bb_squeeze": true, "bb_just_broke": false, "rng": 0.762, "kimp": null, "liq": [127932.76317500001, 23.9574, 13], "vwap_broke": true, "spot_fuel": false, "turnover": 864233530, "tradfi": false, "pinned": false, "rank": 15, "since": 1784628201, "since_min": 65}, {"sym": "SOXSUSDT", "base": "SOXS", "mark": "🟡", "why": "연료 약함 — 관찰", "alpha": 46, "g": [["흡수/이탈", "ACC +28", 28], ["VWAP", "VWAP 위 지지 +4", 4], ["MTF", "BTC 동조화 +0", 0], ["오더북", "매도벽 압박 ×0.62 -8", -8], ["청산", "미미 $5K 0", 0], ["볼밴", "밴드 하단 -3", -3], ["스퀴즈", "정상 +0", 0], ["ATR", "낮은 변동성 +3", 3], ["레인지", "레인지 내 0", 0], ["FLOW", "Flow -8", -8], ["SURGE", "×0.84 +0", 0], ["KIMCHI", "—", 0]], "conflict": [], "onchain": null, "price": 47.79, "p24": -6.99, "oi4": 14.8, "oi1": -10.6, "cvd": 0.379, "fr": 0.0, "atr": 1.89, "flow": -5.0, "surge": 0.84, "ret4": -1.57, "bb_pos": 0.176, "bb_squeeze": false, "bb_just_broke": false, "rng": 0.116, "kimp": null, "liq": [0, 5234.7112967, 6], "vwap_broke": false, "spot_fuel": false, "turnover": 37930577, "tradfi": true, "pinned": false, "rank": 16, "since": 1784630361, "since_min": 30}, {"sym": "ZHIPUUSDT", "base": "ZHIPU", "mark": "🟡", "why": "연료 약함 — 관찰", "alpha": 46, "g": [["흡수/이탈", "— 0", 0], ["VWAP", "VWAP 아래 저항 -4", -4], ["MTF", "BTC 동조화 +0", 0], ["오더북", "매수 우위 ×1.35 +4", 4], ["청산", "미미 $21K 0", 0], ["볼밴", "밴드 중단 0", 0], ["스퀴즈", "대형 FR스퀴즈 ★ +8", 8], ["ATR", "정상 변동성 +0", 0], ["레인지", "레인지 상단 +6", 6], ["FLOW", "Flow +2", 2], ["SURGE", "×0.44 +0", 0], ["KIMCHI", "—", 0]], "conflict": [], "onchain": null, "price": 149.25, "p24": 29.9, "oi4": 9.8, "oi1": -1.9, "cvd": 0.027, "fr": -0.4745, "atr": 2.82, "flow": 1.5, "surge": 0.44, "ret4": -3.6, "bb_pos": 0.764, "bb_squeeze": false, "bb_just_broke": false, "rng": 0.796, "kimp": null, "liq": [21131.9747933, 5759.8764637, 47], "vwap_broke": true, "spot_fuel": false, "turnover": 89232362, "tradfi": false, "pinned": false, "rank": 17, "since": 1784628921, "since_min": 54}, {"sym": "BTCUSDT", "base": "BTC", "mark": "🟡", "why": "연료 약함 — 관찰", "alpha": 45, "g": [["흡수/이탈", "— 0", 0], ["VWAP", "VWAP 아래 저항 -4", -4], ["MTF", "BTC 동조화 +0", 0], ["오더북", "매도벽 압박 ×0.20 -8", -8], ["청산", "대형 숏청산 ★ $5945K +8", 8], ["볼밴", "압축+상단 — 돌파임박 ★ +12", 12], ["스퀴즈", "정상 +0", 0], ["ATR", "극저 변동성 +6", 6], ["레인지", "레인지 상단 +6", 6], ["FLOW", "Flow -5", -5], ["SURGE", "×0.95 +0", 0], ["KIMCHI", "-0.04%", 0]], "conflict": [], "onchain": null, "price": 66132.3, "p24": 2.67, "oi4": 1.9, "oi1": -0.4, "cvd": 0.644, "fr": 0.0074, "atr": 0.28, "flow": -3.1, "surge": 0.95, "ret4": -0.06, "bb_pos": 0.842, "bb_squeeze": true, "bb_just_broke": false, "rng": 0.89, "kimp": -0.04, "liq": [5945439.47547, 238470.3751, 224], "vwap_broke": true, "spot_fuel": false, "turnover": 11467936904, "tradfi": false, "pinned": false, "rank": 18, "since": 1784511858, "since_min": 2005}, {"sym": "SOLUSDT", "base": "SOL", "mark": "🟡", "why": "연료 약함 — 관찰", "alpha": 44, "g": [["흡수/이탈", "— 0", 0], ["VWAP", "VWAP 아래 저항 -4", -4], ["MTF", "BTC 동조화 +0", 0], ["오더북", "균형 ×0.90 +0", 0], ["청산", "대형 숏청산 ★ $436K +8", 8], ["볼밴", "밴드압축 1.7% — 대기 +4", 4], ["스퀴즈", "정상 +0", 0], ["ATR", "극저 변동성 +6", 6], ["레인지", "레인지 상단 +6", 6], ["FLOW", "Flow -6", -6], ["SURGE", "×0.81 +0", 0], ["KIMCHI", "-0.02%", 0]], "conflict": [], "onchain": null, "price": 78.13, "p24": 2.09, "oi4": -0.3, "oi1": -0.4, "cvd": 0.259, "fr": 0.0009, "atr": 0.41, "flow": -3.8, "surge": 0.81, "ret4": -0.53, "bb_pos": 0.585, "bb_squeeze": true, "bb_just_broke": false, "rng": 0.758, "kimp": -0.02, "liq": [436498.32158999995, 80616.4302, 62], "vwap_broke": true, "spot_fuel": false, "turnover": 1240961713, "tradfi": false, "pinned": true, "rank": 19, "since": 1784516538, "since_min": 1927}, {"sym": "NBISUSDT", "base": "NBIS", "mark": "🟡", "why": "연료 약함 — 관찰", "alpha": 43, "g": [["흡수/이탈", "— 0", 0], ["VWAP", "VWAP 아래 저항 -4", -4], ["MTF", "BTC 동조화 +0", 0], ["오더북", "매수벽 우위 ×1.76 +8", 8], ["청산", "청산 데이터 없음 0", 0], ["볼밴", "밴드 중단 0", 0], ["스퀴즈", "정상 +0", 0], ["ATR", "낮은 변동성 +3", 3], ["레인지", "레인지 상단 +6", 6], ["FLOW", "Flow -4", -4], ["SURGE", "×1.49 +4", 4], ["KIMCHI", "—", 0]], "conflict": [], "onchain": null, "price": 194.48, "p24": 5.03, "oi4": 3.4, "oi1": -0.5, "cvd": 0.53, "fr": 0.0194, "atr": 1.22, "flow": -2.3, "surge": 1.49, "ret4": 0.45, "bb_pos": 0.746, "bb_squeeze": false, "bb_just_broke": false, "rng": 0.854, "kimp": null, "liq": null, "vwap_broke": true, "spot_fuel": false, "turnover": 58476962, "tradfi": false, "pinned": false, "rank": 20, "since": 1784555661, "since_min": 1274}, {"sym": "ARBUSDT", "base": "ARB", "mark": "🟡", "why": "연료 약함 — 관찰", "alpha": 43, "g": [["흡수/이탈", "— 0", 0], ["VWAP", "VWAP 아래 저항 -4", -4], ["MTF", "BTC 동조화 +0", 0], ["오더북", "균형 ×1.05 +0", 0], ["청산", "미미 $7K 0", 0], ["볼밴", "밴드압축 1.9% — 대기 +4", 4], ["스퀴즈", "정상 +0", 0], ["ATR", "극저 변동성 +6", 6], ["레인지", "레인지 상단 +6", 6], ["FLOW", "Flow +1", 1], ["SURGE", "×0.75 +0", 0], ["KIMCHI", "-0.21%", 0]], "conflict": [], "onchain": null, "price": 0.09048, "p24": 3.75, "oi4": 2.0, "oi1": -0.3, "cvd": 0.274, "fr": -0.0048, "atr": 0.78, "flow": 0.6, "surge": 0.75, "ret4": -0.51, "bb_pos": 0.613, "bb_squeeze": true, "bb_just_broke": false, "rng": 0.667, "kimp": -0.21, "liq": [385.08424879999995, 6694.604561000001, 9], "vwap_broke": true, "spot_fuel": false, "turnover": 27121308, "tradfi": false, "pinned": false, "rank": 21, "since": 1784628023, "since_min": 68}, {"sym": "GOOGLUSDT", "base": "GOOGL", "mark": "🟡", "why": "연료 약함 — 관찰", "alpha": 39, "g": [["흡수/이탈", "— 0", 0], ["VWAP", "VWAP 위 지지 +4", 4], ["MTF", "BTC 동조화 +0", 0], ["오더북", "균형 ×1.12 +0", 0], ["청산", "청산 데이터 없음 0", 0], ["볼밴", "밴드압축 1.5% — 대기 +4", 4], ["스퀴즈", "정상 +0", 0], ["ATR", "극저 변동성 +6", 6], ["레인지", "레인지 내 0", 0], ["FLOW", "Flow -5", -5], ["SURGE", "×0.93 +0", 0], ["KIMCHI", "—", 0]], "conflict": [], "onchain": null, "price": 354.79, "p24": 1.97, "oi4": 4.3, "oi1": -0.3, "cvd": 0.0, "fr": 0.0335, "atr": 0.62, "flow": -3.2, "surge": 0.93, "ret4": -0.46, "bb_pos": 0.588, "bb_squeeze": true, "bb_just_broke": false, "rng": 0.57, "kimp": null, "liq": null, "vwap_broke": false, "spot_fuel": false, "turnover": 55155829, "tradfi": true, "pinned": false, "rank": 22, "since": 1784628023, "since_min": 68}, {"sym": "LINKUSDT", "base": "LINK", "mark": "🟡", "why": "연료 약함 — 관찰", "alpha": 38, "g": [["흡수/이탈", "— 0", 0], ["VWAP", "VWAP 아래 저항 -4", -4], ["MTF", "BTC 동조화 +0", 0], ["오더북", "균형 ×1.07 +0", 0], ["청산", "미미 $11K 0", 0], ["볼밴", "밴드압축 3.3% — 대기 +4", 4], ["스퀴즈", "정상 +0", 0], ["ATR", "극저 변동성 +6", 6], ["레인지", "레인지 상단 +6", 6], ["FLOW", "Flow -4", -4], ["SURGE", "×0.56 +0", 0], ["KIMCHI", "+0.06%", 0]], "conflict": [], "onchain": {"src": "cold", "score": 73, "mark": "🟢", "grade": "강한 펌프 가능성", "cold_score": 73, "cold_usd": 16441987, "cold_n": 8, "cold_wallets": 9, "cold_days": 33.0, "peak": 10.9, "accum_score": null, "accum_usd": null, "accum_wallets": null, "accum_wd": null, "accum_days": null, "conc": false}, "price": 8.695, "p24": 3.41, "oi4": 1.2, "oi1": 0.3, "cvd": 0.288, "fr": 0.01, "atr": 0.48, "flow": -2.6, "surge": 0.56, "ret4": -0.45, "bb_pos": 0.733, "bb_squeeze": true, "bb_just_broke": false, "rng": 0.868, "kimp": 0.06, "liq": [11043.074980000001, 475.19628, 9], "vwap_broke": true, "spot_fuel": false, "turnover": 98877025, "tradfi": false, "pinned": true, "rank": 23, "since": 1784620823, "since_min": 188}, {"sym": "LABUSDT", "base": "LAB", "mark": "🟡", "why": "연료 약함 — 관찰", "alpha": 37, "g": [["흡수/이탈", "— 0", 0], ["VWAP", "VWAP 강한 돌파 +10", 10], ["MTF", "BTC 대비 강세 +6", 6], ["오더북", "매도 우위 ×0.75 -4", -4], ["청산", "↓ 롱청산 우위 $39K -6", -6], ["볼밴", "밴드 중단 0", 0], ["스퀴즈", "정상 +0", 0], ["ATR", "정상 변동성 +0", 0], ["레인지", "레인지 내 0", 0], ["FLOW", "Flow +1", 1], ["SURGE", "×0.36 +0", 0], ["KIMCHI", "—", 0]], "conflict": [], "onchain": null, "price": 0.1341, "p24": -7.77, "oi4": 2.7, "oi1": 1.7, "cvd": 0.428, "fr": 0.0202, "atr": 3.33, "flow": 0.6, "surge": 0.36, "ret4": 4.44, "bb_pos": 0.401, "bb_squeeze": false, "bb_just_broke": false, "rng": 0.418, "kimp": null, "liq": [10865.6175535, 39415.8074795, 125], "vwap_broke": false, "spot_fuel": false, "turnover": 89065326, "tradfi": false, "pinned": false, "rank": 24, "since": 1784631801, "since_min": 5}, {"sym": "BILLUSDT", "base": "BILL", "mark": "🟡", "why": "연료 약함 — 관찰", "alpha": 29, "g": [["흡수/이탈", "— 0", 0], ["VWAP", "VWAP 위 지지 +4", 4], ["MTF", "BTC 동조화 +0", 0], ["오더북", "균형 ×1.12 +0", 0], ["청산", "미미 $6K 0", 0], ["볼밴", "밴드압축 7.1% — 대기 +4", 4], ["스퀴즈", "정상 +0", 0], ["ATR", "정상 변동성 +0", 0], ["레인지", "레인지 내 0", 0], ["FLOW", "Flow -9", -9], ["SURGE", "×0.96 +0", 0], ["KIMCHI", "—", 0]], "conflict": [], "onchain": {"src": "cold", "score": 73, "mark": "🟢", "grade": "강한 펌프 가능성", "cold_score": 73, "cold_usd": 33392242, "cold_n": 8, "cold_wallets": 3, "cold_days": 22.6, "peak": 0.2, "accum_score": null, "accum_usd": null, "accum_wallets": null, "accum_wd": null, "accum_days": null, "conc": false}, "price": 0.02404, "p24": -3.61, "oi4": 0.1, "oi1": -0.0, "cvd": 0.554, "fr": -0.0088, "atr": 2.19, "flow": -5.7, "surge": 0.96, "ret4": -1.56, "bb_pos": 0.389, "bb_squeeze": true, "bb_just_broke": false, "rng": 0.252, "kimp": null, "liq": [2493.6178649999997, 6383.0454922, 27], "vwap_broke": false, "spot_fuel": false, "turnover": 8148432, "tradfi": false, "pinned": true, "rank": 25, "since": 1784512938, "since_min": 1987}, {"sym": "COINUSDT", "base": "COIN", "mark": "🟡", "why": "연료 약함 — 관찰", "alpha": 27, "g": [["흡수/이탈", "— 0", 0], ["VWAP", "VWAP 아래 저항 -4", -4], ["MTF", "BTC 동조화 +0", 0], ["오더북", "매도벽 압박 ×0.51 -8", -8], ["청산", "청산 데이터 없음 0", 0], ["볼밴", "밴드압축 4.8% — 대기 +4", 4], ["스퀴즈", "롱 과열 -4", -4], ["ATR", "극저 변동성 +6", 6], ["레인지", "레인지 상단 +6", 6], ["FLOW", "Flow -7", -7], ["SURGE", "×1.53 +4", 4], ["KIMCHI", "—", 0]], "conflict": [], "onchain": null, "price": 165.27, "p24": 4.25, "oi4": 3.4, "oi1": 0.6, "cvd": 0.658, "fr": 0.0688, "atr": 0.76, "flow": -4.2, "surge": 1.53, "ret4": 0.41, "bb_pos": 0.798, "bb_squeeze": true, "bb_just_broke": false, "rng": 0.851, "kimp": null, "liq": null, "vwap_broke": true, "spot_fuel": false, "turnover": 25548298, "tradfi": true, "pinned": false, "rank": 26, "since": 1784555841, "since_min": 1272}, {"sym": "GLWUSDT", "base": "GLW", "mark": "🟡", "why": "연료 약함 — 관찰", "alpha": 25, "g": [["흡수/이탈", "— 0", 0], ["VWAP", "VWAP 아래 저항 -4", -4], ["MTF", "BTC 동조화 +0", 0], ["오더북", "매도 우위 ×0.69 -4", -4], ["청산", "미미 $5K 0", 0], ["볼밴", "밴드 중단 0", 0], ["스퀴즈", "정상 +0", 0], ["ATR", "극저 변동성 +6", 6], ["레인지", "레인지 상단 +6", 6], ["FLOW", "Flow -9", -9], ["SURGE", "×1.12 +0", 0], ["KIMCHI", "—", 0]], "conflict": [], "onchain": null, "price": 159.84, "p24": 0.72, "oi4": 3.8, "oi1": -0.2, "cvd": 0.342, "fr": 0.036, "atr": 0.89, "flow": -5.9, "surge": 1.12, "ret4": 0.22, "bb_pos": 0.792, "bb_squeeze": false, "bb_just_broke": false, "rng": 0.775, "kimp": null, "liq": [15.981000000000002, 4820.3764104, 2], "vwap_broke": true, "spot_fuel": false, "turnover": 20847297, "tradfi": false, "pinned": false, "rank": 27, "since": 1784631441, "since_min": 12}, {"sym": "ORCLUSDT", "base": "ORCL", "mark": "🟡", "why": "연료 약함 — 관찰", "alpha": 25, "g": [["흡수/이탈", "— 0", 0], ["VWAP", "VWAP 아래 저항 -4", -4], ["MTF", "BTC 동조화 +0", 0], ["오더북", "매도벽 압박 ×0.65 -8", -8], ["청산", "청산 데이터 없음 0", 0], ["볼밴", "밴드압축 1.9% — 대기 +4", 4], ["스퀴즈", "정상 +0", 0], ["ATR", "극저 변동성 +6", 6], ["레인지", "레인지 내 0", 0], ["FLOW", "Flow -3", -3], ["SURGE", "×0.90 +0", 0], ["KIMCHI", "—", 0]], "conflict": [], "onchain": null, "price": 122.65, "p24": -2.67, "oi4": 2.3, "oi1": 0.2, "cvd": 0.515, "fr": 0.0154, "atr": 0.39, "flow": -1.7, "surge": 0.9, "ret4": -0.3, "bb_pos": 0.571, "bb_squeeze": true, "bb_just_broke": false, "rng": 0.415, "kimp": null, "liq": null, "vwap_broke": true, "spot_fuel": false, "turnover": 22573113, "tradfi": false, "pinned": false, "rank": 28, "since": 1784557461, "since_min": 1245}, {"sym": "MRVLUSDT", "base": "MRVL", "mark": "🟡", "why": "연료 약함 — 관찰", "alpha": 23, "g": [["흡수/이탈", "— 0", 0], ["VWAP", "VWAP 아래 저항 -4", -4], ["MTF", "BTC 동조화 +0", 0], ["오더북", "매도 우위 ×0.71 -4", -4], ["청산", "미미 $10K 0", 0], ["볼밴", "밴드 중단 0", 0], ["스퀴즈", "정상 +0", 0], ["ATR", "낮은 변동성 +3", 3], ["레인지", "레인지 상단 +6", 6], ["FLOW", "Flow -8", -8], ["SURGE", "×0.92 +0", 0], ["KIMCHI", "—", 0]], "conflict": [], "onchain": null, "price": 206.22, "p24": 6.5, "oi4": 3.7, "oi1": -0.9, "cvd": 0.373, "fr": 0.0213, "atr": 1.19, "flow": -5.3, "surge": 0.92, "ret4": -0.16, "bb_pos": 0.783, "bb_squeeze": false, "bb_just_broke": false, "rng": 0.794, "kimp": null, "liq": [9863.0721254, 0, 3], "vwap_broke": true, "spot_fuel": false, "turnover": 164667299, "tradfi": true, "pinned": false, "rank": 29, "since": 1784628023, "since_min": 68}, {"sym": "CBRSUSDT", "base": "CBRS", "mark": "🟡", "why": "연료 약함 — 관찰", "alpha": 21, "g": [["흡수/이탈", "— 0", 0], ["VWAP", "VWAP 아래 저항 -4", -4], ["MTF", "BTC 동조화 +0", 0], ["오더북", "매도벽 압박 ×0.66 -8", -8], ["청산", "청산 데이터 없음 0", 0], ["볼밴", "밴드압축 4.6% — 대기 +4", 4], ["스퀴즈", "정상 +0", 0], ["ATR", "낮은 변동성 +3", 3], ["레인지", "레인지 상단 +6", 6], ["FLOW", "Flow -14", -14], ["SURGE", "×1.44 +4", 4], ["KIMCHI", "—", 0]], "conflict": [], "onchain": null, "price": 180.77, "p24": 2.55, "oi4": 3.3, "oi1": 0.1, "cvd": 0.336, "fr": 0.0, "atr": 1.15, "flow": -8.6, "surge": 1.44, "ret4": 0.37, "bb_pos": 0.71, "bb_squeeze": true, "bb_just_broke": false, "rng": 0.853, "kimp": null, "liq": null, "vwap_broke": true, "spot_fuel": false, "turnover": 26011061, "tradfi": false, "pinned": false, "rank": 30, "since": 1784581401, "since_min": 846}, {"sym": "IBMUSDT", "base": "IBM", "mark": "🟡", "why": "연료 약함 — 관찰", "alpha": 20, "g": [["흡수/이탈", "ACC +14", 14], ["VWAP", "VWAP 아래 저항 -4", -4], ["MTF", "BTC 동조화 +0", 0], ["오더북", "매도 우위 ×0.69 -4", -4], ["청산", "미미 $1K 0", 0], ["볼밴", "밴드압축 2.1% — 대기 +4", 4], ["스퀴즈", "정상 +0", 0], ["ATR", "극저 변동성 +6", 6], ["레인지", "레인지 내 0", 0], ["FLOW", "Flow -30", -30], ["SURGE", "×1.68 +4", 4], ["KIMCHI", "—", 0]], "conflict": [], "onchain": null, "price": 211.5, "p24": -0.39, "oi4": 6.4, "oi1": 1.4, "cvd": 0.24, "fr": 0.0, "atr": 0.4, "flow": -21.8, "surge": 1.68, "ret4": -0.35, "bb_pos": 0.095, "bb_squeeze": true, "bb_just_broke": false, "rng": 0.313, "kimp": null, "liq": [0, 1459.2547568, 4], "vwap_broke": true, "spot_fuel": false, "turnover": 21458264, "tradfi": false, "pinned": false, "rank": 31, "since": 1784574023, "since_min": 968}, {"sym": "TSLAUSDT", "base": "TSLA", "mark": "🟡", "why": "연료 약함 — 관찰", "alpha": 19, "g": [["흡수/이탈", "— 0", 0], ["VWAP", "VWAP 아래 저항 -4", -4], ["MTF", "BTC 동조화 +0", 0], ["오더북", "균형 ×0.94 +0", 0], ["청산", "↓ 롱청산 우위 $38K -6", -6], ["볼밴", "밴드압축 1.6% — 대기 +4", 4], ["스퀴즈", "정상 +0", 0], ["ATR", "극저 변동성 +6", 6], ["레인지", "레인지 내 0", 0], ["FLOW", "Flow -11", -11], ["SURGE", "×1.26 +0", 0], ["KIMCHI", "—", 0]], "conflict": [], "onchain": null, "price": 373.12, "p24": -2.76, "oi4": 2.0, "oi1": 0.9, "cvd": 0.354, "fr": 0.0235, "atr": 0.26, "flow": -6.7, "surge": 1.26, "ret4": -0.32, "bb_pos": 0.597, "bb_squeeze": true, "bb_just_broke": false, "rng": 0.199, "kimp": null, "liq": [0, 38148.4511976, 1], "vwap_broke": true, "spot_fuel": false, "turnover": 47207386, "tradfi": true, "pinned": false, "rank": 32, "since": 1784556201, "since_min": 1266}, {"sym": "HOMEUSDT", "base": "HOME", "mark": "🔴", "why": "하락 중 -15% — 롱 근거 없음", "alpha": 32, "g": [["흡수/이탈", "— 0", 0], ["VWAP", "VWAP 위 지지 +4", 4], ["MTF", "BTC 동조화 +0", 0], ["오더북", "균형 ×1.13 +0", 0], ["청산", "↓ 롱청산 우위 $42K -6", -6], ["볼밴", "밴드압축 12.5% — 대기 +4", 4], ["스퀴즈", "대형 FR스퀴즈 ★ +8", 8], ["ATR", "정상 변동성 +0", 0], ["레인지", "레인지 내 0", 0], ["FLOW", "Flow -8", -8], ["SURGE", "×1.02 +0", 0], ["KIMCHI", "—", 0]], "conflict": [], "onchain": null, "price": 0.00676, "p24": -15.39, "oi4": 3.6, "oi1": 0.7, "cvd": 0.25, "fr": -0.2004, "atr": 2.67, "flow": -4.7, "surge": 1.02, "ret4": -2.03, "bb_pos": 0.203, "bb_squeeze": true, "bb_just_broke": false, "rng": 0.102, "kimp": null, "liq": [2530.6373, 42262.111356299996, 82], "vwap_broke": false, "spot_fuel": false, "turnover": 25981385, "tradfi": false, "pinned": false, "rank": 33, "since": 1784630721, "since_min": 24}, {"sym": "ACEUSDT", "base": "ACE", "mark": "🔴", "why": "하락 중 -29% — 롱 근거 없음", "alpha": 27, "g": [["흡수/이탈", "— 0", 0], ["VWAP", "VWAP 위 지지 +4", 4], ["MTF", "BTC 동조화 +0", 0], ["오더북", "매수 우위 ×1.20 +4", 4], ["청산", "↓ 롱청산 우위 $77K -6", -6], ["볼밴", "밴드압축 34.0% — 대기 +4", 4], ["스퀴즈", "정상 +0", 0], ["ATR", "정상 변동성 +0", 0], ["레인지", "저점 근접 -6", -6], ["FLOW", "Flow -3", -3], ["SURGE", "×0.57 +0", 0], ["KIMCHI", "—", 0]], "conflict": [], "onchain": null, "price": 0.10148, "p24": -29.01, "oi4": 2.6, "oi1": -0.4, "cvd": 0.305, "fr": 0.0016, "atr": 3.68, "flow": -1.6, "surge": 0.57, "ret4": 0.02, "bb_pos": 0.245, "bb_squeeze": true, "bb_just_broke": false, "rng": 0.095, "kimp": null, "liq": [21910.99205158, 77111.97565419, 180], "vwap_broke": false, "spot_fuel": false, "turnover": 343813830, "tradfi": false, "pinned": false, "rank": 34, "since": 1784628201, "since_min": 65}]}