{"updated": "2026-07-21 06:06:21", "updated_ts": 1784581581, "scan_sec": 180, "us_open": false, "ws": true, "liq_events": 20334, "count": 34, "cols": ["흡수/이탈", "VWAP", "MTF", "오더북", "청산", "볼밴", "스퀴즈", "ATR", "레인지", "FLOW", "SURGE", "KIMCHI"], "rows": [{"sym": "SOXSUSDT", "base": "SOXS", "mark": "🟢", "why": "초입(-5%) + 연료 — 진입검토", "alpha": 61, "g": [["흡수/이탈", "ACC +14", 14], ["VWAP", "VWAP 강한 돌파 +10", 10], ["MTF", "BTC 대비 강세 +6", 6], ["오더북", "균형 ×1.00 +0", 0], ["청산", "미미 $0K 0", 0], ["볼밴", "밴드압축 9.5% — 대기 +4", 4], ["스퀴즈", "정상 +0", 0], ["ATR", "낮은 변동성 +3", 3], ["레인지", "레인지 상단 +6", 6], ["FLOW", "Flow -12", -12], ["SURGE", "×0.45 +0", 0], ["KIMCHI", "—", 0]], "conflict": [], "onchain": null, "price": 54.02, "p24": -4.83, "oi4": 6.4, "oi1": -1.2, "cvd": 0.992, "fr": 0.0, "atr": 1.91, "flow": -7.5, "surge": 0.45, "ret4": 3.67, "bb_pos": 0.753, "bb_squeeze": true, "bb_just_broke": false, "rng": 0.687, "kimp": null, "liq": [184.69569869999998, 0, 2], "vwap_broke": false, "spot_fuel": false, "turnover": 31312724, "tradfi": true, "pinned": false, "rank": 1, "since": 1784581401, "since_min": 2}, {"sym": "ADAUSDT", "base": "ADA", "mark": "🟡", "why": "연료 약함 — 관찰", "alpha": 79, "g": [["흡수/이탈", "— 0", 0], ["VWAP", "VWAP 강한 돌파 +10", 10], ["MTF", "BTC 대비 강세 +6", 6], ["오더북", "매수 우위 ×1.16 +4", 4], ["청산", "↑ 숏청산 우위 $78K +5", 5], ["볼밴", "밴드 밖 진행중 — 이미 감 0", 0], ["스퀴즈", "FR스퀴즈 중 +5", 5], ["ATR", "낮은 변동성 +3", 3], ["레인지", "고점 돌파 +4", 4], ["FLOW", "Flow +12", 12], ["SURGE", "×1.16 +0", 0], ["KIMCHI", "+0.02%", 0]], "conflict": [], "onchain": null, "price": 0.1704, "p24": 2.59, "oi4": 1.4, "oi1": 0.0, "cvd": 0.728, "fr": -0.0121, "atr": 1.2, "flow": 7.5, "surge": 1.16, "ret4": 1.85, "bb_pos": 1.009, "bb_squeeze": false, "bb_just_broke": false, "rng": 0.98, "kimp": 0.02, "liq": [77970.89259999999, 19.9087, 39], "vwap_broke": false, "spot_fuel": false, "turnover": 160388111, "tradfi": false, "pinned": false, "rank": 2, "since": 1784581221, "since_min": 5}, {"sym": "LINKUSDT", "base": "LINK", "mark": "🟡", "why": "연료 약함 — 관찰", "alpha": 78, "g": [["흡수/이탈", "— 0", 0], ["VWAP", "VWAP 위 지지 +4", 4], ["MTF", "BTC 동조화 +0", 0], ["오더북", "매수 우위 ×1.28 +4", 4], ["청산", "↑ 숏청산 우위 $32K +5", 5], ["볼밴", "상단 접근 +6", 6], ["스퀴즈", "정상 +0", 0], ["ATR", "극저 변동성 +6", 6], ["레인지", "레인지 상단 +6", 6], ["FLOW", "Flow +17", 17], ["SURGE", "×0.53 +0", 0], ["KIMCHI", "-0.10%", 0]], "conflict": [], "onchain": {"src": "cold", "score": 73, "mark": "🟢", "grade": "강한 펌프 가능성", "cold_score": 73, "cold_usd": 16441987, "cold_n": 8, "cold_wallets": 9, "cold_days": 32.4, "peak": 10.9, "accum_score": null, "accum_usd": null, "accum_wallets": null, "accum_wd": null, "accum_days": null, "conc": false}, "price": 8.571, "p24": 2.39, "oi4": 0.9, "oi1": 0.2, "cvd": 0.463, "fr": 0.0063, "atr": 0.63, "flow": 10.6, "surge": 0.53, "ret4": -0.05, "bb_pos": 0.824, "bb_squeeze": false, "bb_just_broke": false, "rng": 0.792, "kimp": -0.1, "liq": [31807.17652, 1017.4584, 15], "vwap_broke": false, "spot_fuel": false, "turnover": 95195770, "tradfi": false, "pinned": false, "rank": 3, "since": 1784520138, "since_min": 1024}, {"sym": "1000BONKUSDT", "base": "BONK", "mark": "🟡", "why": "연료 약함 — 관찰", "alpha": 74, "g": [["흡수/이탈", "— 0", 0], ["VWAP", "VWAP 강한 돌파 +10", 10], ["MTF", "BTC 대비 강세 +6", 6], ["오더북", "매수 우위 ×1.23 +4", 4], ["청산", "미미 $8K 0", 0], ["볼밴", "밴드 중단 0", 0], ["스퀴즈", "정상 +0", 0], ["ATR", "낮은 변동성 +3", 3], ["레인지", "레인지 상단 +6", 6], ["FLOW", "Flow +15", 15], ["SURGE", "×0.30 +0", 0], ["KIMCHI", "-99.86%", 0]], "conflict": [], "onchain": null, "price": 0.003113, "p24": 9.5, "oi4": 0.8, "oi1": 0.8, "cvd": 0.47, "fr": 0.005, "atr": 1.68, "flow": 9.2, "surge": 0.3, "ret4": 2.0, "bb_pos": 0.768, "bb_squeeze": false, "bb_just_broke": false, "rng": 0.86, "kimp": -99.86, "liq": [495.6324995, 7923.2425803, 14], "vwap_broke": false, "spot_fuel": false, "turnover": 69562480, "tradfi": false, "pinned": false, "rank": 4, "since": 1784538201, "since_min": 723}, {"sym": "BZUSDT", "base": "BZ", "mark": "🟡", "why": "연료 약함 — 관찰", "alpha": 70, "g": [["흡수/이탈", "ACC +14", 14], ["VWAP", "VWAP 아래 저항 -4", -4], ["MTF", "BTC 동조화 +0", 0], ["오더북", "매도벽 압박 ×0.46 -8", -8], ["청산", "↑ 숏청산 우위 $36K +5", 5], ["볼밴", "밴드압축 4.0% — 대기 +4", 4], ["스퀴즈", "정상 +0", 0], ["ATR", "극저 변동성 +6", 6], ["레인지", "레인지 내 0", 0], ["FLOW", "Flow +23", 23], ["SURGE", "×0.35 +0", 0], ["KIMCHI", "—", 0]], "conflict": [], "onchain": null, "price": 86.97, "p24": -1.34, "oi4": 6.2, "oi1": -0.2, "cvd": 0.449, "fr": -0.0089, "atr": 0.59, "flow": 14.4, "surge": 0.35, "ret4": 0.03, "bb_pos": 0.518, "bb_squeeze": true, "bb_just_broke": false, "rng": 0.554, "kimp": null, "liq": [35745.1883, 0, 7], "vwap_broke": true, "spot_fuel": false, "turnover": 435231217, "tradfi": false, "pinned": false, "rank": 5, "since": 1784581221, "since_min": 5}, {"sym": "XRPUSDT", "base": "XRP", "mark": "🟡", "why": "연료 약함 — 관찰", "alpha": 70, "g": [["흡수/이탈", "— 0", 0], ["VWAP", "VWAP 위 지지 +4", 4], ["MTF", "BTC 동조화 +0", 0], ["오더북", "균형 ×0.98 +0", 0], ["청산", "↑ 숏청산 우위 $57K +5", 5], ["볼밴", "상단 접근 +6", 6], ["스퀴즈", "정상 +0", 0], ["ATR", "극저 변동성 +6", 6], ["레인지", "레인지 상단 +6", 6], ["FLOW", "Flow +13", 13], ["SURGE", "×0.67 +0", 0], ["KIMCHI", "-0.10%", 0]], "conflict": [], "onchain": null, "price": 1.1161, "p24": 1.81, "oi4": 1.2, "oi1": -0.2, "cvd": 0.38, "fr": 0.0084, "atr": 0.48, "flow": 8.0, "surge": 0.67, "ret4": 0.14, "bb_pos": 0.846, "bb_squeeze": false, "bb_just_broke": false, "rng": 0.89, "kimp": -0.1, "liq": [56949.24379, 3265.5250799999994, 32], "vwap_broke": false, "spot_fuel": false, "turnover": 524391607, "tradfi": false, "pinned": false, "rank": 6, "since": 1784513118, "since_min": 1141}, {"sym": "TRXUSDT", "base": "TRX", "mark": "🟡", "why": "연료 약함 — 관찰", "alpha": 68, "g": [["흡수/이탈", "— 0", 0], ["VWAP", "VWAP 아래 저항 -4", -4], ["MTF", "BTC 동조화 +0", 0], ["오더북", "매도 우위 ×0.73 -4", -4], ["청산", "미미 $0K 0", 0], ["볼밴", "밴드압축 0.5% — 대기 +4", 4], ["스퀴즈", "정상 +0", 0], ["ATR", "극저 변동성 +6", 6], ["레인지", "레인지 내 0", 0], ["FLOW", "Flow +36", 36], ["SURGE", "×0.47 +0", 0], ["KIMCHI", "+0.22%", 0]], "conflict": [], "onchain": null, "price": 0.32645, "p24": -0.13, "oi4": 1.3, "oi1": 0.2, "cvd": 0.678, "fr": 0.01, "atr": 0.13, "flow": 22.7, "surge": 0.47, "ret4": 0.02, "bb_pos": 0.706, "bb_squeeze": true, "bb_just_broke": false, "rng": 0.599, "kimp": 0.22, "liq": [88.24419999999999, 0, 2], "vwap_broke": true, "spot_fuel": false, "turnover": 29506633, "tradfi": false, "pinned": false, "rank": 7, "since": 1784574202, "since_min": 122}, {"sym": "SOLUSDT", "base": "SOL", "mark": "🟡", "why": "연료 약함 — 관찰", "alpha": 67, "g": [["흡수/이탈", "— 0", 0], ["VWAP", "VWAP 위 지지 +4", 4], ["MTF", "BTC 동조화 +0", 0], ["오더북", "균형 ×0.97 +0", 0], ["청산", "↑ 숏청산 우위 $297K +5", 5], ["볼밴", "상단 접근 +6", 6], ["스퀴즈", "정상 +0", 0], ["ATR", "극저 변동성 +6", 6], ["레인지", "레인지 상단 +6", 6], ["FLOW", "Flow +10", 10], ["SURGE", "×0.66 +0", 0], ["KIMCHI", "+0.01%", 0]], "conflict": [], "onchain": null, "price": 77.95, "p24": 2.39, "oi4": 0.5, "oi1": -0.0, "cvd": 0.141, "fr": 0.01, "atr": 0.62, "flow": 6.1, "surge": 0.66, "ret4": 0.31, "bb_pos": 0.879, "bb_squeeze": false, "bb_just_broke": false, "rng": 0.856, "kimp": 0.01, "liq": [297090.185744, 38932.1901, 60], "vwap_broke": false, "spot_fuel": false, "turnover": 1465341603, "tradfi": false, "pinned": true, "rank": 8, "since": 1784516538, "since_min": 1084}, {"sym": "BTCUSDT", "base": "BTC", "mark": "🟡", "why": "연료 약함 — 관찰", "alpha": 66, "g": [["흡수/이탈", "— 0", 0], ["VWAP", "VWAP 위 지지 +4", 4], ["MTF", "BTC 동조화 +0", 0], ["오더북", "매도벽 압박 ×0.56 -8", -8], ["청산", "대형 숏청산 ★ $16312K +8", 8], ["볼밴", "밴드 중단 0", 0], ["스퀴즈", "정상 +0", 0], ["ATR", "극저 변동성 +6", 6], ["레인지", "레인지 상단 +6", 6], ["FLOW", "Flow +20", 20], ["SURGE", "×0.53 +0", 0], ["KIMCHI", "-0.06%", 0]], "conflict": [], "onchain": null, "price": 65323.0, "p24": 1.28, "oi4": -2.5, "oi1": -0.7, "cvd": 0.188, "fr": 0.0064, "atr": 0.51, "flow": 12.3, "surge": 0.53, "ret4": -0.36, "bb_pos": 0.77, "bb_squeeze": false, "bb_just_broke": false, "rng": 0.773, "kimp": -0.06, "liq": [16312345.346520001, 707401.33188, 130], "vwap_broke": false, "spot_fuel": false, "turnover": 11885355040, "tradfi": false, "pinned": true, "rank": 9, "since": 1784511858, "since_min": 1162}, {"sym": "CLUSDT", "base": "CL", "mark": "🟡", "why": "연료 약함 — 관찰", "alpha": 59, "g": [["흡수/이탈", "— 0", 0], ["VWAP", "VWAP 아래 저항 -4", -4], ["MTF", "BTC 동조화 +0", 0], ["오더북", "균형 ×1.07 +0", 0], ["청산", "↑ 숏청산 우위 $37K +5", 5], ["볼밴", "밴드압축 4.5% — 대기 +4", 4], ["스퀴즈", "FR스퀴즈 중 +5", 5], ["ATR", "극저 변동성 +6", 6], ["레인지", "레인지 내 0", 0], ["FLOW", "Flow +13", 13], ["SURGE", "×0.35 +0", 0], ["KIMCHI", "—", 0]], "conflict": [], "onchain": null, "price": 82.35, "p24": -1.61, "oi4": 3.4, "oi1": 0.0, "cvd": 0.541, "fr": -0.0115, "atr": 0.73, "flow": 8.0, "surge": 0.35, "ret4": 0.23, "bb_pos": 0.511, "bb_squeeze": true, "bb_just_broke": false, "rng": 0.554, "kimp": null, "liq": [36701.9378, 21618.0199, 16], "vwap_broke": true, "spot_fuel": false, "turnover": 988658932, "tradfi": false, "pinned": false, "rank": 10, "since": 1784563223, "since_min": 305}, {"sym": "ETHUSDT", "base": "ETH", "mark": "🟡", "why": "연료 약함 — 관찰", "alpha": 58, "g": [["흡수/이탈", "— 0", 0], ["VWAP", "VWAP 위 지지 +4", 4], ["MTF", "BTC 동조화 +0", 0], ["오더북", "매도벽 압박 ×0.39 -8", -8], ["청산", "대형 숏청산 ★ $8657K +8", 8], ["볼밴", "상단 접근 +6", 6], ["스퀴즈", "정상 +0", 0], ["ATR", "극저 변동성 +6", 6], ["레인지", "레인지 상단 +6", 6], ["FLOW", "Flow +6", 6], ["SURGE", "×0.47 +0", 0], ["KIMCHI", "+0.02%", 0]], "conflict": [], "onchain": null, "price": 1905.19, "p24": 2.09, "oi4": -1.0, "oi1": 0.0, "cvd": 0.154, "fr": 0.0043, "atr": 0.62, "flow": 3.5, "surge": 0.47, "ret4": -0.12, "bb_pos": 0.838, "bb_squeeze": false, "bb_just_broke": false, "rng": 0.825, "kimp": 0.02, "liq": [8657342.443190001, 183009.66692, 140], "vwap_broke": false, "spot_fuel": false, "turnover": 9495596350, "tradfi": false, "pinned": true, "rank": 11, "since": 1784408538, "since_min": 2884}, {"sym": "OPUSDT", "base": "OP", "mark": "🟡", "why": "연료 약함 — 관찰", "alpha": 51, "g": [["흡수/이탈", "— 0", 0], ["VWAP", "VWAP 아래 저항 -4", -4], ["MTF", "BTC 동조화 +0", 0], ["오더북", "매수벽 우위 ×1.53 +8", 8], ["청산", "미미 $1K 0", 0], ["볼밴", "밴드압축 3.0% — 대기 +4", 4], ["스퀴즈", "정상 +0", 0], ["ATR", "극저 변동성 +6", 6], ["레인지", "레인지 내 0", 0], ["FLOW", "Flow +7", 7], ["SURGE", "×0.62 +0", 0], ["KIMCHI", "+0.31%", 0]], "conflict": [], "onchain": null, "price": 0.0928, "p24": -1.9, "oi4": 1.8, "oi1": 0.4, "cvd": 0.228, "fr": 0.0013, "atr": 0.81, "flow": 4.5, "surge": 0.62, "ret4": -0.85, "bb_pos": 0.363, "bb_squeeze": true, "bb_just_broke": false, "rng": 0.293, "kimp": 0.31, "liq": [0, 1215.52316, 1], "vwap_broke": true, "spot_fuel": false, "turnover": 20439320, "tradfi": false, "pinned": false, "rank": 12, "since": 1784348597, "since_min": 3883}, {"sym": "INJUSDT", "base": "INJ", "mark": "🟡", "why": "연료 약함 — 관찰", "alpha": 47, "g": [["흡수/이탈", "— 0", 0], ["VWAP", "VWAP 아래 저항 -4", -4], ["MTF", "BTC 동조화 +0", 0], ["오더북", "매수벽 우위 ×1.95 +8", 8], ["청산", "↑ 숏청산 우위 $181K +5", 5], ["볼밴", "상단 접근 +6", 6], ["스퀴즈", "정상 +0", 0], ["ATR", "낮은 변동성 +3", 3], ["레인지", "레인지 상단 +6", 6], ["FLOW", "Flow -7", -7], ["SURGE", "×0.80 +0", 0], ["KIMCHI", "+0.07%", 0]], "conflict": [], "onchain": null, "price": 5.383, "p24": 4.22, "oi4": 1.4, "oi1": 0.1, "cvd": 0.242, "fr": -0.01, "atr": 1.18, "flow": -4.6, "surge": 0.8, "ret4": -0.2, "bb_pos": 0.803, "bb_squeeze": false, "bb_just_broke": false, "rng": 0.752, "kimp": 0.07, "liq": [181224.0694864, 2905.484855, 36], "vwap_broke": true, "spot_fuel": false, "turnover": 36157717, "tradfi": false, "pinned": false, "rank": 13, "since": 1784556201, "since_min": 423}, {"sym": "CBRSUSDT", "base": "CBRS", "mark": "🟡", "why": "연료 약함 — 관찰", "alpha": 46, "g": [["흡수/이탈", "— 0", 0], ["VWAP", "VWAP 아래 저항 -4", -4], ["MTF", "BTC 동조화 +0", 0], ["오더북", "매수벽 우위 ×1.91 +8", 8], ["청산", "청산 데이터 없음 0", 0], ["볼밴", "밴드압축 4.8% — 대기 +4", 4], ["스퀴즈", "정상 +0", 0], ["ATR", "낮은 변동성 +3", 3], ["레인지", "레인지 상단 +6", 6], ["FLOW", "Flow -1", -1], ["SURGE", "×0.56 +0", 0], ["KIMCHI", "—", 0]], "conflict": [], "onchain": null, "price": 177.27, "p24": 4.56, "oi4": 1.0, "oi1": 1.1, "cvd": 0.004, "fr": 0.0, "atr": 1.8, "flow": -0.4, "surge": 0.56, "ret4": -0.39, "bb_pos": 0.737, "bb_squeeze": true, "bb_just_broke": false, "rng": 0.73, "kimp": null, "liq": null, "vwap_broke": true, "spot_fuel": false, "turnover": 26232519, "tradfi": false, "pinned": false, "rank": 14, "since": 1784581401, "since_min": 2}, {"sym": "MUUUSDT", "base": "MUU", "mark": "🟡", "why": "연료 약함 — 관찰", "alpha": 45, "g": [["흡수/이탈", "ACC +28", 28], ["VWAP", "VWAP 위 지지 +4", 4], ["MTF", "BTC 동조화 +0", 0], ["오더북", "매도벽 압박 ×0.50 -8", -8], ["청산", "미미 $4K 0", 0], ["볼밴", "밴드압축 9.5% — 대기 +4", 4], ["스퀴즈", "정상 +0", 0], ["ATR", "정상 변동성 +0", 0], ["레인지", "레인지 내 0", 0], ["FLOW", "Flow -13", -13], ["SURGE", "×0.25 +0", 0], ["KIMCHI", "—", 0]], "conflict": [], "onchain": null, "price": 28.73, "p24": 4.47, "oi4": 17.2, "oi1": -4.3, "cvd": 0.11, "fr": 0.0, "atr": 2.32, "flow": -8.4, "surge": 0.25, "ret4": -3.1, "bb_pos": 0.433, "bb_squeeze": true, "bb_just_broke": false, "rng": 0.459, "kimp": null, "liq": [5.1011999999999995, 3699.9991072, 7], "vwap_broke": false, "spot_fuel": false, "turnover": 21026741, "tradfi": false, "pinned": false, "rank": 15, "since": 1784566821, "since_min": 245}, {"sym": "BILLUSDT", "base": "BILL", "mark": "🟡", "why": "연료 약함 — 관찰", "alpha": 43, "g": [["흡수/이탈", "— 0", 0], ["VWAP", "VWAP 위 지지 +4", 4], ["MTF", "BTC 동조화 +0", 0], ["오더북", "매수 우위 ×1.38 +4", 4], ["청산", "미미 $3K 0", 0], ["볼밴", "밴드압축 6.0% — 대기 +4", 4], ["스퀴즈", "정상 +0", 0], ["ATR", "낮은 변동성 +3", 3], ["레인지", "레인지 상단 +6", 6], ["FLOW", "Flow -8", -8], ["SURGE", "×0.43 +0", 0], ["KIMCHI", "—", 0]], "conflict": [], "onchain": {"src": "cold", "score": 73, "mark": "🟢", "grade": "강한 펌프 가능성", "cold_score": 73, "cold_usd": 33392242, "cold_n": 8, "cold_wallets": 3, "cold_days": 22.0, "peak": 0.2, "accum_score": null, "accum_usd": null, "accum_wallets": null, "accum_wd": null, "accum_days": null, "conc": false}, "price": 0.02483, "p24": -2.89, "oi4": 0.2, "oi1": -0.3, "cvd": 0.399, "fr": 0.005, "atr": 1.75, "flow": -5.0, "surge": 0.43, "ret4": -1.04, "bb_pos": 0.618, "bb_squeeze": true, "bb_just_broke": false, "rng": 0.671, "kimp": null, "liq": [0, 2757.8256369, 6], "vwap_broke": false, "spot_fuel": false, "turnover": 10566943, "tradfi": false, "pinned": true, "rank": 16, "since": 1784512938, "since_min": 1144}, {"sym": "ALICEUSDT", "base": "ALICE", "mark": "🟡", "why": "연료 약함 — 관찰", "alpha": 41, "g": [["흡수/이탈", "— 0", 0], ["VWAP", "VWAP 아래 저항 -4", -4], ["MTF", "BTC 동조화 +0", 0], ["오더북", "매수벽 우위 ×1.51 +8", 8], ["청산", "미미 $8K 0", 0], ["볼밴", "밴드압축 19.6% — 대기 +4", 4], ["스퀴즈", "대형 FR스퀴즈 ★ +8", 8], ["ATR", "정상 변동성 +0", 0], ["레인지", "레인지 내 0", 0], ["FLOW", "Flow -5", -5], ["SURGE", "×0.47 +0", 0], ["KIMCHI", "—", 0]], "conflict": [], "onchain": null, "price": 0.1244, "p24": 4.19, "oi4": 1.0, "oi1": -6.4, "cvd": 0.415, "fr": -0.1679, "atr": 2.66, "flow": -3.1, "surge": 0.47, "ret4": -2.04, "bb_pos": 0.361, "bb_squeeze": true, "bb_just_broke": false, "rng": 0.258, "kimp": null, "liq": [185.92067000000003, 7888.2822156, 8], "vwap_broke": true, "spot_fuel": false, "turnover": 36676367, "tradfi": false, "pinned": false, "rank": 17, "since": 1784579961, "since_min": 27}, {"sym": "DOGEUSDT", "base": "DOGE", "mark": "🟡", "why": "연료 약함 — 관찰", "alpha": 40, "g": [["흡수/이탈", "— 0", 0], ["VWAP", "VWAP 위 지지 +4", 4], ["MTF", "BTC 동조화 +0", 0], ["오더북", "매수 우위 ×1.22 +4", 4], ["청산", "↓ 롱청산 우위 $76K -6", -6], ["볼밴", "밴드 중단 0", 0], ["스퀴즈", "정상 +0", 0], ["ATR", "극저 변동성 +6", 6], ["레인지", "레인지 내 0", 0], ["FLOW", "Flow +2", 2], ["SURGE", "×1.10 +0", 0], ["KIMCHI", "+0.42%", 0]], "conflict": [], "onchain": null, "price": 0.07225, "p24": -0.06, "oi4": 1.6, "oi1": 0.1, "cvd": 0.14, "fr": 0.01, "atr": 0.86, "flow": 1.1, "surge": 1.1, "ret4": -1.14, "bb_pos": 0.462, "bb_squeeze": false, "bb_just_broke": false, "rng": 0.484, "kimp": 0.42, "liq": [291.17321, 75702.074122, 50], "vwap_broke": false, "spot_fuel": false, "turnover": 334593565, "tradfi": false, "pinned": false, "rank": 18, "since": 1784311337, "since_min": 4504}, {"sym": "ONUSDT", "base": "ON", "mark": "🟡", "why": "연료 약함 — 관찰", "alpha": 36, "g": [["흡수/이탈", "— 0", 0], ["VWAP", "VWAP 강한 돌파 +10", 10], ["MTF", "BTC 동조화 +0", 0], ["오더북", "매도 우위 ×0.76 -4", -4], ["청산", "미미 $21K 0", 0], ["볼밴", "상단 접근 +6", 6], ["스퀴즈", "정상 +0", 0], ["ATR", "정상 변동성 +0", 0], ["레인지", "고점 돌파 +4", 4], ["FLOW", "Flow -10", -10], ["SURGE", "×0.79 +0", 0], ["KIMCHI", "—", 0]], "conflict": [], "onchain": null, "price": 0.1517, "p24": 24.16, "oi4": 5.3, "oi1": 1.6, "cvd": 0.246, "fr": 0.0144, "atr": 3.91, "flow": -6.1, "surge": 0.79, "ret4": 1.04, "bb_pos": 0.893, "bb_squeeze": false, "bb_just_broke": false, "rng": 0.962, "kimp": null, "liq": [20858.1486703, 6869.5339091999995, 50], "vwap_broke": false, "spot_fuel": false, "turnover": 18110524, "tradfi": false, "pinned": false, "rank": 19, "since": 1784571862, "since_min": 161}, {"sym": "XAUUSDT", "base": "XAU", "mark": "🟡", "why": "연료 약함 — 관찰", "alpha": 36, "g": [["흡수/이탈", "— 0", 0], ["VWAP", "VWAP 아래 저항 -4", -4], ["MTF", "BTC 동조화 +0", 0], ["오더북", "매수벽 우위 ×3.38 +8", 8], ["청산", "미미 $3K 0", 0], ["볼밴", "밴드압축 0.7% — 대기 +4", 4], ["스퀴즈", "정상 +0", 0], ["ATR", "극저 변동성 +6", 6], ["레인지", "레인지 내 0", 0], ["FLOW", "Flow -8", -8], ["SURGE", "×0.33 +0", 0], ["KIMCHI", "—", 0]], "conflict": [], "onchain": null, "price": 4013.47, "p24": -0.09, "oi4": 1.2, "oi1": 0.2, "cvd": 0.546, "fr": 0.0027, "atr": 0.16, "flow": -5.1, "surge": 0.33, "ret4": 0.06, "bb_pos": 0.321, "bb_squeeze": true, "bb_just_broke": false, "rng": 0.428, "kimp": null, "liq": [3423.41728, 421.04805000000005, 5], "vwap_broke": true, "spot_fuel": false, "turnover": 1558870045, "tradfi": true, "pinned": false, "rank": 20, "since": 1784487738, "since_min": 1564}, {"sym": "XAGUSDT", "base": "XAG", "mark": "🟡", "why": "연료 약함 — 관찰", "alpha": 32, "g": [["흡수/이탈", "— 0", 0], ["VWAP", "VWAP 아래 저항 -4", -4], ["MTF", "BTC 동조화 +0", 0], ["오더북", "매수벽 우위 ×2.43 +8", 8], ["청산", "미미 $4K 0", 0], ["볼밴", "밴드압축 1.6% — 대기 +4", 4], ["스퀴즈", "정상 +0", 0], ["ATR", "극저 변동성 +6", 6], ["레인지", "레인지 내 0", 0], ["FLOW", "Flow -12", -12], ["SURGE", "×0.38 +0", 0], ["KIMCHI", "—", 0]], "conflict": [], "onchain": null, "price": 56.57, "p24": 1.29, "oi4": 2.1, "oi1": 0.6, "cvd": 0.171, "fr": 0.0043, "atr": 0.43, "flow": -7.5, "surge": 0.38, "ret4": -0.44, "bb_pos": 0.179, "bb_squeeze": true, "bb_just_broke": false, "rng": 0.49, "kimp": null, "liq": [220.384, 3818.09314, 11], "vwap_broke": true, "spot_fuel": false, "turnover": 821195092, "tradfi": true, "pinned": false, "rank": 21, "since": 1784494938, "since_min": 1444}, {"sym": "1000XECUSDT", "base": "XEC", "mark": "🟡", "why": "연료 약함 — 관찰", "alpha": 29, "g": [["흡수/이탈", "— 0", 0], ["VWAP", "VWAP 아래 저항 -4", -4], ["MTF", "BTC 동조화 +0", 0], ["오더북", "균형 ×0.96 +0", 0], ["청산", "미미 $1K 0", 0], ["볼밴", "밴드압축 7.2% — 대기 +4", 4], ["스퀴즈", "FR스퀴즈 중 +5", 5], ["ATR", "낮은 변동성 +3", 3], ["레인지", "레인지 내 0", 0], ["FLOW", "Flow -9", -9], ["SURGE", "×0.45 +0", 0], ["KIMCHI", "-99.90%", 0]], "conflict": [], "onchain": null, "price": 0.007736, "p24": -7.4, "oi4": 2.3, "oi1": 0.1, "cvd": 0.338, "fr": -0.0373, "atr": 1.33, "flow": -5.8, "surge": 0.45, "ret4": -1.7, "bb_pos": 0.289, "bb_squeeze": true, "bb_just_broke": false, "rng": 0.134, "kimp": -99.9, "liq": [1415.8263619999998, 1394.7110854999999, 14], "vwap_broke": true, "spot_fuel": false, "turnover": 33402901, "tradfi": false, "pinned": false, "rank": 22, "since": 1784531001, "since_min": 842}, {"sym": "SOXLUSDT", "base": "SOXL", "mark": "🟡", "why": "연료 약함 — 관찰", "alpha": 27, "g": [["흡수/이탈", "— 0", 0], ["VWAP", "VWAP 아래 저항 -4", -4], ["MTF", "BTC 동조화 +0", 0], ["오더북", "매수 우위 ×1.25 +4", 4], ["청산", "↓ 롱청산 우위 $167K -6", -6], ["볼밴", "밴드압축 8.9% — 대기 +4", 4], ["스퀴즈", "정상 +0", 0], ["ATR", "낮은 변동성 +3", 3], ["레인지", "레인지 내 0", 0], ["FLOW", "Flow -4", -4], ["SURGE", "×0.41 +0", 0], ["KIMCHI", "—", 0]], "conflict": [], "onchain": null, "price": 136.68, "p24": 5.29, "oi4": 0.8, "oi1": 1.1, "cvd": 0.011, "fr": 0.0, "atr": 1.92, "flow": -2.6, "surge": 0.41, "ret4": -3.49, "bb_pos": 0.235, "bb_squeeze": true, "bb_just_broke": false, "rng": 0.356, "kimp": null, "liq": [9439.6196412, 166783.5260474, 40], "vwap_broke": true, "spot_fuel": false, "turnover": 2196140824, "tradfi": true, "pinned": false, "rank": 23, "since": 1784555841, "since_min": 428}, {"sym": "ORCLUSDT", "base": "ORCL", "mark": "🟡", "why": "연료 약함 — 관찰", "alpha": 26, "g": [["흡수/이탈", "— 0", 0], ["VWAP", "VWAP 아래 저항 -4", -4], ["MTF", "BTC 동조화 +0", 0], ["오더북", "매도 우위 ×0.67 -4", -4], ["청산", "청산 데이터 없음 0", 0], ["볼밴", "밴드 중단 0", 0], ["스퀴즈", "정상 +0", 0], ["ATR", "극저 변동성 +6", 6], ["레인지", "레인지 내 0", 0], ["FLOW", "Flow -2", -2], ["SURGE", "×0.31 +0", 0], ["KIMCHI", "—", 0]], "conflict": [], "onchain": null, "price": 121.86, "p24": -3.81, "oi4": 0.9, "oi1": 1.9, "cvd": 0.397, "fr": 0.0, "atr": 0.81, "flow": -1.5, "surge": 0.31, "ret4": -1.0, "bb_pos": 0.219, "bb_squeeze": false, "bb_just_broke": false, "rng": 0.225, "kimp": null, "liq": null, "vwap_broke": true, "spot_fuel": false, "turnover": 21538801, "tradfi": false, "pinned": false, "rank": 24, "since": 1784557461, "since_min": 402}, {"sym": "RKLBUSDT", "base": "RKLB", "mark": "🟡", "why": "연료 약함 — 관찰", "alpha": 23, "g": [["흡수/이탈", "— 0", 0], ["VWAP", "VWAP 아래 저항 -4", -4], ["MTF", "BTC 동조화 +0", 0], ["오더북", "균형 ×0.98 +0", 0], ["청산", "청산 데이터 없음 0", 0], ["볼밴", "밴드 하단 -3", -3], ["스퀴즈", "정상 +0", 0], ["ATR", "낮은 변동성 +3", 3], ["레인지", "레인지 내 0", 0], ["FLOW", "Flow -3", -3], ["SURGE", "×0.42 +0", 0], ["KIMCHI", "—", 0]], "conflict": [], "onchain": null, "price": 66.03, "p24": -2.64, "oi4": 2.2, "oi1": 0.1, "cvd": 0.067, "fr": 0.0, "atr": 1.32, "flow": -1.6, "surge": 0.42, "ret4": -1.37, "bb_pos": 0.171, "bb_squeeze": false, "bb_just_broke": false, "rng": 0.104, "kimp": null, "liq": null, "vwap_broke": true, "spot_fuel": false, "turnover": 18968312, "tradfi": false, "pinned": false, "rank": 25, "since": 1784561421, "since_min": 335}, {"sym": "ZAMAUSDT", "base": "ZAMA", "mark": "🟡", "why": "연료 약함 — 관찰", "alpha": 20, "g": [["흡수/이탈", "— 0", 0], ["VWAP", "VWAP 아래 저항 -4", -4], ["MTF", "BTC 동조화 +0", 0], ["오더북", "균형 ×0.99 +0", 0], ["청산", "미미 $3K 0", 0], ["볼밴", "밴드 중단 0", 0], ["스퀴즈", "정상 +0", 0], ["ATR", "낮은 변동성 +3", 3], ["레인지", "레인지 내 0", 0], ["FLOW", "Flow -9", -9], ["SURGE", "×0.22 +0", 0], ["KIMCHI", "+0.16%", 0]], "conflict": [], "onchain": null, "price": 0.0382, "p24": 6.5, "oi4": 3.9, "oi1": 0.9, "cvd": 0.262, "fr": -0.0046, "atr": 1.7, "flow": -5.9, "surge": 0.22, "ret4": -2.45, "bb_pos": 0.524, "bb_squeeze": false, "bb_just_broke": false, "rng": 0.512, "kimp": 0.16, "liq": [77.15922, 3141.698022, 15], "vwap_broke": true, "spot_fuel": false, "turnover": 23893880, "tradfi": false, "pinned": false, "rank": 26, "since": 1784573842, "since_min": 128}, {"sym": "GOOGLUSDT", "base": "GOOGL", "mark": "🟡", "why": "연료 약함 — 관찰", "alpha": 20, "g": [["흡수/이탈", "— 0", 0], ["VWAP", "VWAP 위 지지 +4", 4], ["MTF", "BTC 동조화 +0", 0], ["오더북", "매도벽 압박 ×0.46 -8", -8], ["청산", "미미 $0K 0", 0], ["볼밴", "밴드 중단 0", 0], ["스퀴즈", "정상 +0", 0], ["ATR", "극저 변동성 +6", 6], ["레인지", "레인지 내 0", 0], ["FLOW", "Flow -12", -12], ["SURGE", "×0.22 +0", 0], ["KIMCHI", "—", 0]], "conflict": [], "onchain": null, "price": 352.88, "p24": 1.39, "oi4": 3.4, "oi1": 1.0, "cvd": 0.694, "fr": 0.0, "atr": 0.38, "flow": -7.5, "surge": 0.22, "ret4": -0.13, "bb_pos": 0.63, "bb_squeeze": false, "bb_just_broke": false, "rng": 0.444, "kimp": null, "liq": [0, 169.14239999999998, 1], "vwap_broke": false, "spot_fuel": false, "turnover": 36520259, "tradfi": true, "pinned": false, "rank": 27, "since": 1784556201, "since_min": 423}, {"sym": "AMDUSDT", "base": "AMD", "mark": "🟡", "why": "연료 약함 — 관찰", "alpha": 19, "g": [["흡수/이탈", "— 0", 0], ["VWAP", "VWAP 아래 저항 -4", -4], ["MTF", "BTC 동조화 +0", 0], ["오더북", "매도벽 압박 ×0.24 -8", -8], ["청산", "청산 데이터 없음 0", 0], ["볼밴", "밴드압축 4.1% — 대기 +4", 4], ["스퀴즈", "정상 +0", 0], ["ATR", "낮은 변동성 +3", 3], ["레인지", "레인지 내 0", 0], ["FLOW", "Flow -6", -6], ["SURGE", "×0.29 +0", 0], ["KIMCHI", "—", 0]], "conflict": [], "onchain": null, "price": 504.17, "p24": 2.05, "oi4": 0.8, "oi1": -0.3, "cvd": 0.597, "fr": 0.0, "atr": 1.0, "flow": -3.9, "surge": 0.29, "ret4": -1.65, "bb_pos": 0.372, "bb_squeeze": true, "bb_just_broke": false, "rng": 0.277, "kimp": null, "liq": null, "vwap_broke": true, "spot_fuel": false, "turnover": 54470625, "tradfi": true, "pinned": false, "rank": 28, "since": 1784570602, "since_min": 182}, {"sym": "SPCXUSDT", "base": "SPCX", "mark": "🟡", "why": "연료 약함 — 관찰", "alpha": 8, "g": [["흡수/이탈", "— 0", 0], ["VWAP", "VWAP 아래 저항 -4", -4], ["MTF", "BTC 동조화 +0", 0], ["오더북", "매도벽 압박 ×0.38 -8", -8], ["청산", "↓ 롱청산 우위 $490K -6", -6], ["볼밴", "밴드 하단 -3", -3], ["스퀴즈", "정상 +0", 0], ["ATR", "낮은 변동성 +3", 3], ["레인지", "레인지 내 0", 0], ["FLOW", "Flow -4", -4], ["SURGE", "×0.33 +0", 0], ["KIMCHI", "—", 0]], "conflict": [], "onchain": null, "price": 120.55, "p24": -5.97, "oi4": 1.1, "oi1": -0.1, "cvd": 0.218, "fr": 0.0, "atr": 1.06, "flow": -2.6, "surge": 0.33, "ret4": -1.73, "bb_pos": 0.111, "bb_squeeze": false, "bb_just_broke": false, "rng": 0.105, "kimp": null, "liq": [12136.1365223, 489866.69997819996, 81], "vwap_broke": true, "spot_fuel": false, "turnover": 686388532, "tradfi": true, "pinned": false, "rank": 29, "since": 1784581401, "since_min": 2}, {"sym": "TSLAUSDT", "base": "TSLA", "mark": "🟡", "why": "연료 약함 — 관찰", "alpha": 5, "g": [["흡수/이탈", "— 0", 0], ["VWAP", "VWAP 아래 저항 -4", -4], ["MTF", "BTC 동조화 +0", 0], ["오더북", "매수 우위 ×1.17 +4", 4], ["청산", "미미 $6K 0", 0], ["볼밴", "밴드 하단 -3", -3], ["스퀴즈", "정상 +0", 0], ["ATR", "극저 변동성 +6", 6], ["레인지", "저점 근접 -6", -6], ["FLOW", "Flow -22", -22], ["SURGE", "×0.26 +0", 0], ["KIMCHI", "—", 0]], "conflict": [], "onchain": null, "price": 370.55, "p24": -2.98, "oi4": 2.2, "oi1": 1.0, "cvd": 0.14, "fr": 0.0, "atr": 0.49, "flow": -13.5, "surge": 0.26, "ret4": -0.79, "bb_pos": 0.137, "bb_squeeze": false, "bb_just_broke": false, "rng": 0.044, "kimp": null, "liq": [0, 5515.4960098, 9], "vwap_broke": true, "spot_fuel": false, "turnover": 44140212, "tradfi": true, "pinned": false, "rank": 30, "since": 1784556201, "since_min": 423}, {"sym": "HEMIUSDT", "base": "HEMI", "mark": "🔴", "why": "수직급등 +71% — 과열 추격금지", "alpha": 67, "g": [["흡수/이탈", "— 0", 0], ["VWAP", "VWAP 강한 돌파 +10", 10], ["MTF", "BTC 대비 초강세 +12", 12], ["오더북", "매도벽 압박 ×0.65 -8", -8], ["청산", "↑ 숏청산 우위 $118K +5", 5], ["볼밴", "밴드 밖 진행중 — 이미 감 0", 0], ["스퀴즈", "대형 FR스퀴즈 ★ +8", 8], ["ATR", "고변동성 -4", -4], ["레인지", "레인지 상단 +6", 6], ["FLOW", "Flow +0", 0], ["SURGE", "×2.50 +8", 8], ["KIMCHI", "—", 0]], "conflict": [], "onchain": null, "price": 0.007658, "p24": 70.56, "oi4": 15.1, "oi1": 9.7, "cvd": 0.864, "fr": -0.0603, "atr": 10.5, "flow": -0.2, "surge": 2.5, "ret4": 29.51, "bb_pos": 1.07, "bb_squeeze": false, "bb_just_broke": false, "rng": 0.922, "kimp": null, "liq": [118420.7349509, 39232.2415668, 183], "vwap_broke": false, "spot_fuel": false, "turnover": 69094181, "tradfi": false, "pinned": false, "rank": 31, "since": 1784580322, "since_min": 20}, {"sym": "NIGHTUSDT", "base": "NIGHT", "mark": "🔴", "why": "하락 중 -35% — 롱 근거 없음", "alpha": 49, "g": [["흡수/이탈", "ACC +28", 28], ["VWAP", "VWAP 아래 저항 -4", -4], ["MTF", "BTC 대비 약세 -6", -6], ["오더북", "균형 ×0.93 +0", 0], ["청산", "↓ 롱청산 우위 $191K -6", -6], ["볼밴", "밴드 하단 -3", -3], ["스퀴즈", "정상 +0", 0], ["ATR", "고변동성 -4", -4], ["레인지", "레인지 내 0", 0], ["FLOW", "Flow -4", -4], ["SURGE", "×4.78 +18", 18], ["KIMCHI", "—", 0]], "conflict": [], "onchain": null, "price": 0.0172, "p24": -35.17, "oi4": 47.5, "oi1": 13.2, "cvd": 0.0, "fr": -0.0024, "atr": 11.05, "flow": -2.7, "surge": 4.78, "ret4": -15.89, "bb_pos": -0.016, "bb_squeeze": false, "bb_just_broke": false, "rng": 0.177, "kimp": null, "liq": [64187.8847982, 190925.8771256, 274], "vwap_broke": true, "spot_fuel": false, "turnover": 39285834, "tradfi": false, "pinned": false, "rank": 32, "since": 1784572941, "since_min": 143}, {"sym": "ACEUSDT", "base": "ACE", "mark": "🔴", "why": "수직급등 +63% — 과열 추격금지", "alpha": 32, "g": [["흡수/이탈", "— 0", 0], ["VWAP", "VWAP 아래 저항 -4", -4], ["MTF", "BTC 동조화 +0", 0], ["오더북", "균형 ×0.94 +0", 0], ["청산", "혼조 0", 0], ["볼밴", "밴드압축 52.4% — 대기 +4", 4], ["스퀴즈", "대형 FR스퀴즈 ★ +8", 8], ["ATR", "고변동성 -4", -4], ["레인지", "레인지 내 0", 0], ["FLOW", "Flow -2", -2], ["SURGE", "×0.69 +0", 0], ["KIMCHI", "—", 0]], "conflict": [], "onchain": null, "price": 0.11709, "p24": 62.6, "oi4": 7.5, "oi1": 0.0, "cvd": 0.615, "fr": -0.4388, "atr": 8.46, "flow": -1.4, "surge": 0.69, "ret4": -4.14, "bb_pos": 0.418, "bb_squeeze": true, "bb_just_broke": false, "rng": 0.535, "kimp": null, "liq": [160595.31970595, 111906.63514648999, 340], "vwap_broke": true, "spot_fuel": false, "turnover": 520653586, "tradfi": false, "pinned": false, "rank": 33, "since": 1784528662, "since_min": 881}, {"sym": "TLMUSDT", "base": "TLM", "mark": "🔴", "why": "하락 중 -23% — 롱 근거 없음", "alpha": 29, "g": [["흡수/이탈", "— 0", 0], ["VWAP", "VWAP 아래 저항 -4", -4], ["MTF", "BTC 동조화 +0", 0], ["오더북", "매수 우위 ×1.20 +4", 4], ["청산", "미미 $8K 0", 0], ["볼밴", "밴드압축 28.2% — 대기 +4", 4], ["스퀴즈", "대형 FR스퀴즈 ★ +8", 8], ["ATR", "정상 변동성 +0", 0], ["레인지", "저점 근접 -6", -6], ["FLOW", "Flow -7", -7], ["SURGE", "×0.33 +0", 0], ["KIMCHI", "—", 0]], "conflict": [], "onchain": null, "price": 0.001863, "p24": -22.76, "oi4": 1.7, "oi1": 1.0, "cvd": 0.345, "fr": -0.0883, "atr": 2.01, "flow": -4.5, "surge": 0.33, "ret4": -2.46, "bb_pos": 0.263, "bb_squeeze": true, "bb_just_broke": false, "rng": 0.027, "kimp": null, "liq": [1494.8310288, 7877.6202155, 18], "vwap_broke": true, "spot_fuel": false, "turnover": 95193367, "tradfi": false, "pinned": false, "rank": 34, "since": 1784581401, "since_min": 2}]}