{"updated": "2026-07-20 22:33:21", "updated_ts": 1784554401, "scan_sec": 180, "us_open": false, "ws": true, "liq_events": 9899, "count": 35, "cols": ["흡수/이탈", "VWAP", "MTF", "오더북", "청산", "볼밴", "스퀴즈", "ATR", "레인지", "FLOW", "SURGE", "KIMCHI"], "rows": [{"sym": "HEMIUSDT", "base": "HEMI", "mark": "💎", "why": "순위권 + 강한연료 — 아직 갈 자리", "alpha": 62, "g": [["흡수/이탈", "— 0", 0], ["VWAP", "VWAP 강한 돌파 +10", 10], ["MTF", "BTC 대비 초강세 +12", 12], ["오더북", "매수벽 우위 ×1.69 +8", 8], ["청산", "미미 $3K 0", 0], ["볼밴", "밴드 밖 진행중 — 이미 감 0", 0], ["스퀴즈", "정상 +0", 0], ["ATR", "정상 변동성 +0", 0], ["레인지", "레인지 상단 +6", 6], ["FLOW", "Flow -8", -8], ["SURGE", "×1.72 +4", 4], ["KIMCHI", "—", 0]], "conflict": ["볼밴 이미 감", "이미 +18%"], "onchain": null, "price": 0.005397, "p24": 17.94, "oi4": 9.0, "oi1": 2.0, "cvd": 1.0, "fr": -0.0045, "atr": 5.43, "flow": -4.9, "surge": 1.72, "ret4": 8.23, "bb_pos": 1.091, "bb_squeeze": false, "bb_just_broke": false, "rng": 0.825, "kimp": null, "liq": [2795.7607358, 2774.2473044999997, 16], "vwap_broke": false, "spot_fuel": false, "turnover": 13340684, "tradfi": false, "pinned": false, "rank": 1, "since": 1784553861, "since_min": 9}, {"sym": "PAXGUSDT", "base": "PAXG", "mark": "⭐", "why": "현물주도 상승 — 실제 돈", "alpha": 21, "g": [["흡수/이탈", "— 0", 0], ["VWAP", "VWAP 아래 저항 -4", -4], ["MTF", "BTC 동조화 +0", 0], ["오더북", "매도 우위 ×0.79 -4", -4], ["청산", "↓ 롱청산 우위 $44K -6", -6], ["볼밴", "밴드 중단 0", 0], ["스퀴즈", "정상 +0", 0], ["ATR", "극저 변동성 +6", 6], ["레인지", "레인지 내 0", 0], ["FLOW", "Flow -9", -9], ["SURGE", "×2.06 +8", 8], ["KIMCHI", "—", 0]], "conflict": ["VWAP 아래", "매도벽"], "onchain": null, "price": 4008.68, "p24": 0.09, "oi4": 1.7, "oi1": 0.7, "cvd": 0.741, "fr": 0.005, "atr": 0.32, "flow": -5.3, "surge": 2.06, "ret4": -0.16, "bb_pos": 0.519, "bb_squeeze": false, "bb_just_broke": false, "rng": 0.53, "kimp": null, "liq": [598.6596499999999, 44425.7484311, 11], "vwap_broke": true, "spot_fuel": true, "turnover": 51517816, "tradfi": false, "pinned": false, "rank": 2, "since": 1784554401, "since_min": 0}, {"sym": "PROMUSDT", "base": "PROM", "mark": "🟢", "why": "연료생존 — 진입검토", "alpha": 100, "g": [["흡수/이탈", "— 0", 0], ["VWAP", "VWAP 강한 돌파 +10", 10], ["MTF", "BTC 대비 초강세 +12", 12], ["오더북", "매수벽 우위 ×2.11 +8", 8], ["청산", "↑ 숏청산 우위 $173K +5", 5], ["볼밴", "방금 상단 돌파 — 초입 +8", 8], ["스퀴즈", "FR스퀴즈 중 +5", 5], ["ATR", "고변동성 -4", -4], ["레인지", "고점 돌파 +4", 4], ["FLOW", "Flow +6", 6], ["SURGE", "×3.16 +18", 18], ["KIMCHI", "—", 0]], "conflict": ["레인지 고점", "이미 +59%"], "onchain": null, "price": 2.22, "p24": 58.8, "oi4": 15.2, "oi1": 7.4, "cvd": 0.87, "fr": -0.0359, "atr": 9.93, "flow": 3.4, "surge": 3.16, "ret4": 23.74, "bb_pos": 1.425, "bb_squeeze": false, "bb_just_broke": true, "rng": 0.953, "kimp": null, "liq": [172645.18628145, 49269.74070677, 187], "vwap_broke": false, "spot_fuel": false, "turnover": 69638551, "tradfi": false, "pinned": false, "rank": 3, "since": 1784553141, "since_min": 21}, {"sym": "SOXLUSDT", "base": "SOXL", "mark": "🟢", "why": "연료생존 — 진입검토", "alpha": 57, "g": [["흡수/이탈", "— 0", 0], ["VWAP", "VWAP 위 지지 +4", 4], ["MTF", "BTC 대비 강세 +6", 6], ["오더북", "매도벽 압박 ×0.63 -8", -8], ["청산", "↑ 숏청산 우위 $45K +5", 5], ["볼밴", "상단 접근 +6", 6], ["스퀴즈", "정상 +0", 0], ["ATR", "정상 변동성 +0", 0], ["레인지", "레인지 상단 +6", 6], ["FLOW", "Flow +4", 4], ["SURGE", "×1.93 +4", 4], ["KIMCHI", "—", 0]], "conflict": ["매도벽"], "onchain": null, "price": 145.73, "p24": 9.8, "oi4": 4.0, "oi1": 0.7, "cvd": 0.745, "fr": 0.0351, "atr": 2.6, "flow": 2.8, "surge": 1.93, "ret4": 3.55, "bb_pos": 0.934, "bb_squeeze": false, "bb_just_broke": false, "rng": 0.932, "kimp": null, "liq": [45262.5523779, 7239.402357599999, 38], "vwap_broke": false, "spot_fuel": false, "turnover": 1094104169, "tradfi": true, "pinned": false, "rank": 4, "since": 1784554401, "since_min": 0}, {"sym": "NBISUSDT", "base": "NBIS", "mark": "🟢", "why": "연료생존 — 진입검토", "alpha": 51, "g": [["흡수/이탈", "— 0", 0], ["VWAP", "VWAP 강한 돌파 +10", 10], ["MTF", "BTC 대비 강세 +6", 6], ["오더북", "매도벽 압박 ×0.53 -8", -8], ["청산", "미미 $0K 0", 0], ["볼밴", "밴드 밖 진행중 — 이미 감 0", 0], ["스퀴즈", "롱 과열 -4", -4], ["ATR", "정상 변동성 +0", 0], ["레인지", "고점 돌파 +4", 4], ["FLOW", "Flow -5", -5], ["SURGE", "×3.73 +18", 18], ["KIMCHI", "—", 0]], "conflict": ["볼밴 이미 감", "레인지 고점", "매도벽"], "onchain": null, "price": 190.31, "p24": 8.61, "oi4": 3.3, "oi1": 1.5, "cvd": 1.0, "fr": 0.0835, "atr": 2.12, "flow": -2.9, "surge": 3.73, "ret4": 4.46, "bb_pos": 1.177, "bb_squeeze": false, "bb_just_broke": false, "rng": 0.97, "kimp": null, "liq": [9.204, 0, 1], "vwap_broke": false, "spot_fuel": false, "turnover": 20442620, "tradfi": false, "pinned": false, "rank": 5, "since": 1784554401, "since_min": 0}, {"sym": "HANAUSDT", "base": "HANA", "mark": "🟢", "why": "연료생존 — 진입검토", "alpha": 47, "g": [["흡수/이탈", "— 0", 0], ["VWAP", "VWAP 위 지지 +4", 4], ["MTF", "BTC 대비 강세 +6", 6], ["오더북", "매수 우위 ×1.27 +4", 4], ["청산", "↓ 롱청산 우위 $49K -6", -6], ["볼밴", "상단 접근 +6", 6], ["스퀴즈", "롱 과열 -4", -4], ["ATR", "고변동성 -4", -4], ["레인지", "레인지 상단 +6", 6], ["FLOW", "Flow -3", -3], ["SURGE", "×2.24 +8", 8], ["KIMCHI", "—", 0]], "conflict": ["이미 +28%"], "onchain": null, "price": 0.04672, "p24": 28.14, "oi4": 12.4, "oi1": 2.5, "cvd": 0.553, "fr": 0.0713, "atr": 12.13, "flow": -1.6, "surge": 2.24, "ret4": 6.53, "bb_pos": 0.959, "bb_squeeze": false, "bb_just_broke": false, "rng": 0.624, "kimp": null, "liq": [13012.102048199999, 48810.0827552, 90], "vwap_broke": false, "spot_fuel": false, "turnover": 33376953, "tradfi": false, "pinned": false, "rank": 6, "since": 1784553501, "since_min": 14}, {"sym": "INTCUSDT", "base": "INTC", "mark": "🟡", "why": "연료 약함 — 관찰", "alpha": 89, "g": [["흡수/이탈", "— 0", 0], ["VWAP", "VWAP 강한 돌파 +10", 10], ["MTF", "BTC 대비 강세 +6", 6], ["오더북", "매수벽 우위 ×2.41 +8", 8], ["청산", "미미 $2K 0", 0], ["볼밴", "방금 상단 돌파 — 초입 +8", 8], ["스퀴즈", "정상 +0", 0], ["ATR", "낮은 변동성 +3", 3], ["레인지", "고점 돌파 +4", 4], ["FLOW", "Flow +2", 2], ["SURGE", "×4.13 +18", 18], ["KIMCHI", "—", 0]], "conflict": [], "onchain": null, "price": 99.14, "p24": 4.91, "oi4": 1.7, "oi1": 0.8, "cvd": 0.797, "fr": 0.0193, "atr": 1.5, "flow": 1.4, "surge": 4.13, "ret4": 2.78, "bb_pos": 1.12, "bb_squeeze": false, "bb_just_broke": true, "rng": 1.0, "kimp": null, "liq": [2207.2604392000003, 8.7804, 2], "vwap_broke": false, "spot_fuel": false, "turnover": 56535541, "tradfi": true, "pinned": false, "rank": 7, "since": 1784541622, "since_min": 212}, {"sym": "LITEUSDT", "base": "LITE", "mark": "🟡", "why": "연료 약함 — 관찰", "alpha": 72, "g": [["흡수/이탈", "— 0", 0], ["VWAP", "VWAP 강한 돌파 +10", 10], ["MTF", "BTC 대비 강세 +6", 6], ["오더북", "매도벽 압박 ×0.62 -8", -8], ["청산", "미미 $0K 0", 0], ["볼밴", "방금 상단 돌파 — 초입 +8", 8], ["스퀴즈", "정상 +0", 0], ["ATR", "낮은 변동성 +3", 3], ["레인지", "레인지 상단 +6", 6], ["FLOW", "Flow +13", 13], ["SURGE", "×1.77 +4", 4], ["KIMCHI", "—", 0]], "conflict": [], "onchain": null, "price": 784.6, "p24": 8.26, "oi4": 2.8, "oi1": -0.1, "cvd": 0.833, "fr": 0.0, "atr": 1.56, "flow": 7.8, "surge": 1.77, "ret4": 3.65, "bb_pos": 1.196, "bb_squeeze": false, "bb_just_broke": true, "rng": 0.941, "kimp": null, "liq": [328.4745987, 0, 3], "vwap_broke": false, "spot_fuel": false, "turnover": 13534316, "tradfi": false, "pinned": false, "rank": 8, "since": 1784554401, "since_min": 0}, {"sym": "FILUSDT", "base": "FIL", "mark": "🟡", "why": "연료 약함 — 관찰", "alpha": 64, "g": [["흡수/이탈", "— 0", 0], ["VWAP", "VWAP 위 지지 +4", 4], ["MTF", "BTC 동조화 +0", 0], ["오더북", "균형 ×0.98 +0", 0], ["청산", "미미 $3K 0", 0], ["볼밴", "밴드압축 2.7% — 대기 +4", 4], ["스퀴즈", "FR스퀴즈 중 +5", 5], ["ATR", "극저 변동성 +6", 6], ["레인지", "레인지 상단 +6", 6], ["FLOW", "Flow +9", 9], ["SURGE", "×0.60 +0", 0], ["KIMCHI", "-0.02%", 0]], "conflict": [], "onchain": null, "price": 0.7161, "p24": -1.47, "oi4": 1.4, "oi1": 0.7, "cvd": 0.735, "fr": -0.0189, "atr": 0.63, "flow": 5.6, "surge": 0.6, "ret4": 1.29, "bb_pos": 0.631, "bb_squeeze": true, "bb_just_broke": false, "rng": 0.603, "kimp": -0.02, "liq": [112.47681, 2872.85156, 5], "vwap_broke": false, "spot_fuel": false, "turnover": 51977157, "tradfi": false, "pinned": false, "rank": 9, "since": 1784293517, "since_min": 4348}, {"sym": "SOLUSDT", "base": "SOL", "mark": "🟡", "why": "연료 약함 — 관찰", "alpha": 58, "g": [["흡수/이탈", "— 0", 0], ["VWAP", "VWAP 위 지지 +4", 4], ["MTF", "BTC 동조화 +0", 0], ["오더북", "균형 ×1.12 +0", 0], ["청산", "대형 숏청산 ★ $552K +8", 8], ["볼밴", "상단 접근 +6", 6], ["스퀴즈", "정상 +0", 0], ["ATR", "극저 변동성 +6", 6], ["레인지", "레인지 상단 +6", 6], ["FLOW", "Flow -2", -2], ["SURGE", "×1.07 +0", 0], ["KIMCHI", "+0.17%", 0]], "conflict": [], "onchain": null, "price": 76.78, "p24": 0.95, "oi4": 0.5, "oi1": -0.1, "cvd": 0.572, "fr": 0.0011, "atr": 0.68, "flow": -1.5, "surge": 1.07, "ret4": 0.52, "bb_pos": 0.82, "bb_squeeze": false, "bb_just_broke": false, "rng": 0.726, "kimp": 0.17, "liq": [552069.3226, 4552.3418, 45], "vwap_broke": false, "spot_fuel": false, "turnover": 1073719789, "tradfi": false, "pinned": true, "rank": 10, "since": 1784516538, "since_min": 631}, {"sym": "SAMSUNGUSDT", "base": "SAMSUNG", "mark": "🟡", "why": "연료 약함 — 관찰", "alpha": 57, "g": [["흡수/이탈", "— 0", 0], ["VWAP", "VWAP 위 지지 +4", 4], ["MTF", "BTC 동조화 +0", 0], ["오더북", "매수 우위 ×1.23 +4", 4], ["청산", "청산 데이터 없음 0", 0], ["볼밴", "상단 접근 +6", 6], ["스퀴즈", "정상 +0", 0], ["ATR", "낮은 변동성 +3", 3], ["레인지", "레인지 상단 +6", 6], ["FLOW", "Flow +4", 4], ["SURGE", "×0.36 +0", 0], ["KIMCHI", "—", 0]], "conflict": [], "onchain": null, "price": 170.45, "p24": 1.11, "oi4": 2.0, "oi1": -1.1, "cvd": 0.784, "fr": 0.0, "atr": 1.12, "flow": 2.4, "surge": 0.36, "ret4": 1.37, "bb_pos": 0.867, "bb_squeeze": false, "bb_just_broke": false, "rng": 0.703, "kimp": null, "liq": null, "vwap_broke": false, "spot_fuel": false, "turnover": 118589044, "tradfi": true, "pinned": false, "rank": 11, "since": 1784516538, "since_min": 631}, {"sym": "ETHUSDT", "base": "ETH", "mark": "🟡", "why": "연료 약함 — 관찰", "alpha": 53, "g": [["흡수/이탈", "— 0", 0], ["VWAP", "VWAP 아래 저항 -4", -4], ["MTF", "BTC 동조화 +0", 0], ["오더북", "매수벽 우위 ×1.65 +8", 8], ["청산", "대형 숏청산 ★ $3543K +8", 8], ["볼밴", "밴드 중단 0", 0], ["스퀴즈", "정상 +0", 0], ["ATR", "극저 변동성 +6", 6], ["레인지", "레인지 내 0", 0], ["FLOW", "Flow +5", 5], ["SURGE", "×1.35 +0", 0], ["KIMCHI", "+0.08%", 0]], "conflict": [], "onchain": null, "price": 1872.53, "p24": 0.07, "oi4": -0.8, "oi1": -1.4, "cvd": 0.674, "fr": 0.0024, "atr": 0.93, "flow": 3.2, "surge": 1.35, "ret4": 0.55, "bb_pos": 0.665, "bb_squeeze": false, "bb_just_broke": false, "rng": 0.586, "kimp": 0.08, "liq": [3543366.18512, 1481951.05171, 186], "vwap_broke": true, "spot_fuel": false, "turnover": 7040359924, "tradfi": false, "pinned": true, "rank": 12, "since": 1784408538, "since_min": 2431}, {"sym": "GLWUSDT", "base": "GLW", "mark": "🟡", "why": "연료 약함 — 관찰", "alpha": 52, "g": [["흡수/이탈", "— 0", 0], ["VWAP", "VWAP 위 지지 +4", 4], ["MTF", "BTC 동조화 +0", 0], ["오더북", "매수 우위 ×1.18 +4", 4], ["청산", "청산 데이터 없음 0", 0], ["볼밴", "밴드 중단 0", 0], ["스퀴즈", "정상 +0", 0], ["ATR", "낮은 변동성 +3", 3], ["레인지", "레인지 상단 +6", 6], ["FLOW", "Flow +1", 1], ["SURGE", "×1.62 +4", 4], ["KIMCHI", "—", 0]], "conflict": [], "onchain": null, "price": 159.73, "p24": 0.61, "oi4": 1.4, "oi1": 0.5, "cvd": 0.223, "fr": 0.0101, "atr": 1.28, "flow": 0.3, "surge": 1.62, "ret4": 0.8, "bb_pos": 0.782, "bb_squeeze": false, "bb_just_broke": false, "rng": 0.785, "kimp": null, "liq": null, "vwap_broke": false, "spot_fuel": false, "turnover": 15894910, "tradfi": false, "pinned": false, "rank": 13, "since": 1784485218, "since_min": 1153}, {"sym": "AAVEUSDT", "base": "AAVE", "mark": "🟡", "why": "연료 약함 — 관찰", "alpha": 51, "g": [["흡수/이탈", "— 0", 0], ["VWAP", "VWAP 아래 저항 -4", -4], ["MTF", "BTC 동조화 +0", 0], ["오더북", "균형 ×0.88 +0", 0], ["청산", "미미 $7K 0", 0], ["볼밴", "밴드 중단 0", 0], ["스퀴즈", "정상 +0", 0], ["ATR", "극저 변동성 +6", 6], ["레인지", "레인지 상단 +6", 6], ["FLOW", "Flow +13", 13], ["SURGE", "×1.12 +0", 0], ["KIMCHI", "+0.12%", 0]], "conflict": [], "onchain": null, "price": 90.29, "p24": 0.72, "oi4": 1.7, "oi1": 0.1, "cvd": 0.321, "fr": 0.0025, "atr": 0.71, "flow": 8.2, "surge": 1.12, "ret4": -0.41, "bb_pos": 0.775, "bb_squeeze": false, "bb_just_broke": false, "rng": 0.658, "kimp": 0.12, "liq": [3584.2026, 7046.6782, 7], "vwap_broke": true, "spot_fuel": false, "turnover": 42805622, "tradfi": false, "pinned": false, "rank": 14, "since": 1784170952, "since_min": 6390}, {"sym": "APTUSDT", "base": "APT", "mark": "🟡", "why": "연료 약함 — 관찰", "alpha": 50, "g": [["흡수/이탈", "— 0", 0], ["VWAP", "VWAP 아래 저항 -4", -4], ["MTF", "BTC 동조화 +0", 0], ["오더북", "균형 ×0.89 +0", 0], ["청산", "미미 $4K 0", 0], ["볼밴", "밴드압축 2.8% — 대기 +4", 4], ["스퀴즈", "FR스퀴즈 중 +5", 5], ["ATR", "극저 변동성 +6", 6], ["레인지", "레인지 내 0", 0], ["FLOW", "Flow +9", 9], ["SURGE", "×1.03 +0", 0], ["KIMCHI", "+0.06%", 0]], "conflict": [], "onchain": null, "price": 0.5889, "p24": -1.77, "oi4": 1.5, "oi1": -0.1, "cvd": 0.603, "fr": -0.02, "atr": 0.99, "flow": 5.7, "surge": 1.03, "ret4": 0.53, "bb_pos": 0.452, "bb_squeeze": true, "bb_just_broke": false, "rng": 0.414, "kimp": 0.06, "liq": [3957.1980599999997, 1071.70317, 6], "vwap_broke": true, "spot_fuel": false, "turnover": 16575932, "tradfi": false, "pinned": false, "rank": 15, "since": 1784379737, "since_min": 2911}, {"sym": "LABUSDT", "base": "LAB", "mark": "🟡", "why": "연료 약함 — 관찰", "alpha": 49, "g": [["흡수/이탈", "— 0", 0], ["VWAP", "VWAP 강한 돌파 +10", 10], ["MTF", "BTC 대비 강세 +6", 6], ["오더북", "매도벽 압박 ×0.51 -8", -8], ["청산", "미미 $30K 0", 0], ["볼밴", "밴드압축 9.9% — 대기 +4", 4], ["스퀴즈", "정상 +0", 0], ["ATR", "정상 변동성 +0", 0], ["레인지", "레인지 내 0", 0], ["FLOW", "Flow +7", 7], ["SURGE", "×1.30 +0", 0], ["KIMCHI", "—", 0]], "conflict": [], "onchain": null, "price": 0.1541, "p24": -10.25, "oi4": 2.2, "oi1": 0.3, "cvd": 0.819, "fr": 0.0202, "atr": 4.87, "flow": 4.7, "surge": 1.3, "ret4": 6.13, "bb_pos": 0.768, "bb_squeeze": true, "bb_just_broke": false, "rng": 0.428, "kimp": null, "liq": [29880.1370142, 22400.7992798, 55], "vwap_broke": false, "spot_fuel": false, "turnover": 87637703, "tradfi": false, "pinned": false, "rank": 16, "since": 1784554221, "since_min": 3}, {"sym": "XAGUSDT", "base": "XAG", "mark": "🟡", "why": "연료 약함 — 관찰", "alpha": 48, "g": [["흡수/이탈", "— 0", 0], ["VWAP", "VWAP 아래 저항 -4", -4], ["MTF", "BTC 동조화 +0", 0], ["오더북", "매수 우위 ×1.35 +4", 4], ["청산", "↑ 숏청산 우위 $44K +5", 5], ["볼밴", "밴드 중단 0", 0], ["스퀴즈", "정상 +0", 0], ["ATR", "극저 변동성 +6", 6], ["레인지", "레인지 상단 +6", 6], ["FLOW", "Flow +1", 1], ["SURGE", "×1.21 +0", 0], ["KIMCHI", "—", 0]], "conflict": [], "onchain": null, "price": 56.85, "p24": 1.5, "oi4": 1.5, "oi1": 0.5, "cvd": 0.595, "fr": 0.0, "atr": 0.69, "flow": 0.5, "surge": 1.21, "ret4": -0.33, "bb_pos": 0.637, "bb_squeeze": false, "bb_just_broke": false, "rng": 0.648, "kimp": null, "liq": [44210.371660000004, 4593.6585, 13], "vwap_broke": true, "spot_fuel": false, "turnover": 645358428, "tradfi": true, "pinned": false, "rank": 17, "since": 1784494938, "since_min": 991}, {"sym": "LINKUSDT", "base": "LINK", "mark": "🟡", "why": "연료 약함 — 관찰", "alpha": 47, "g": [["흡수/이탈", "— 0", 0], ["VWAP", "VWAP 아래 저항 -4", -4], ["MTF", "BTC 동조화 +0", 0], ["오더북", "매수 우위 ×1.19 +4", 4], ["청산", "미미 $24K 0", 0], ["볼밴", "밴드 중단 0", 0], ["스퀴즈", "정상 +0", 0], ["ATR", "극저 변동성 +6", 6], ["레인지", "레인지 상단 +6", 6], ["FLOW", "Flow +5", 5], ["SURGE", "×1.04 +0", 0], ["KIMCHI", "+0.06%", 0]], "conflict": [], "onchain": {"src": "cold", "score": 73, "mark": "🟢", "grade": "강한 펌프 가능성", "cold_score": 73, "cold_usd": 14019354, "cold_n": 7, "cold_wallets": 8, "cold_days": 32.1, "peak": 10.9, "accum_score": null, "accum_usd": null, "accum_wallets": null, "accum_wd": null, "accum_days": null, "conc": false}, "price": 8.442, "p24": 1.28, "oi4": 0.5, "oi1": 0.1, "cvd": 0.391, "fr": 0.0083, "atr": 0.81, "flow": 2.8, "surge": 1.04, "ret4": 0.56, "bb_pos": 0.761, "bb_squeeze": false, "bb_just_broke": false, "rng": 0.663, "kimp": 0.06, "liq": [23763.445150000003, 319.28807, 15], "vwap_broke": true, "spot_fuel": false, "turnover": 69184235, "tradfi": false, "pinned": true, "rank": 18, "since": 1784520138, "since_min": 571}, {"sym": "BTCUSDT", "base": "BTC", "mark": "🟡", "why": "연료 약함 — 관찰", "alpha": 46, "g": [["흡수/이탈", "— 0", 0], ["VWAP", "VWAP 아래 저항 -4", -4], ["MTF", "BTC 동조화 +0", 0], ["오더북", "매도 우위 ×0.78 -4", -4], ["청산", "대형 숏청산 ★ $4940K +8", 8], ["볼밴", "밴드 중단 0", 0], ["스퀴즈", "정상 +0", 0], ["ATR", "극저 변동성 +6", 6], ["레인지", "레인지 상단 +6", 6], ["FLOW", "Flow +4", 4], ["SURGE", "×1.29 +0", 0], ["KIMCHI", "+0.10%", 0]], "conflict": [], "onchain": null, "price": 64524.9, "p24": 0.14, "oi4": -0.2, "oi1": -0.5, "cvd": 0.549, "fr": 0.0087, "atr": 0.67, "flow": 2.3, "surge": 1.29, "ret4": 0.62, "bb_pos": 0.6, "bb_squeeze": false, "bb_just_broke": false, "rng": 0.62, "kimp": 0.1, "liq": [4939915.10007, 131769.8461, 155], "vwap_broke": true, "spot_fuel": false, "turnover": 7627741145, "tradfi": false, "pinned": true, "rank": 19, "since": 1784511858, "since_min": 709}, {"sym": "AKEUSDT", "base": "AKE", "mark": "🟡", "why": "연료 약함 — 관찰", "alpha": 45, "g": [["흡수/이탈", "— 0", 0], ["VWAP", "VWAP 강한 돌파 +10", 10], ["MTF", "BTC 동조화 +0", 0], ["오더북", "매수 우위 ×1.17 +4", 4], ["청산", "미미 $29K 0", 0], ["볼밴", "밴드 중단 0", 0], ["스퀴즈", "정상 +0", 0], ["ATR", "고변동성 -4", -4], ["레인지", "레인지 내 0", 0], ["FLOW", "Flow +5", 5], ["SURGE", "×0.51 +0", 0], ["KIMCHI", "—", 0]], "conflict": [], "onchain": null, "price": 0.0017274, "p24": -11.38, "oi4": 1.9, "oi1": 0.0, "cvd": 0.674, "fr": 0.0461, "atr": 6.77, "flow": 3.0, "surge": 0.51, "ret4": 0.5, "bb_pos": 0.381, "bb_squeeze": false, "bb_just_broke": false, "rng": 0.265, "kimp": null, "liq": [29252.685190700002, 22324.4338847, 105], "vwap_broke": false, "spot_fuel": false, "turnover": 381425255, "tradfi": false, "pinned": false, "rank": 20, "since": 1784554401, "since_min": 0}, {"sym": "SKHYUSDT", "base": "SKHY", "mark": "🟡", "why": "연료 약함 — 관찰", "alpha": 43, "g": [["흡수/이탈", "ACC +14", 14], ["VWAP", "VWAP 아래 저항 -4", -4], ["MTF", "BTC 동조화 +0", 0], ["오더북", "매수 우위 ×1.16 +4", 4], ["청산", "↓ 롱청산 우위 $107K -6", -6], ["볼밴", "밴드 중단 0", 0], ["스퀴즈", "정상 +0", 0], ["ATR", "낮은 변동성 +3", 3], ["레인지", "레인지 상단 +6", 6], ["FLOW", "Flow -8", -8], ["SURGE", "×1.71 +4", 4], ["KIMCHI", "—", 0]], "conflict": [], "onchain": null, "price": 161.38, "p24": 4.05, "oi4": 7.9, "oi1": -0.5, "cvd": 0.418, "fr": 0.0262, "atr": 1.92, "flow": -5.0, "surge": 1.71, "ret4": -0.02, "bb_pos": 0.785, "bb_squeeze": false, "bb_just_broke": false, "rng": 0.731, "kimp": null, "liq": [26895.5495608, 106695.4004461, 21], "vwap_broke": true, "spot_fuel": false, "turnover": 558405999, "tradfi": false, "pinned": false, "rank": 21, "since": 1784554221, "since_min": 3}, {"sym": "XAUUSDT", "base": "XAU", "mark": "🟡", "why": "연료 약함 — 관찰", "alpha": 40, "g": [["흡수/이탈", "— 0", 0], ["VWAP", "VWAP 아래 저항 -4", -4], ["MTF", "BTC 동조화 +0", 0], ["오더북", "매도벽 압박 ×0.29 -8", -8], ["청산", "↑ 숏청산 우위 $174K +5", 5], ["볼밴", "밴드 중단 0", 0], ["스퀴즈", "정상 +0", 0], ["ATR", "극저 변동성 +6", 6], ["레인지", "레인지 내 0", 0], ["FLOW", "Flow +7", 7], ["SURGE", "×1.55 +4", 4], ["KIMCHI", "—", 0]], "conflict": [], "onchain": null, "price": 4019.1, "p24": 0.05, "oi4": 2.4, "oi1": 0.7, "cvd": 0.638, "fr": 0.0, "atr": 0.33, "flow": 4.2, "surge": 1.55, "ret4": -0.18, "bb_pos": 0.518, "bb_squeeze": false, "bb_just_broke": false, "rng": 0.524, "kimp": null, "liq": [173799.55159, 23214.20293, 30], "vwap_broke": true, "spot_fuel": false, "turnover": 1236842880, "tradfi": true, "pinned": false, "rank": 22, "since": 1784487738, "since_min": 1111}, {"sym": "BILLUSDT", "base": "BILL", "mark": "🟡", "why": "연료 약함 — 관찰", "alpha": 39, "g": [["흡수/이탈", "— 0", 0], ["VWAP", "VWAP 아래 저항 -4", -4], ["MTF", "BTC 동조화 +0", 0], ["오더북", "균형 ×1.14 +0", 0], ["청산", "미미 $2K 0", 0], ["볼밴", "밴드압축 7.6% — 대기 +4", 4], ["스퀴즈", "정상 +0", 0], ["ATR", "정상 변동성 +0", 0], ["레인지", "레인지 내 0", 0], ["FLOW", "Flow +9", 9], ["SURGE", "×0.79 +0", 0], ["KIMCHI", "—", 0]], "conflict": [], "onchain": {"src": "cold", "score": 73, "mark": "🟢", "grade": "강한 펌프 가능성", "cold_score": 73, "cold_usd": 33392242, "cold_n": 8, "cold_wallets": 3, "cold_days": 21.7, "peak": 0.2, "accum_score": null, "accum_usd": null, "accum_wallets": null, "accum_wd": null, "accum_days": null, "conc": false}, "price": 0.0246, "p24": -7.31, "oi4": -1.1, "oi1": -0.4, "cvd": 0.528, "fr": -0.0018, "atr": 2.6, "flow": 5.9, "surge": 0.79, "ret4": 0.74, "bb_pos": 0.458, "bb_squeeze": true, "bb_just_broke": false, "rng": 0.319, "kimp": null, "liq": [773.455863, 1872.228751, 8], "vwap_broke": true, "spot_fuel": false, "turnover": 13938779, "tradfi": false, "pinned": true, "rank": 23, "since": 1784512938, "since_min": 691}, {"sym": "1000PEPEUSDT", "base": "PEPE", "mark": "🟡", "why": "연료 약함 — 관찰", "alpha": 34, "g": [["흡수/이탈", "— 0", 0], ["VWAP", "VWAP 아래 저항 -4", -4], ["MTF", "BTC 동조화 +0", 0], ["오더북", "매도벽 압박 ×0.63 -8", -8], ["청산", "↑ 숏청산 우위 $102K +5", 5], ["볼밴", "상단 접근 +6", 6], ["스퀴즈", "정상 +0", 0], ["ATR", "낮은 변동성 +3", 3], ["레인지", "레인지 상단 +6", 6], ["FLOW", "Flow -4", -4], ["SURGE", "×0.84 +0", 0], ["KIMCHI", "-99.90%", 0]], "conflict": [], "onchain": null, "price": 0.0028965, "p24": 1.45, "oi4": 3.7, "oi1": 1.3, "cvd": 0.606, "fr": 0.01, "atr": 1.41, "flow": -2.2, "surge": 0.84, "ret4": 1.6, "bb_pos": 0.824, "bb_squeeze": false, "bb_just_broke": false, "rng": 0.723, "kimp": -99.9, "liq": [101831.2931313, 23095.0792173, 33], "vwap_broke": true, "spot_fuel": false, "turnover": 173639558, "tradfi": false, "pinned": false, "rank": 24, "since": 1784517618, "since_min": 613}, {"sym": "SPCXUSDT", "base": "SPCX", "mark": "🟡", "why": "연료 약함 — 관찰", "alpha": 32, "g": [["흡수/이탈", "— 0", 0], ["VWAP", "VWAP 아래 저항 -4", -4], ["MTF", "BTC 동조화 +0", 0], ["오더북", "매도 우위 ×0.83 -4", -4], ["청산", "↓ 롱청산 우위 $148K -6", -6], ["볼밴", "밴드압축 3.5% — 대기 +4", 4], ["스퀴즈", "정상 +0", 0], ["ATR", "낮은 변동성 +3", 3], ["레인지", "레인지 내 0", 0], ["FLOW", "Flow -9", -9], ["SURGE", "×4.07 +18", 18], ["KIMCHI", "—", 0]], "conflict": [], "onchain": null, "price": 124.47, "p24": -2.51, "oi4": 1.8, "oi1": 1.1, "cvd": 0.078, "fr": 0.0299, "atr": 1.03, "flow": -5.4, "surge": 4.07, "ret4": -1.07, "bb_pos": 0.143, "bb_squeeze": true, "bb_just_broke": false, "rng": 0.243, "kimp": null, "liq": [839.5689000000001, 147895.1216287, 46], "vwap_broke": true, "spot_fuel": false, "turnover": 268413557, "tradfi": true, "pinned": false, "rank": 25, "since": 1784405118, "since_min": 2488}, {"sym": "BANKUSDT", "base": "BANK", "mark": "🟡", "why": "연료 약함 — 관찰", "alpha": 31, "g": [["흡수/이탈", "— 0", 0], ["VWAP", "VWAP 아래 저항 -4", -4], ["MTF", "BTC 동조화 +0", 0], ["오더북", "매도벽 압박 ×0.41 -8", -8], ["청산", "↑ 숏청산 우위 $733K +5", 5], ["볼밴", "밴드압축 38.6% — 대기 +4", 4], ["스퀴즈", "정상 +0", 0], ["ATR", "고변동성 -4", -4], ["레인지", "레인지 상단 +6", 6], ["FLOW", "Flow +2", 2], ["SURGE", "×0.92 +0", 0], ["KIMCHI", "—", 0]], "conflict": [], "onchain": null, "price": 0.27136, "p24": 51.49, "oi4": 2.3, "oi1": 1.4, "cvd": 0.532, "fr": 0.005, "atr": 7.98, "flow": 1.2, "surge": 0.92, "ret4": -3.07, "bb_pos": 0.743, "bb_squeeze": true, "bb_just_broke": false, "rng": 0.819, "kimp": null, "liq": [733365.1488281, 392221.0463727, 911], "vwap_broke": true, "spot_fuel": false, "turnover": 1800943328, "tradfi": false, "pinned": false, "rank": 26, "since": 1784552601, "since_min": 30}, {"sym": "CLUSDT", "base": "CL", "mark": "🟡", "why": "연료 약함 — 관찰", "alpha": 25, "g": [["흡수/이탈", "— 0", 0], ["VWAP", "VWAP 위 지지 +4", 4], ["MTF", "BTC 동조화 +0", 0], ["오더북", "균형 ×0.99 +0", 0], ["청산", "↓ 롱청산 우위 $972K -6", -6], ["볼밴", "밴드 하단 -3", -3], ["스퀴즈", "정상 +0", 0], ["ATR", "낮은 변동성 +3", 3], ["레인지", "레인지 내 0", 0], ["FLOW", "Flow -11", -11], ["SURGE", "×2.80 +8", 8], ["KIMCHI", "—", 0]], "conflict": [], "onchain": null, "price": 81.39, "p24": -2.86, "oi4": 3.2, "oi1": 3.3, "cvd": 0.513, "fr": -0.0063, "atr": 1.69, "flow": -6.7, "surge": 2.8, "ret4": 0.26, "bb_pos": 0.161, "bb_squeeze": false, "bb_just_broke": false, "rng": 0.355, "kimp": null, "liq": [187446.53762030002, 972480.1227366, 61], "vwap_broke": false, "spot_fuel": false, "turnover": 755161718, "tradfi": false, "pinned": false, "rank": 27, "since": 1784162671, "since_min": 6528}, {"sym": "AVAXUSDT", "base": "AVAX", "mark": "🟡", "why": "연료 약함 — 관찰", "alpha": 24, "g": [["흡수/이탈", "— 0", 0], ["VWAP", "VWAP 아래 저항 -4", -4], ["MTF", "BTC 동조화 +0", 0], ["오더북", "매도벽 압박 ×0.64 -8", -8], ["청산", "미미 $4K 0", 0], ["볼밴", "밴드 중단 0", 0], ["스퀴즈", "정상 +0", 0], ["ATR", "극저 변동성 +6", 6], ["레인지", "레인지 상단 +6", 6], ["FLOW", "Flow -6", -6], ["SURGE", "×0.80 +0", 0], ["KIMCHI", "-0.04%", 0]], "conflict": [], "onchain": null, "price": 6.576, "p24": 2.14, "oi4": 2.7, "oi1": 0.7, "cvd": 0.444, "fr": 0.008, "atr": 0.86, "flow": -3.5, "surge": 0.8, "ret4": 0.37, "bb_pos": 0.759, "bb_squeeze": false, "bb_just_broke": false, "rng": 0.725, "kimp": -0.04, "liq": [3881.4959999999996, 0, 3], "vwap_broke": true, "spot_fuel": false, "turnover": 74362699, "tradfi": false, "pinned": false, "rank": 28, "since": 1784523773, "since_min": 510}, {"sym": "SOXSUSDT", "base": "SOXS", "mark": "🟡", "why": "연료 약함 — 관찰", "alpha": 17, "g": [["흡수/이탈", "— 0", 0], ["VWAP", "VWAP 아래 저항 -4", -4], ["MTF", "BTC 대비 약세 -6", -6], ["오더북", "균형 ×1.03 +0", 0], ["청산", "미미 $9K 0", 0], ["볼밴", "밴드 하단 -3", -3], ["스퀴즈", "정상 +0", 0], ["ATR", "정상 변동성 +0", 0], ["레인지", "저점 근접 -6", -6], ["FLOW", "Flow -2", -2], ["SURGE", "×2.09 +8", 8], ["KIMCHI", "—", 0]], "conflict": [], "onchain": null, "price": 50.39, "p24": -8.78, "oi4": 3.5, "oi1": 7.8, "cvd": 0.312, "fr": 0.0, "atr": 2.92, "flow": -1.5, "surge": 2.09, "ret4": -3.69, "bb_pos": 0.063, "bb_squeeze": false, "bb_just_broke": false, "rng": 0.083, "kimp": null, "liq": [0, 8754.4083271, 6], "vwap_broke": true, "spot_fuel": false, "turnover": 15526695, "tradfi": true, "pinned": false, "rank": 29, "since": 1784554401, "since_min": 0}, {"sym": "BABAUSDT", "base": "BABA", "mark": "🟡", "why": "연료 약함 — 관찰", "alpha": 17, "g": [["흡수/이탈", "— 0", 0], ["VWAP", "VWAP 아래 저항 -4", -4], ["MTF", "BTC 동조화 +0", 0], ["오더북", "균형 ×1.11 +0", 0], ["청산", "미미 $0K 0", 0], ["볼밴", "밴드압축 4.4% — 대기 +4", 4], ["스퀴즈", "정상 +0", 0], ["ATR", "극저 변동성 +6", 6], ["레인지", "레인지 내 0", 0], ["FLOW", "Flow -19", -19], ["SURGE", "×1.12 +0", 0], ["KIMCHI", "—", 0]], "conflict": [], "onchain": null, "price": 118.7, "p24": -0.05, "oi4": 2.3, "oi1": 3.8, "cvd": 0.0, "fr": 0.0497, "atr": 0.79, "flow": -11.8, "surge": 1.12, "ret4": -0.64, "bb_pos": 0.275, "bb_squeeze": true, "bb_just_broke": false, "rng": 0.287, "kimp": null, "liq": [205.9451976, 0, 1], "vwap_broke": true, "spot_fuel": false, "turnover": 30891352, "tradfi": true, "pinned": false, "rank": 30, "since": 1784516178, "since_min": 637}, {"sym": "REUSDT", "base": "RE", "mark": "🟡", "why": "연료 약함 — 관찰", "alpha": 12, "g": [["흡수/이탈", "— 0", 0], ["VWAP", "VWAP 아래 저항 -4", -4], ["MTF", "BTC 대비 약세 -6", -6], ["오더북", "균형 ×1.13 +0", 0], ["청산", "미미 $28K 0", 0], ["볼밴", "밴드 하단 -3", -3], ["스퀴즈", "대형 FR스퀴즈 ★ +8", 8], ["ATR", "정상 변동성 +0", 0], ["레인지", "저점 근접 -6", -6], ["FLOW", "Flow -11", -11], ["SURGE", "×1.74 +4", 4], ["KIMCHI", "+0.53%", 0]], "conflict": [], "onchain": null, "price": 0.3632, "p24": -7.35, "oi4": 4.0, "oi1": 1.2, "cvd": 0.253, "fr": -0.1275, "atr": 2.67, "flow": -7.1, "surge": 1.74, "ret4": -3.77, "bb_pos": -0.013, "bb_squeeze": false, "bb_just_broke": false, "rng": 0.043, "kimp": 0.53, "liq": [2480.6378872, 27926.2398654, 35], "vwap_broke": true, "spot_fuel": false, "turnover": 26408261, "tradfi": false, "pinned": false, "rank": 31, "since": 1784538741, "since_min": 261}, {"sym": "AVAAIUSDT", "base": "AVAAI", "mark": "🟡", "why": "연료 약함 — 관찰", "alpha": 0, "g": [["흡수/이탈", "— 0", 0], ["VWAP", "VWAP 아래 저항 -4", -4], ["MTF", "BTC 대비 약세 -6", -6], ["오더북", "균형 ×0.95 +0", 0], ["청산", "↓ 롱청산 우위 $82K -6", -6], ["볼밴", "밴드 하단 -3", -3], ["스퀴즈", "정상 +0", 0], ["ATR", "고변동성 -4", -4], ["레인지", "저점 근접 -6", -6], ["FLOW", "Flow -13", -13], ["SURGE", "×0.93 +0", 0], ["KIMCHI", "—", 0]], "conflict": [], "onchain": null, "price": 0.008539, "p24": 0.25, "oi4": 3.9, "oi1": -0.2, "cvd": 0.377, "fr": 0.005, "atr": 9.98, "flow": -8.1, "surge": 0.93, "ret4": -17.83, "bb_pos": -0.111, "bb_squeeze": false, "bb_just_broke": false, "rng": 0.03, "kimp": null, "liq": [2265.8511879, 82409.7850809, 138], "vwap_broke": true, "spot_fuel": false, "turnover": 66266594, "tradfi": false, "pinned": false, "rank": 32, "since": 1784552781, "since_min": 27}, {"sym": "ARIAUSDT", "base": "ARIA", "mark": "🔴", "why": "하락 중 -16% — 롱 근거 없음", "alpha": 68, "g": [["흡수/이탈", "— 0", 0], ["VWAP", "VWAP 강한 돌파 +10", 10], ["MTF", "BTC 대비 강세 +6", 6], ["오더북", "균형 ×0.97 +0", 0], ["청산", "미미 $1K 0", 0], ["볼밴", "밴드압축 10.3% — 대기 +4", 4], ["스퀴즈", "정상 +0", 0], ["ATR", "정상 변동성 +0", 0], ["레인지", "레인지 내 0", 0], ["FLOW", "Flow +18", 18], ["SURGE", "×0.87 +0", 0], ["KIMCHI", "—", 0]], "conflict": [], "onchain": null, "price": 0.02594, "p24": -16.4, "oi4": 1.9, "oi1": -0.7, "cvd": 1.0, "fr": 0.005, "atr": 2.67, "flow": 11.0, "surge": 0.87, "ret4": 4.66, "bb_pos": 0.71, "bb_squeeze": true, "bb_just_broke": false, "rng": 0.174, "kimp": null, "liq": [91.98285, 529.6511763999999, 8], "vwap_broke": false, "spot_fuel": false, "turnover": 16939204, "tradfi": false, "pinned": false, "rank": 33, "since": 1784552061, "since_min": 39}, {"sym": "ACEUSDT", "base": "ACE", "mark": "🔴", "why": "수직급등 +85% — 과열 추격금지", "alpha": 20, "g": [["흡수/이탈", "— 0", 0], ["VWAP", "VWAP 아래 저항 -4", -4], ["MTF", "BTC 대비 약세 -6", -6], ["오더북", "매도벽 압박 ×0.59 -8", -8], ["청산", "혼조 0", 0], ["볼밴", "밴드 중단 0", 0], ["스퀴즈", "대형 FR스퀴즈 ★ +8", 8], ["ATR", "고변동성 -4", -4], ["레인지", "레인지 상단 +6", 6], ["FLOW", "Flow -2", -2], ["SURGE", "×1.25 +0", 0], ["KIMCHI", "—", 0]], "conflict": [], "onchain": null, "price": 0.12048, "p24": 85.41, "oi4": 12.1, "oi1": 3.5, "cvd": 0.241, "fr": -0.4423, "atr": 12.19, "flow": -1.2, "surge": 1.25, "ret4": -15.43, "bb_pos": 0.634, "bb_squeeze": false, "bb_just_broke": false, "rng": 0.623, "kimp": null, "liq": [153264.18145768, 225090.63424355, 424], "vwap_broke": true, "spot_fuel": false, "turnover": 355003987, "tradfi": false, "pinned": false, "rank": 34, "since": 1784528662, "since_min": 428}, {"sym": "ESPORTSUSDT", "base": "ESPORTS", "mark": "🔴", "why": "하락 중 -43% — 롱 근거 없음", "alpha": 6, "g": [["흡수/이탈", "— 0", 0], ["VWAP", "VWAP 아래 저항 -4", -4], ["MTF", "BTC 동조화 +0", 0], ["오더북", "매수 우위 ×1.18 +4", 4], ["청산", "↓ 롱청산 우위 $72K -6", -6], ["볼밴", "밴드 하단 -3", -3], ["스퀴즈", "정상 +0", 0], ["ATR", "정상 변동성 +0", 0], ["레인지", "저점 근접 -6", -6], ["FLOW", "Flow -9", -9], ["SURGE", "×0.47 +0", 0], ["KIMCHI", "—", 0]], "conflict": [], "onchain": null, "price": 0.01883, "p24": -43.35, "oi4": 4.6, "oi1": 1.1, "cvd": 0.296, "fr": 0.0408, "atr": 5.82, "flow": -5.8, "surge": 0.47, "ret4": -1.05, "bb_pos": 0.105, "bb_squeeze": false, "bb_just_broke": false, "rng": 0.065, "kimp": null, "liq": [204.30146, 72353.9829807, 87], "vwap_broke": true, "spot_fuel": false, "turnover": 253040383, "tradfi": false, "pinned": false, "rank": 35, "since": 1784481799, "since_min": 1210}]}