{"updated": "2026-07-21 00:03:21", "updated_ts": 1784559801, "scan_sec": 180, "us_open": true, "ws": true, "liq_events": 12838, "count": 35, "cols": ["흡수/이탈", "VWAP", "MTF", "오더북", "청산", "볼밴", "스퀴즈", "ATR", "레인지", "FLOW", "SURGE", "KIMCHI"], "rows": [{"sym": "VIRTUALUSDT", "base": "VIRTUAL", "mark": "🟢", "why": "초입(+7%) + 연료 — 진입검토", "alpha": 78, "g": [["흡수/이탈", "ACC +14", 14], ["VWAP", "VWAP 강한 돌파 +10", 10], ["MTF", "BTC 대비 강세 +6", 6], ["오더북", "매도벽 압박 ×0.35 -8", -8], ["청산", "미미 $5K 0", 0], ["볼밴", "밴드 밖 진행중 — 이미 감 0", 0], ["스퀴즈", "정상 +0", 0], ["ATR", "정상 변동성 +0", 0], ["레인지", "고점 돌파 +4", 4], ["FLOW", "Flow +4", 4], ["SURGE", "×3.45 +18", 18], ["KIMCHI", "+0.39%", 0]], "conflict": ["볼밴 이미 감", "레인지 고점", "매도벽"], "onchain": null, "price": 0.6516, "p24": 7.17, "oi4": 9.7, "oi1": 3.4, "cvd": 0.92, "fr": 0.005, "atr": 2.6, "flow": 2.7, "surge": 3.45, "ret4": 4.83, "bb_pos": 1.195, "bb_squeeze": false, "bb_just_broke": false, "rng": 1.0, "kimp": 0.39, "liq": [1145.57166, 4617.81948076, 13], "vwap_broke": false, "spot_fuel": false, "turnover": 22335327, "tradfi": false, "pinned": false, "rank": 1, "since": 1784556201, "since_min": 59}, {"sym": "ZAMAUSDT", "base": "ZAMA", "mark": "🟢", "why": "연료생존 — 진입검토", "alpha": 77, "g": [["흡수/이탈", "ACC +14", 14], ["VWAP", "VWAP 위 지지 +4", 4], ["MTF", "BTC 대비 강세 +6", 6], ["오더북", "매도 우위 ×0.79 -4", -4], ["청산", "↑ 숏청산 우위 $36K +5", 5], ["볼밴", "상단 접근 +6", 6], ["스퀴즈", "정상 +0", 0], ["ATR", "정상 변동성 +0", 0], ["레인지", "레인지 상단 +6", 6], ["FLOW", "Flow -8", -8], ["SURGE", "×3.05 +18", 18], ["KIMCHI", "+0.48%", 0]], "conflict": ["매도벽"], "onchain": null, "price": 0.03985, "p24": 12.47, "oi4": 7.8, "oi1": 3.8, "cvd": 0.61, "fr": -0.006, "atr": 3.26, "flow": -5.1, "surge": 3.05, "ret4": 1.53, "bb_pos": 0.902, "bb_squeeze": false, "bb_just_broke": false, "rng": 0.783, "kimp": 0.48, "liq": [36363.6967188, 16918.5636403, 52], "vwap_broke": false, "spot_fuel": false, "turnover": 19177358, "tradfi": false, "pinned": false, "rank": 2, "since": 1784556201, "since_min": 59}, {"sym": "MUUUSDT", "base": "MUU", "mark": "🟢", "why": "초입(+6%) + 연료 — 진입검토", "alpha": 59, "g": [["흡수/이탈", "ACC +28", 28], ["VWAP", "VWAP 아래 저항 -4", -4], ["MTF", "BTC 동조화 +0", 0], ["오더북", "매도벽 압박 ×0.56 -8", -8], ["청산", "미미 $7K 0", 0], ["볼밴", "밴드 중단 0", 0], ["스퀴즈", "정상 +0", 0], ["ATR", "정상 변동성 +0", 0], ["레인지", "레인지 내 0", 0], ["FLOW", "Flow -5", -5], ["SURGE", "×3.54 +18", 18], ["KIMCHI", "—", 0]], "conflict": ["VWAP 아래", "매도벽"], "onchain": null, "price": 28.79, "p24": 5.54, "oi4": 19.2, "oi1": 5.2, "cvd": 0.575, "fr": 0.0, "atr": 3.69, "flow": -3.1, "surge": 3.54, "ret4": -4.46, "bb_pos": 0.638, "bb_squeeze": false, "bb_just_broke": false, "rng": 0.538, "kimp": null, "liq": [0, 7173.540134100001, 4], "vwap_broke": true, "spot_fuel": false, "turnover": 17248296, "tradfi": false, "pinned": false, "rank": 3, "since": 1784559621, "since_min": 2}, {"sym": "HEMIUSDT", "base": "HEMI", "mark": "🟢", "why": "연료생존 — 진입검토", "alpha": 59, "g": [["흡수/이탈", "— 0", 0], ["VWAP", "VWAP 강한 돌파 +10", 10], ["MTF", "BTC 대비 초강세 +12", 12], ["오더북", "균형 ×0.89 +0", 0], ["청산", "미미 $4K 0", 0], ["볼밴", "상단 접근 +6", 6], ["스퀴즈", "FR스퀴즈 중 +5", 5], ["ATR", "정상 변동성 +0", 0], ["레인지", "레인지 상단 +6", 6], ["FLOW", "Flow -10", -10], ["SURGE", "×1.35 +0", 0], ["KIMCHI", "—", 0]], "conflict": ["이미 +21%"], "onchain": null, "price": 0.005491, "p24": 20.68, "oi4": 5.6, "oi1": 1.4, "cvd": 0.975, "fr": -0.0189, "atr": 5.82, "flow": -5.9, "surge": 1.35, "ret4": 7.88, "bb_pos": 0.962, "bb_squeeze": false, "bb_just_broke": false, "rng": 0.846, "kimp": null, "liq": [4261.5224177, 3632.0545198, 29], "vwap_broke": false, "spot_fuel": false, "turnover": 16171181, "tradfi": false, "pinned": false, "rank": 4, "since": 1784556201, "since_min": 59}, {"sym": "CLUSDT", "base": "CL", "mark": "🟢", "why": "초입(-3%) + 연료 — 진입검토", "alpha": 55, "g": [["흡수/이탈", "ACC +14", 14], ["VWAP", "VWAP 위 지지 +4", 4], ["MTF", "BTC 대비 강세 +6", 6], ["오더북", "균형 ×0.95 +0", 0], ["청산", "↓ 롱청산 우위 $977K -6", -6], ["볼밴", "밴드 중단 0", 0], ["스퀴즈", "정상 +0", 0], ["ATR", "낮은 변동성 +3", 3], ["레인지", "레인지 내 0", 0], ["FLOW", "Flow +4", 4], ["SURGE", "×1.13 +0", 0], ["KIMCHI", "—", 0]], "conflict": [], "onchain": null, "price": 81.67, "p24": -2.58, "oi4": 7.2, "oi1": -0.1, "cvd": 0.753, "fr": -0.0036, "atr": 1.19, "flow": 2.6, "surge": 1.13, "ret4": 1.72, "bb_pos": 0.261, "bb_squeeze": false, "bb_just_broke": false, "rng": 0.414, "kimp": null, "liq": [273738.0799307, 976557.5185366, 63], "vwap_broke": false, "spot_fuel": false, "turnover": 805797682, "tradfi": false, "pinned": false, "rank": 5, "since": 1784559621, "since_min": 2}, {"sym": "COINUSDT", "base": "COIN", "mark": "🟡", "why": "연료 약함 — 관찰", "alpha": 86, "g": [["흡수/이탈", "ACC +14", 14], ["VWAP", "VWAP 강한 돌파 +10", 10], ["MTF", "BTC 동조화 +0", 0], ["오더북", "매수벽 우위 ×9.11 +8", 8], ["청산", "청산 데이터 없음 0", 0], ["볼밴", "밴드 중단 0", 0], ["스퀴즈", "정상 +0", 0], ["ATR", "낮은 변동성 +3", 3], ["레인지", "레인지 상단 +6", 6], ["FLOW", "Flow -3", -3], ["SURGE", "×5.54 +18", 18], ["KIMCHI", "—", 0]], "conflict": [], "onchain": null, "price": 158.62, "p24": 0.03, "oi4": 9.2, "oi1": -0.4, "cvd": 0.312, "fr": 0.008, "atr": 1.37, "flow": -1.9, "surge": 5.54, "ret4": -0.66, "bb_pos": 0.678, "bb_squeeze": false, "bb_just_broke": false, "rng": 0.717, "kimp": null, "liq": null, "vwap_broke": false, "spot_fuel": false, "turnover": 16630121, "tradfi": true, "pinned": false, "rank": 6, "since": 1784555841, "since_min": 65}, {"sym": "NVDAUSDT", "base": "NVDA", "mark": "🟡", "why": "연료 약함 — 관찰", "alpha": 67, "g": [["흡수/이탈", "— 0", 0], ["VWAP", "VWAP 아래 저항 -4", -4], ["MTF", "BTC 동조화 +0", 0], ["오더북", "균형 ×0.90 +0", 0], ["청산", "미미 $1K 0", 0], ["볼밴", "상단 접근 +6", 6], ["스퀴즈", "정상 +0", 0], ["ATR", "극저 변동성 +6", 6], ["레인지", "레인지 상단 +6", 6], ["FLOW", "Flow +5", 5], ["SURGE", "×6.07 +18", 18], ["KIMCHI", "—", 0]], "conflict": [], "onchain": null, "price": 205.59, "p24": 1.23, "oi4": 2.6, "oi1": 0.7, "cvd": 0.141, "fr": 0.0, "atr": 0.84, "flow": 3.1, "surge": 6.07, "ret4": -0.09, "bb_pos": 0.873, "bb_squeeze": false, "bb_just_broke": false, "rng": 0.615, "kimp": null, "liq": [1270.1753999999999, 869.5962, 3], "vwap_broke": true, "spot_fuel": false, "turnover": 62467285, "tradfi": true, "pinned": false, "rank": 7, "since": 1784433738, "since_min": 2101}, {"sym": "MRVLUSDT", "base": "MRVL", "mark": "🟡", "why": "연료 약함 — 관찰", "alpha": 63, "g": [["흡수/이탈", "— 0", 0], ["VWAP", "VWAP 위 지지 +4", 4], ["MTF", "BTC 동조화 +0", 0], ["오더북", "매도 우위 ×0.78 -4", -4], ["청산", "미미 $4K 0", 0], ["볼밴", "상단 접근 +6", 6], ["스퀴즈", "정상 +0", 0], ["ATR", "낮은 변동성 +3", 3], ["레인지", "레인지 상단 +6", 6], ["FLOW", "Flow +0", 0], ["SURGE", "×6.97 +18", 18], ["KIMCHI", "—", 0]], "conflict": [], "onchain": null, "price": 196.21, "p24": 3.92, "oi4": 3.1, "oi1": 1.6, "cvd": 0.426, "fr": 0.0, "atr": 1.98, "flow": 0.3, "surge": 6.97, "ret4": 0.5, "bb_pos": 0.991, "bb_squeeze": false, "bb_just_broke": false, "rng": 0.781, "kimp": null, "liq": [3594.7153859, 1058.81768, 5], "vwap_broke": false, "spot_fuel": false, "turnover": 102819020, "tradfi": true, "pinned": false, "rank": 8, "since": 1784419338, "since_min": 2341}, {"sym": "AMDUSDT", "base": "AMD", "mark": "🟡", "why": "연료 약함 — 관찰", "alpha": 58, "g": [["흡수/이탈", "ACC +14", 14], ["VWAP", "VWAP 아래 저항 -4", -4], ["MTF", "BTC 동조화 +0", 0], ["오더북", "매도벽 압박 ×0.37 -8", -8], ["청산", "미미 $5K 0", 0], ["볼밴", "밴드 중단 0", 0], ["스퀴즈", "정상 +0", 0], ["ATR", "정상 변동성 +0", 0], ["레인지", "레인지 내 0", 0], ["FLOW", "Flow +8", 8], ["SURGE", "×4.94 +18", 18], ["KIMCHI", "—", 0]], "conflict": [], "onchain": null, "price": 509.95, "p24": 4.13, "oi4": 6.5, "oi1": 0.8, "cvd": 0.007, "fr": 0.0, "atr": 2.16, "flow": 5.0, "surge": 4.94, "ret4": -0.71, "bb_pos": 0.797, "bb_squeeze": false, "bb_just_broke": false, "rng": 0.493, "kimp": null, "liq": [5004.0930419, 329.4448, 4], "vwap_broke": true, "spot_fuel": false, "turnover": 44938486, "tradfi": true, "pinned": false, "rank": 9, "since": 1784556201, "since_min": 59}, {"sym": "TSLAUSDT", "base": "TSLA", "mark": "🟡", "why": "연료 약함 — 관찰", "alpha": 55, "g": [["흡수/이탈", "ACC +14", 14], ["VWAP", "VWAP 아래 저항 -4", -4], ["MTF", "BTC 동조화 +0", 0], ["오더북", "균형 ×0.94 +0", 0], ["청산", "미미 $7K 0", 0], ["볼밴", "밴드 하단 -3", -3], ["스퀴즈", "정상 +0", 0], ["ATR", "낮은 변동성 +3", 3], ["레인지", "저점 근접 -6", -6], ["FLOW", "Flow +3", 3], ["SURGE", "×7.93 +18", 18], ["KIMCHI", "—", 0]], "conflict": [], "onchain": null, "price": 374.48, "p24": -2.05, "oi4": 5.6, "oi1": 1.6, "cvd": 0.015, "fr": 0.0, "atr": 1.2, "flow": 1.6, "surge": 7.93, "ret4": -2.92, "bb_pos": -0.046, "bb_squeeze": false, "bb_just_broke": false, "rng": 0.092, "kimp": null, "liq": [0, 7013.087214499999, 5], "vwap_broke": true, "spot_fuel": false, "turnover": 30656542, "tradfi": true, "pinned": false, "rank": 10, "since": 1784556201, "since_min": 59}, {"sym": "PENGUUSDT", "base": "PENGU", "mark": "🟡", "why": "연료 약함 — 관찰", "alpha": 55, "g": [["흡수/이탈", "— 0", 0], ["VWAP", "VWAP 위 지지 +4", 4], ["MTF", "BTC 동조화 +0", 0], ["오더북", "균형 ×1.05 +0", 0], ["청산", "미미 $17K 0", 0], ["볼밴", "상단 접근 +6", 6], ["스퀴즈", "정상 +0", 0], ["ATR", "낮은 변동성 +3", 3], ["레인지", "레인지 상단 +6", 6], ["FLOW", "Flow +6", 6], ["SURGE", "×0.87 +0", 0], ["KIMCHI", "-0.01%", 0]], "conflict": [], "onchain": null, "price": 0.006276, "p24": 2.48, "oi4": 2.0, "oi1": 0.8, "cvd": 0.44, "fr": 0.0047, "atr": 1.46, "flow": 3.9, "surge": 0.87, "ret4": -0.08, "bb_pos": 0.877, "bb_squeeze": false, "bb_just_broke": false, "rng": 0.859, "kimp": -0.01, "liq": [16686.0090875, 705.862792, 10], "vwap_broke": false, "spot_fuel": false, "turnover": 38361521, "tradfi": false, "pinned": false, "rank": 11, "since": 1784516538, "since_min": 721}, {"sym": "SPCXUSDT", "base": "SPCX", "mark": "🟡", "why": "연료 약함 — 관찰", "alpha": 53, "g": [["흡수/이탈", "ACC +28", 28], ["VWAP", "VWAP 아래 저항 -4", -4], ["MTF", "BTC 동조화 +0", 0], ["오더북", "매도벽 압박 ×0.65 -8", -8], ["청산", "↓ 롱청산 우위 $1206K -6", -6], ["볼밴", "밴드 하단 -3", -3], ["스퀴즈", "정상 +0", 0], ["ATR", "낮은 변동성 +3", 3], ["레인지", "레인지 내 0", 0], ["FLOW", "Flow -5", -5], ["SURGE", "×7.88 +18", 18], ["KIMCHI", "—", 0]], "conflict": [], "onchain": null, "price": 122.13, "p24": -4.33, "oi4": 13.8, "oi1": 3.3, "cvd": 0.369, "fr": 0.0047, "atr": 1.94, "flow": -2.9, "surge": 7.88, "ret4": -2.94, "bb_pos": 0.051, "bb_squeeze": false, "bb_just_broke": false, "rng": 0.248, "kimp": null, "liq": [40046.7405068, 1206437.3314463, 172], "vwap_broke": true, "spot_fuel": false, "turnover": 499114029, "tradfi": true, "pinned": false, "rank": 12, "since": 1784405118, "since_min": 2578}, {"sym": "ETHUSDT", "base": "ETH", "mark": "🟡", "why": "연료 약함 — 관찰", "alpha": 50, "g": [["흡수/이탈", "— 0", 0], ["VWAP", "VWAP 위 지지 +4", 4], ["MTF", "BTC 동조화 +0", 0], ["오더북", "매수벽 우위 ×6.54 +8", 8], ["청산", "↑ 숏청산 우위 $4314K +5", 5], ["볼밴", "밴드 중단 0", 0], ["스퀴즈", "정상 +0", 0], ["ATR", "극저 변동성 +6", 6], ["레인지", "레인지 상단 +6", 6], ["FLOW", "Flow -9", -9], ["SURGE", "×1.09 +0", 0], ["KIMCHI", "+0.22%", 0]], "conflict": [], "onchain": null, "price": 1871.11, "p24": -0.17, "oi4": -1.0, "oi1": 0.2, "cvd": 0.28, "fr": 0.0006, "atr": 0.97, "flow": -5.9, "surge": 1.09, "ret4": -0.93, "bb_pos": 0.687, "bb_squeeze": false, "bb_just_broke": false, "rng": 0.607, "kimp": 0.22, "liq": [4313883.03258, 2439926.02315, 288], "vwap_broke": false, "spot_fuel": false, "turnover": 7601780776, "tradfi": false, "pinned": true, "rank": 13, "since": 1784408538, "since_min": 2521}, {"sym": "BTCUSDT", "base": "BTC", "mark": "🟡", "why": "연료 약함 — 관찰", "alpha": 47, "g": [["흡수/이탈", "— 0", 0], ["VWAP", "VWAP 위 지지 +4", 4], ["MTF", "BTC 동조화 +0", 0], ["오더북", "매도 우위 ×0.84 -4", -4], ["청산", "대형 숏청산 ★ $5335K +8", 8], ["볼밴", "밴드 중단 0", 0], ["스퀴즈", "정상 +0", 0], ["ATR", "극저 변동성 +6", 6], ["레인지", "레인지 상단 +6", 6], ["FLOW", "Flow -3", -3], ["SURGE", "×1.01 +0", 0], ["KIMCHI", "+0.13%", 0]], "conflict": [], "onchain": null, "price": 64517.6, "p24": -0.08, "oi4": -0.3, "oi1": 0.1, "cvd": 0.288, "fr": 0.0066, "atr": 0.66, "flow": -2.0, "surge": 1.01, "ret4": -0.61, "bb_pos": 0.606, "bb_squeeze": false, "bb_just_broke": false, "rng": 0.62, "kimp": 0.13, "liq": [5334882.93653, 1245713.57634, 241], "vwap_broke": false, "spot_fuel": false, "turnover": 8338456860, "tradfi": false, "pinned": true, "rank": 14, "since": 1784511858, "since_min": 799}, {"sym": "XAGUSDT", "base": "XAG", "mark": "🟡", "why": "연료 약함 — 관찰", "alpha": 45, "g": [["흡수/이탈", "— 0", 0], ["VWAP", "VWAP 위 지지 +4", 4], ["MTF", "BTC 동조화 +0", 0], ["오더북", "균형 ×0.95 +0", 0], ["청산", "혼조 0", 0], ["볼밴", "밴드압축 3.3% — 대기 +4", 4], ["스퀴즈", "정상 +0", 0], ["ATR", "극저 변동성 +6", 6], ["레인지", "레인지 상단 +6", 6], ["FLOW", "Flow -5", -5], ["SURGE", "×1.20 +0", 0], ["KIMCHI", "—", 0]], "conflict": [], "onchain": null, "price": 56.95, "p24": 1.73, "oi4": 2.4, "oi1": 0.3, "cvd": 0.382, "fr": 0.0, "atr": 0.74, "flow": -3.0, "surge": 1.2, "ret4": -0.35, "bb_pos": 0.647, "bb_squeeze": true, "bb_just_broke": false, "rng": 0.694, "kimp": null, "liq": [40459.15168, 34007.84698, 26], "vwap_broke": false, "spot_fuel": false, "turnover": 709683450, "tradfi": true, "pinned": false, "rank": 15, "since": 1784494938, "since_min": 1081}, {"sym": "BILLUSDT", "base": "BILL", "mark": "🟡", "why": "연료 약함 — 관찰", "alpha": 45, "g": [["흡수/이탈", "— 0", 0], ["VWAP", "VWAP 위 지지 +4", 4], ["MTF", "BTC 동조화 +0", 0], ["오더북", "균형 ×1.04 +0", 0], ["청산", "미미 $1K 0", 0], ["볼밴", "밴드압축 6.1% — 대기 +4", 4], ["스퀴즈", "정상 +0", 0], ["ATR", "낮은 변동성 +3", 3], ["레인지", "레인지 내 0", 0], ["FLOW", "Flow +4", 4], ["SURGE", "×0.57 +0", 0], ["KIMCHI", "—", 0]], "conflict": [], "onchain": {"src": "cold", "score": 73, "mark": "🟢", "grade": "강한 펌프 가능성", "cold_score": 73, "cold_usd": 33392242, "cold_n": 8, "cold_wallets": 3, "cold_days": 21.8, "peak": 0.2, "accum_score": null, "accum_usd": null, "accum_wallets": null, "accum_wd": null, "accum_days": null, "conc": false}, "price": 0.02472, "p24": -7.38, "oi4": -0.9, "oi1": -0.5, "cvd": 0.714, "fr": -0.0034, "atr": 1.82, "flow": 2.7, "surge": 0.57, "ret4": 1.06, "bb_pos": 0.583, "bb_squeeze": true, "bb_just_broke": false, "rng": 0.406, "kimp": null, "liq": [189.37329259999998, 589.813251, 4], "vwap_broke": false, "spot_fuel": false, "turnover": 13282384, "tradfi": false, "pinned": true, "rank": 16, "since": 1784512938, "since_min": 781}, {"sym": "PAXGUSDT", "base": "PAXG", "mark": "🟡", "why": "연료 약함 — 관찰", "alpha": 41, "g": [["흡수/이탈", "— 0", 0], ["VWAP", "VWAP 위 지지 +4", 4], ["MTF", "BTC 동조화 +0", 0], ["오더북", "매수벽 우위 ×2.36 +8", 8], ["청산", "미미 $16K 0", 0], ["볼밴", "밴드 중단 0", 0], ["스퀴즈", "정상 +0", 0], ["ATR", "극저 변동성 +6", 6], ["레인지", "레인지 내 0", 0], ["FLOW", "Flow -11", -11], ["SURGE", "×1.58 +4", 4], ["KIMCHI", "—", 0]], "conflict": [], "onchain": null, "price": 4005.8, "p24": -0.04, "oi4": 1.3, "oi1": 0.5, "cvd": 0.394, "fr": 0.0018, "atr": 0.3, "flow": -6.7, "surge": 1.58, "ret4": -0.37, "bb_pos": 0.457, "bb_squeeze": false, "bb_just_broke": false, "rng": 0.476, "kimp": null, "liq": [0, 15500.249473599999, 6], "vwap_broke": false, "spot_fuel": false, "turnover": 59010261, "tradfi": false, "pinned": false, "rank": 17, "since": 1784555481, "since_min": 71}, {"sym": "SOLUSDT", "base": "SOL", "mark": "🟡", "why": "연료 약함 — 관찰", "alpha": 39, "g": [["흡수/이탈", "— 0", 0], ["VWAP", "VWAP 위 지지 +4", 4], ["MTF", "BTC 동조화 +0", 0], ["오더북", "균형 ×1.04 +0", 0], ["청산", "혼조 0", 0], ["볼밴", "밴드 중단 0", 0], ["스퀴즈", "정상 +0", 0], ["ATR", "극저 변동성 +6", 6], ["레인지", "레인지 내 0", 0], ["FLOW", "Flow -1", -1], ["SURGE", "×1.11 +0", 0], ["KIMCHI", "+0.22%", 0]], "conflict": [], "onchain": null, "price": 76.37, "p24": 0.0, "oi4": -0.4, "oi1": -0.1, "cvd": 0.023, "fr": -0.0011, "atr": 0.87, "flow": -0.9, "surge": 1.11, "ret4": -0.77, "bb_pos": 0.626, "bb_squeeze": false, "bb_just_broke": false, "rng": 0.572, "kimp": 0.22, "liq": [637449.6265, 537304.5960639999, 94], "vwap_broke": false, "spot_fuel": false, "turnover": 1154905095, "tradfi": false, "pinned": true, "rank": 18, "since": 1784516538, "since_min": 721}, {"sym": "APTUSDT", "base": "APT", "mark": "🟡", "why": "연료 약함 — 관찰", "alpha": 37, "g": [["흡수/이탈", "— 0", 0], ["VWAP", "VWAP 위 지지 +4", 4], ["MTF", "BTC 동조화 +0", 0], ["오더북", "매도 우위 ×0.82 -4", -4], ["청산", "미미 $1K 0", 0], ["볼밴", "밴드압축 2.9% — 대기 +4", 4], ["스퀴즈", "FR스퀴즈 중 +5", 5], ["ATR", "낮은 변동성 +3", 3], ["레인지", "레인지 내 0", 0], ["FLOW", "Flow -5", -5], ["SURGE", "×0.99 +0", 0], ["KIMCHI", "+0.12%", 0]], "conflict": [], "onchain": null, "price": 0.5873, "p24": -2.3, "oi4": 1.9, "oi1": 0.5, "cvd": 0.052, "fr": -0.0188, "atr": 1.05, "flow": -3.3, "surge": 0.99, "ret4": -1.08, "bb_pos": 0.42, "bb_squeeze": true, "bb_just_broke": false, "rng": 0.399, "kimp": 0.12, "liq": [1034.7315, 1363.73103, 6], "vwap_broke": false, "spot_fuel": false, "turnover": 17932939, "tradfi": false, "pinned": false, "rank": 19, "since": 1784379737, "since_min": 3001}, {"sym": "LINKUSDT", "base": "LINK", "mark": "🟡", "why": "연료 약함 — 관찰", "alpha": 37, "g": [["흡수/이탈", "— 0", 0], ["VWAP", "VWAP 위 지지 +4", 4], ["MTF", "BTC 동조화 +0", 0], ["오더북", "매도 우위 ×0.82 -4", -4], ["청산", "미미 $12K 0", 0], ["볼밴", "밴드 중단 0", 0], ["스퀴즈", "정상 +0", 0], ["ATR", "낮은 변동성 +3", 3], ["레인지", "레인지 내 0", 0], ["FLOW", "Flow +4", 4], ["SURGE", "×1.29 +0", 0], ["KIMCHI", "+0.35%", 0]], "conflict": [], "onchain": {"src": "cold", "score": 73, "mark": "🟢", "grade": "강한 펌프 가능성", "cold_score": 73, "cold_usd": 16441987, "cold_n": 8, "cold_wallets": 9, "cold_days": 32.1, "peak": 10.9, "accum_score": null, "accum_usd": null, "accum_wallets": null, "accum_wd": null, "accum_days": null, "conc": false}, "price": 8.395, "p24": 0.26, "oi4": -0.1, "oi1": 0.4, "cvd": 0.054, "fr": 0.0052, "atr": 1.05, "flow": 2.4, "surge": 1.29, "ret4": -1.06, "bb_pos": 0.629, "bb_squeeze": false, "bb_just_broke": false, "rng": 0.548, "kimp": 0.35, "liq": [12292.61971, 9097.722909999999, 18], "vwap_broke": false, "spot_fuel": false, "turnover": 78391745, "tradfi": false, "pinned": true, "rank": 20, "since": 1784520138, "since_min": 661}, {"sym": "REUSDT", "base": "RE", "mark": "🟡", "why": "연료 약함 — 관찰", "alpha": 34, "g": [["흡수/이탈", "ACC +14", 14], ["VWAP", "VWAP 아래 저항 -4", -4], ["MTF", "BTC 동조화 +0", 0], ["오더북", "균형 ×1.01 +0", 0], ["청산", "미미 $21K 0", 0], ["볼밴", "밴드 하단 -3", -3], ["스퀴즈", "대형 FR스퀴즈 ★ +8", 8], ["ATR", "낮은 변동성 +3", 3], ["레인지", "레인지 내 0", 0], ["FLOW", "Flow -14", -14], ["SURGE", "×0.85 +0", 0], ["KIMCHI", "+1.01%", 0]], "conflict": [], "onchain": null, "price": 0.3613, "p24": -7.71, "oi4": 5.2, "oi1": 1.1, "cvd": 0.299, "fr": -0.1393, "atr": 1.86, "flow": -8.5, "surge": 0.85, "ret4": -2.77, "bb_pos": 0.097, "bb_squeeze": false, "bb_just_broke": false, "rng": 0.138, "kimp": 1.01, "liq": [5412.2396521, 21380.4379916, 33], "vwap_broke": true, "spot_fuel": false, "turnover": 26585140, "tradfi": false, "pinned": false, "rank": 21, "since": 1784538741, "since_min": 350}, {"sym": "INJUSDT", "base": "INJ", "mark": "🟡", "why": "연료 약함 — 관찰", "alpha": 33, "g": [["흡수/이탈", "— 0", 0], ["VWAP", "VWAP 위 지지 +4", 4], ["MTF", "BTC 동조화 +0", 0], ["오더북", "균형 ×0.92 +0", 0], ["청산", "미미 $1K 0", 0], ["볼밴", "상단 접근 +6", 6], ["스퀴즈", "정상 +0", 0], ["ATR", "낮은 변동성 +3", 3], ["레인지", "레인지 상단 +6", 6], ["FLOW", "Flow -16", -16], ["SURGE", "×1.19 +0", 0], ["KIMCHI", "+0.07%", 0]], "conflict": [], "onchain": null, "price": 5.286, "p24": 3.28, "oi4": 1.6, "oi1": 0.4, "cvd": 0.056, "fr": 0.0017, "atr": 1.15, "flow": -10.0, "surge": 1.19, "ret4": -0.23, "bb_pos": 0.879, "bb_squeeze": false, "bb_just_broke": false, "rng": 0.86, "kimp": 0.07, "liq": [1342.4959999999999, 378.4452, 11], "vwap_broke": false, "spot_fuel": false, "turnover": 26985839, "tradfi": false, "pinned": false, "rank": 22, "since": 1784556201, "since_min": 59}, {"sym": "SLXUSDT", "base": "SLX", "mark": "🟡", "why": "연료 약함 — 관찰", "alpha": 32, "g": [["흡수/이탈", "— 0", 0], ["VWAP", "VWAP 위 지지 +4", 4], ["MTF", "BTC 동조화 +0", 0], ["오더북", "균형 ×0.95 +0", 0], ["청산", "미미 $2K 0", 0], ["볼밴", "밴드압축 6.5% — 대기 +4", 4], ["스퀴즈", "대형 FR스퀴즈 ★ +8", 8], ["ATR", "극저 변동성 +6", 6], ["레인지", "레인지 내 0", 0], ["FLOW", "Flow -20", -20], ["SURGE", "×0.62 +0", 0], ["KIMCHI", "+0.71%", 0]], "conflict": [], "onchain": null, "price": 0.10228, "p24": -2.76, "oi4": 3.5, "oi1": 1.2, "cvd": 0.551, "fr": -0.0724, "atr": 1.0, "flow": -12.5, "surge": 0.62, "ret4": -0.39, "bb_pos": 0.396, "bb_squeeze": true, "bb_just_broke": false, "rng": 0.231, "kimp": 0.71, "liq": [0, 2112.9723108000003, 4], "vwap_broke": false, "spot_fuel": false, "turnover": 16164738, "tradfi": false, "pinned": false, "rank": 23, "since": 1784394137, "since_min": 2761}, {"sym": "ETCUSDT", "base": "ETC", "mark": "🟡", "why": "연료 약함 — 관찰", "alpha": 30, "g": [["흡수/이탈", "— 0", 0], ["VWAP", "VWAP 위 지지 +4", 4], ["MTF", "BTC 동조화 +0", 0], ["오더북", "매도 우위 ×0.86 -4", -4], ["청산", "미미 $1K 0", 0], ["볼밴", "밴드 중단 0", 0], ["스퀴즈", "FR스퀴즈 중 +5", 5], ["ATR", "극저 변동성 +6", 6], ["레인지", "레인지 내 0", 0], ["FLOW", "Flow -11", -11], ["SURGE", "×0.52 +0", 0], ["KIMCHI", "+0.13%", 0]], "conflict": [], "onchain": null, "price": 6.833, "p24": -1.24, "oi4": 1.7, "oi1": 0.3, "cvd": 0.333, "fr": -0.0156, "atr": 0.6, "flow": -6.7, "surge": 0.52, "ret4": 0.09, "bb_pos": 0.435, "bb_squeeze": false, "bb_just_broke": false, "rng": 0.393, "kimp": 0.13, "liq": [855.26659, 0, 3], "vwap_broke": false, "spot_fuel": false, "turnover": 28367068, "tradfi": false, "pinned": false, "rank": 24, "since": 1784397737, "since_min": 2701}, {"sym": "AVAXUSDT", "base": "AVAX", "mark": "🟡", "why": "연료 약함 — 관찰", "alpha": 30, "g": [["흡수/이탈", "— 0", 0], ["VWAP", "VWAP 위 지지 +4", 4], ["MTF", "BTC 동조화 +0", 0], ["오더북", "균형 ×0.96 +0", 0], ["청산", "↓ 롱청산 우위 $67K -6", -6], ["볼밴", "밴드압축 3.4% — 대기 +4", 4], ["스퀴즈", "정상 +0", 0], ["ATR", "낮은 변동성 +3", 3], ["레인지", "레인지 상단 +6", 6], ["FLOW", "Flow -11", -11], ["SURGE", "×0.88 +0", 0], ["KIMCHI", "-0.04%", 0]], "conflict": [], "onchain": null, "price": 6.544, "p24": 1.25, "oi4": 1.5, "oi1": 0.5, "cvd": 0.017, "fr": 0.0051, "atr": 1.05, "flow": -7.0, "surge": 0.88, "ret4": -1.12, "bb_pos": 0.649, "bb_squeeze": true, "bb_just_broke": false, "rng": 0.634, "kimp": -0.04, "liq": [1185.696, 67460.5067, 5], "vwap_broke": false, "spot_fuel": false, "turnover": 76979590, "tradfi": false, "pinned": false, "rank": 25, "since": 1784523773, "since_min": 600}, {"sym": "OPUSDT", "base": "OP", "mark": "🟡", "why": "연료 약함 — 관찰", "alpha": 28, "g": [["흡수/이탈", "— 0", 0], ["VWAP", "VWAP 위 지지 +4", 4], ["MTF", "BTC 동조화 +0", 0], ["오더북", "매수 우위 ×1.34 +4", 4], ["청산", "↓ 롱청산 우위 $72K -6", -6], ["볼밴", "밴드 중단 0", 0], ["스퀴즈", "FR스퀴즈 중 +5", 5], ["ATR", "극저 변동성 +6", 6], ["레인지", "레인지 내 0", 0], ["FLOW", "Flow -15", -15], ["SURGE", "×0.99 +0", 0], ["KIMCHI", "+0.18%", 0]], "conflict": [], "onchain": null, "price": 0.0926, "p24": -1.8, "oi4": 1.0, "oi1": 0.2, "cvd": 0.27, "fr": -0.0155, "atr": 0.89, "flow": -9.6, "surge": 0.99, "ret4": -0.43, "bb_pos": 0.269, "bb_squeeze": false, "bb_just_broke": false, "rng": 0.268, "kimp": 0.18, "liq": [905.4891, 71918.83664617, 10], "vwap_broke": false, "spot_fuel": false, "turnover": 22746591, "tradfi": false, "pinned": false, "rank": 26, "since": 1784348597, "since_min": 3520}, {"sym": "ORCLUSDT", "base": "ORCL", "mark": "🟡", "why": "연료 약함 — 관찰", "alpha": 27, "g": [["흡수/이탈", "— 0", 0], ["VWAP", "VWAP 아래 저항 -4", -4], ["MTF", "BTC 동조화 +0", 0], ["오더북", "매도벽 압박 ×0.66 -8", -8], ["청산", "↓ 롱청산 우위 $50K -6", -6], ["볼밴", "밴드 하단 -3", -3], ["스퀴즈", "정상 +0", 0], ["ATR", "낮은 변동성 +3", 3], ["레인지", "레인지 내 0", 0], ["FLOW", "Flow -3", -3], ["SURGE", "×8.93 +18", 18], ["KIMCHI", "—", 0]], "conflict": [], "onchain": null, "price": 121.44, "p24": -4.49, "oi4": 5.0, "oi1": 0.6, "cvd": 0.008, "fr": 0.0, "atr": 1.73, "flow": -2.0, "surge": 8.93, "ret4": -3.79, "bb_pos": -0.077, "bb_squeeze": false, "bb_just_broke": false, "rng": 0.173, "kimp": null, "liq": [0, 49823.0029472, 6], "vwap_broke": true, "spot_fuel": false, "turnover": 15587570, "tradfi": false, "pinned": false, "rank": 27, "since": 1784557461, "since_min": 38}, {"sym": "GLWUSDT", "base": "GLW", "mark": "🟡", "why": "연료 약함 — 관찰", "alpha": 27, "g": [["흡수/이탈", "— 0", 0], ["VWAP", "VWAP 아래 저항 -4", -4], ["MTF", "BTC 동조화 +0", 0], ["오더북", "매도벽 압박 ×0.56 -8", -8], ["청산", "미미 $6K 0", 0], ["볼밴", "밴드압축 3.7% — 대기 +4", 4], ["스퀴즈", "정상 +0", 0], ["ATR", "낮은 변동성 +3", 3], ["레인지", "레인지 내 0", 0], ["FLOW", "Flow -6", -6], ["SURGE", "×2.68 +8", 8], ["KIMCHI", "—", 0]], "conflict": [], "onchain": null, "price": 156.23, "p24": -1.54, "oi4": 1.9, "oi1": 0.9, "cvd": 0.011, "fr": 0.0, "atr": 1.68, "flow": -3.7, "surge": 2.68, "ret4": -2.19, "bb_pos": 0.352, "bb_squeeze": true, "bb_just_broke": false, "rng": 0.333, "kimp": null, "liq": [0, 6446.774998999999, 4], "vwap_broke": true, "spot_fuel": false, "turnover": 20019868, "tradfi": false, "pinned": false, "rank": 28, "since": 1784485218, "since_min": 1243}, {"sym": "HANAUSDT", "base": "HANA", "mark": "🟡", "why": "연료 약함 — 관찰", "alpha": 26, "g": [["흡수/이탈", "— 0", 0], ["VWAP", "VWAP 강한 돌파 +10", 10], ["MTF", "BTC 동조화 +0", 0], ["오더북", "매도벽 압박 ×0.63 -8", -8], ["청산", "↓ 롱청산 우위 $43K -6", -6], ["볼밴", "상단 접근 +6", 6], ["스퀴즈", "롱 과열 -4", -4], ["ATR", "고변동성 -4", -4], ["레인지", "레인지 상단 +6", 6], ["FLOW", "Flow -4", -4], ["SURGE", "×0.89 +0", 0], ["KIMCHI", "—", 0]], "conflict": [], "onchain": null, "price": 0.04738, "p24": 29.0, "oi4": 9.1, "oi1": 2.3, "cvd": 0.201, "fr": 0.0677, "atr": 8.97, "flow": -2.6, "surge": 0.89, "ret4": -1.97, "bb_pos": 0.87, "bb_squeeze": false, "bb_just_broke": false, "rng": 0.652, "kimp": null, "liq": [13462.3388253, 42964.011415199995, 79], "vwap_broke": false, "spot_fuel": false, "turnover": 36887297, "tradfi": false, "pinned": false, "rank": 29, "since": 1784556021, "since_min": 62}, {"sym": "SKHYUSDT", "base": "SKHY", "mark": "🟡", "why": "연료 약함 — 관찰", "alpha": 21, "g": [["흡수/이탈", "ACC +14", 14], ["VWAP", "VWAP 아래 저항 -4", -4], ["MTF", "BTC 대비 약세 -6", -6], ["오더북", "매도벽 압박 ×0.44 -8", -8], ["청산", "↓ 롱청산 우위 $353K -6", -6], ["볼밴", "밴드 중단 0", 0], ["스퀴즈", "정상 +0", 0], ["ATR", "정상 변동성 +0", 0], ["레인지", "레인지 내 0", 0], ["FLOW", "Flow -7", -7], ["SURGE", "×2.97 +8", 8], ["KIMCHI", "—", 0]], "conflict": [], "onchain": null, "price": 155.6, "p24": 1.13, "oi4": 5.4, "oi1": -1.7, "cvd": 0.022, "fr": 0.0, "atr": 2.8, "flow": -4.2, "surge": 2.97, "ret4": -4.73, "bb_pos": 0.326, "bb_squeeze": false, "bb_just_broke": false, "rng": 0.297, "kimp": null, "liq": [33201.7881681, 352778.2263167, 60], "vwap_broke": true, "spot_fuel": false, "turnover": 759385987, "tradfi": false, "pinned": false, "rank": 30, "since": 1784554221, "since_min": 92}, {"sym": "LTCUSDT", "base": "LTC", "mark": "🟡", "why": "연료 약함 — 관찰", "alpha": 20, "g": [["흡수/이탈", "— 0", 0], ["VWAP", "VWAP 아래 저항 -4", -4], ["MTF", "BTC 동조화 +0", 0], ["오더북", "균형 ×0.90 +0", 0], ["청산", "미미 $25K 0", 0], ["볼밴", "밴드 중단 0", 0], ["스퀴즈", "정상 +0", 0], ["ATR", "극저 변동성 +6", 6], ["레인지", "레인지 내 0", 0], ["FLOW", "Flow -12", -12], ["SURGE", "×0.82 +0", 0], ["KIMCHI", "—", 0]], "conflict": [], "onchain": null, "price": 46.73, "p24": -1.35, "oi4": 1.4, "oi1": 0.1, "cvd": 0.026, "fr": 0.01, "atr": 0.85, "flow": -7.3, "surge": 0.82, "ret4": -1.39, "bb_pos": 0.264, "bb_squeeze": false, "bb_just_broke": false, "rng": 0.26, "kimp": null, "liq": [24848.336199999998, 9348.157920000001, 12], "vwap_broke": true, "spot_fuel": false, "turnover": 78014693, "tradfi": false, "pinned": false, "rank": 31, "since": 1784408538, "since_min": 2521}, {"sym": "AAVEUSDT", "base": "AAVE", "mark": "🟡", "why": "연료 약함 — 관찰", "alpha": 14, "g": [["흡수/이탈", "— 0", 0], ["VWAP", "VWAP 아래 저항 -4", -4], ["MTF", "BTC 동조화 +0", 0], ["오더북", "매수벽 우위 ×1.56 +8", 8], ["청산", "↓ 롱청산 우위 $39K -6", -6], ["볼밴", "밴드 하단 -3", -3], ["스퀴즈", "정상 +0", 0], ["ATR", "낮은 변동성 +3", 3], ["레인지", "레인지 내 0", 0], ["FLOW", "Flow -18", -18], ["SURGE", "×1.68 +4", 4], ["KIMCHI", "+0.27%", 0]], "conflict": [], "onchain": null, "price": 88.64, "p24": -1.14, "oi4": 1.6, "oi1": 0.6, "cvd": 0.022, "fr": 0.0016, "atr": 1.13, "flow": -11.2, "surge": 1.68, "ret4": -2.47, "bb_pos": 0.15, "bb_squeeze": false, "bb_just_broke": false, "rng": 0.168, "kimp": 0.27, "liq": [327.234, 39131.2097, 15], "vwap_broke": true, "spot_fuel": false, "turnover": 51131561, "tradfi": false, "pinned": false, "rank": 32, "since": 1784170952, "since_min": 6480}, {"sym": "SPYUSDT", "base": "SPY", "mark": "🟡", "why": "연료 약함 — 관찰", "alpha": 12, "g": [["흡수/이탈", "— 0", 0], ["VWAP", "VWAP 아래 저항 -4", -4], ["MTF", "BTC 동조화 +0", 0], ["오더북", "매도벽 압박 ×0.21 -8", -8], ["청산", "청산 데이터 없음 0", 0], ["볼밴", "밴드 중단 0", 0], ["스퀴즈", "정상 +0", 0], ["ATR", "극저 변동성 +6", 6], ["레인지", "레인지 내 0", 0], ["FLOW", "Flow -20", -20], ["SURGE", "×2.32 +8", 8], ["KIMCHI", "—", 0]], "conflict": [], "onchain": null, "price": 745.35, "p24": 0.29, "oi4": 2.4, "oi1": 1.5, "cvd": 0.043, "fr": 0.0, "atr": 0.27, "flow": -12.8, "surge": 2.32, "ret4": -0.27, "bb_pos": 0.62, "bb_squeeze": false, "bb_just_broke": false, "rng": 0.457, "kimp": null, "liq": null, "vwap_broke": true, "spot_fuel": false, "turnover": 24098731, "tradfi": true, "pinned": false, "rank": 33, "since": 1784163032, "since_min": 6612}, {"sym": "PROMUSDT", "base": "PROM", "mark": "🔴", "why": "수직급등 +73% — 과열 추격금지", "alpha": 84, "g": [["흡수/이탈", "— 0", 0], ["VWAP", "VWAP 강한 돌파 +10", 10], ["MTF", "BTC 대비 초강세 +12", 12], ["오더북", "균형 ×1.04 +0", 0], ["청산", "대형 숏청산 ★ $331K +8", 8], ["볼밴", "밴드 밖 진행중 — 이미 감 0", 0], ["스퀴즈", "FR스퀴즈 중 +5", 5], ["ATR", "고변동성 -4", -4], ["레인지", "고점 돌파 +4", 4], ["FLOW", "Flow +1", 1], ["SURGE", "×6.11 +18", 18], ["KIMCHI", "—", 0]], "conflict": [], "onchain": null, "price": 2.427, "p24": 72.99, "oi4": 48.3, "oi1": 28.6, "cvd": 0.971, "fr": -0.0477, "atr": 13.21, "flow": 0.5, "surge": 6.11, "ret4": 39.65, "bb_pos": 1.144, "bb_squeeze": false, "bb_just_broke": false, "rng": 0.954, "kimp": null, "liq": [330877.13339383, 150804.18754204, 433], "vwap_broke": false, "spot_fuel": false, "turnover": 112557102, "tradfi": false, "pinned": false, "rank": 34, "since": 1784558001, "since_min": 29}, {"sym": "VANRYUSDT", "base": "VANRY", "mark": "🔴", "why": "하락 중 -12% — 롱 근거 없음", "alpha": 45, "g": [["흡수/이탈", "— 0", 0], ["VWAP", "VWAP 위 지지 +4", 4], ["MTF", "BTC 동조화 +0", 0], ["오더북", "균형 ×1.06 +0", 0], ["청산", "미미 $1K 0", 0], ["볼밴", "밴드압축 10.9% — 대기 +4", 4], ["스퀴즈", "대형 FR스퀴즈 ★ +8", 8], ["ATR", "낮은 변동성 +3", 3], ["레인지", "저점 근접 -6", -6], ["FLOW", "Flow +2", 2], ["SURGE", "×0.64 +0", 0], ["KIMCHI", "—", 0]], "conflict": [], "onchain": null, "price": 0.005011, "p24": -12.07, "oi4": 1.5, "oi1": 0.1, "cvd": 0.269, "fr": -0.1619, "atr": 1.6, "flow": 1.2, "surge": 0.64, "ret4": -0.28, "bb_pos": 0.245, "bb_squeeze": true, "bb_just_broke": false, "rng": 0.075, "kimp": null, "liq": [0, 614.3039857, 5], "vwap_broke": false, "spot_fuel": false, "turnover": 26512504, "tradfi": false, "pinned": false, "rank": 35, "since": 1784559801, "since_min": 0}]}